Workbook

Sheet README
A1: RedLine Medical — Project Team and Roles
A3: Project | B3: RedLine Medical Supplies & Equipment Trading — Odoo ERP Graduation Project
A4: Project window (simulated) | B4: 2026-10-01 to 2026-10-20
A5: Business reporting period | B5: 1 May 2026 – 30 September 2026
A6: Document date | B6: 2026-10-25
A7: Status basis | B7: All 38 documentation/design/data-preparation tasks are shown at 100% as the project register for this graduation simulation. 100% means the documented deliverable exists; it does NOT mean the solution has been installed or tested on a live Odoo server.
A8: Formulas | B8: Summary sheet figures are computed with COUNTIFS/AVERAGEIFS from the Task List.
A9: Sheets | B9: Team Register · Roles and Responsibilities · Task List · Deliverable Register · Milestones · Summary (variant B adds Module Responsibility Matrix)

Sheet Team Register
A1: Member ID | B1: Name | C1: Role | D1: Primary Responsibilities | E1: Team | F1: Note
A2: TM-01 | B2: Mohamed Mahmoud Abdel Bary | C2: Team Leader - Apps, Settings, Permissions & Design | D2: App installation, general settings, companies and branches; Users, access rights, record rules and approval workflows (permissions); Solution design, GAWF, SSD and final integration of all documents; Project governance, presentation and final review | E2: Core project team | F2: Simulated project member
A3: TM-02 | B3: Mohamed Essam El-Din Youssef | C3: Sales & CRM | D3: Sales and CRM configuration: pipeline, quotations, pricelists, sales teams; Customer master data and contract pricing (preparing and uploading files); BRD, RTM and business process documentation; Sales and CRM test scenarios and business acceptance | E3: Core project team | F3: Simulated project member
A4: TM-03 | B4: Ahmed Mahmoud Mohamed | C4: Inventory & Data Upload | D4: Inventory configuration: warehouses, locations, routes, lots, serials, expiry, FEFO; Product master, opening stock and reordering rules; Data upload: preparing and importing all CSV files and data quality checks; Technical proposal, go-live plan and package validation | E4: Core project team | F4: Simulated project member
A5: TM-04 | B5: Fathy Adel Fathy | C5: Purchase, Quality & Testing | D5: Purchase configuration: vendors, RFQ and PO, approvals, vendor pricelists; Quality inspection, receipts follow-up and supplier returns; UAT execution, defect log and test documentation; User's guide, training and final quality assurance | E5: Core project team | F5: Simulated project member
A6: TM-05 | B6: Omnia Haitham | C6: Accounting & Finance | D6: Accounting configuration: chart of accounts, journals, taxes, payment terms; Invoices, bills, payments, credit notes, bank and cash; Opening balances, stock valuation and financial reconciliations; Financial proposal (FPD) and accounting test scenarios | E6: Core project team | F6: Simulated project member

Sheet Roles and Responsibilities
A1: Member ID | B1: Name | C1: Role | D1: Resp. ID | E1: Responsibility | F1: RACI
A2: TM-01 | B2: Mohamed Mahmoud Abdel Bary | C2: Team Leader - Apps, Settings, Permissions & Design | D2: R1 | E2: App installation, general settings, companies and branches | F2: Accountable owner
A3: TM-01 | B3: Mohamed Mahmoud Abdel Bary | C3: Team Leader - Apps, Settings, Permissions & Design | D3: R2 | E3: Users, access rights, record rules and approval workflows (permissions) | F3: Accountable owner
A4: TM-01 | B4: Mohamed Mahmoud Abdel Bary | C4: Team Leader - Apps, Settings, Permissions & Design | D4: R3 | E4: Solution design, GAWF, SSD and final integration of all documents | F4: Accountable owner
A5: TM-01 | B5: Mohamed Mahmoud Abdel Bary | C5: Team Leader - Apps, Settings, Permissions & Design | D5: R4 | E5: Project governance, presentation and final review | F5: Accountable owner
A6: TM-02 | B6: Mohamed Essam El-Din Youssef | C6: Sales & CRM | D6: R1 | E6: Sales and CRM configuration: pipeline, quotations, pricelists, sales teams | F6: Accountable owner
A7: TM-02 | B7: Mohamed Essam El-Din Youssef | C7: Sales & CRM | D7: R2 | E7: Customer master data and contract pricing (preparing and uploading files) | F7: Accountable owner
A8: TM-02 | B8: Mohamed Essam El-Din Youssef | C8: Sales & CRM | D8: R3 | E8: BRD, RTM and business process documentation | F8: Accountable owner
A9: TM-02 | B9: Mohamed Essam El-Din Youssef | C9: Sales & CRM | D9: R4 | E9: Sales and CRM test scenarios and business acceptance | F9: Accountable owner
A10: TM-03 | B10: Ahmed Mahmoud Mohamed | C10: Inventory & Data Upload | D10: R1 | E10: Inventory configuration: warehouses, locations, routes, lots, serials, expiry, FEFO | F10: Accountable owner
A11: TM-03 | B11: Ahmed Mahmoud Mohamed | C11: Inventory & Data Upload | D11: R2 | E11: Product master, opening stock and reordering rules | F11: Accountable owner
A12: TM-03 | B12: Ahmed Mahmoud Mohamed | C12: Inventory & Data Upload | D12: R3 | E12: Data upload: preparing and importing all CSV files and data quality checks | F12: Accountable owner
... A21: TM-05 | B21: Omnia Haitham | C21: Accounting & Finance | D21: R4 | E21: Financial proposal (FPD) and accounting test scenarios | F21: Accountable owner

Sheet Task List
A1: Task ID | B1: Phase | C1: Task | D1: Description | E1: Owner | F1: Start Date | G1: End Date | H1: Priority | I1: Deliverable | J1: Dependencies | K1: Status | L1: Progress % | M1: Acceptance Criteria
A2: T-001 | B2: 1 Initiation | C2: Project kick-off and charter | D2: Define scope, objectives, governance, branch/warehouse structure and success criteria. | E2: Mohamed Mahmoud Abdel Bary | F2: 46296 | G2: 46296 | H2: High | I2: Project charter (in SSD §1) | K2: Completed | L2: 1 | M2: Charter approved by the team leader
A3: T-002 | B3: 1 Initiation | C3: Company profile and business context | D3: Compile bilingual company profile, branches, warehouse network, product categories and customers. | E3: Mohamed Essam El-Din Youssef | F3: 46296 | G3: 46299 | H3: High | I3: Company_Profile.docx | J3: T-001 | K3: Completed | L3: 1 | M3: Profile reviewed; facts consistent with the charter
A4: T-003 | B4: 1 Initiation | C4: Project team, roles and task register | D4: Define five-member team, responsibilities, task register and milestones. | E4: Mohamed Mahmoud Abdel Bary | F4: 46296 | G4: 46296 | H4: High | I4: Project_Team_and_Roles.xlsx | J4: T-001 | K4: Completed | L4: 1 | M4: Every deliverable has an accountable owner
A5: T-004 | B5: 1 Initiation | C5: Odoo version and edition assumptions | D5: Select version/edition, list standard vs Enterprise vs custom features. | E5: Mohamed Mahmoud Abdel Bary | F5: 46296 | G5: 46296 | H5: High | I5: Assumptions (BDC §1, TPD §2) | J5: T-001 | K5: Completed | L5: 1 | M5: Version stated; unverified features flagged
A6: T-005 | B6: 2 Analysis | C6: Stakeholder analysis and interviews (simulated) | D6: Identify stakeholders, document as-is processes of the legacy/manual baseline. | E6: Mohamed Essam El-Din Youssef | F6: 46299 | G6: 46300 | H6: High | I6: BRD §3-4 | J6: T-002 | K6: Completed | L6: 1 | M6: Stakeholder register approved
A7: T-006 | B7: 2 Analysis | C7: As-is process documentation | D7: Document manual quotation, purchasing, receiving, stock-card, invoicing and collection processes. | E7: Mohamed Essam El-Din Youssef | F7: 46300 | G7: 46301 | H7: High | I7: BRD §4; GAWF §3 | J7: T-005 | K7: Completed | L7: 1 | M7: Processes validated with owners
A8: T-007 | B8: 2 Analysis | C8: Functional and non-functional requirements | D8: Write requirements with IDs, priorities, owners and acceptance criteria. | E8: Mohamed Essam El-Din Youssef | F8: 46301 | G8: 46302 | H8: High | I8: BRD §6-8 | J8: T-006 | K8: Completed | L8: 1 | M8: All requirements baselined
A9: T-008 | B9: 2 Analysis | C9: Business rules, roles and reporting requirements | D9: Capture rules for credit, FEFO, quarantine, approvals; define reports and KPIs. | E9: Mohamed Essam El-Din Youssef | F9: 46302 | G9: 46303 | H9: High | I9: BRD §9-11 | J9: T-007 | K9: Completed | L9: 1 | M9: Rules reviewed
A10: T-009 | B10: 2 Analysis | C10: Gap analysis and workflow documentation (GAWF) | D10: Compare manual baseline with proposed Odoo processes; propose solutions per gap. | E10: Mohamed Mahmoud Abdel Bary | F10: 46302 | G10: 46303 | H10: High | I10: GAWF_Gap_Analysis.docx | J10: T-006, T-007 | K10: Completed | L10: 1 | M10: Each gap has solution, owner, priority, validation
A11: T-010 | B11: 2 Analysis | C11: Requirements traceability matrix | D11: Map each requirement to process, module, feature class, owner and test case. | E11: Mohamed Essam El-Din Youssef | F11: 46302 | G11: 46303 | H11: High | I11: RTM_Traceability_Matrix.xlsx | J11: T-007 | K11: Completed | L11: 1 | M11: Every requirement linked to a test case
A12: T-011 | B12: 3 Design | C12: Solution architecture and module selection | D12: Define modules, dependencies, single-company/multi-branch model, warehouse routes. | E12: Mohamed Mahmoud Abdel Bary | F12: 46302 | G12: 46303 | H12: High | I12: SSD §2-4 | J12: T-007 | K12: Completed | L12: 1 | M12: Architecture approved
A13: T-012 | B13: 3 Design | C13: Security model and approval workflows | D13: Define roles, groups, record-rule limitations, approval thresholds and audit trail. | E13: Mohamed Mahmoud Abdel Bary | F13: 46303 | G13: 46306 | H13: High | I13: SSD §7 | J13: T-011 | K13: Completed | L13: 1 | M13: Segregation of duties documented
A14: T-013 | B14: 3 Design | C14: Process diagrams (P2P, O2C, receipt, transfers, returns, close) | D14: Create workflow diagrams for six core processes. | E14: Mohamed Mahmoud Abdel Bary | F14: 46303 | G14: 46306 | H14: High | I14: SSD §8 | J14: T-011 | K14: Completed | L14: 1 | M14: Diagrams consistent with requirements
... A46: T-045 | B46: 6 Closure | C46: ZIP packaging and validation report | D46: Package deliverables and run automated validation. | E46: Ahmed Mahmoud Mohamed | F46: 46315 | G46: 46315 | H46: High | I46: RedLine_Odoo_Graduation_Project.zip; Validation_Report | J46: T-044 | K46: Completed | L46: 1 | M46: All required files present and opening

Sheet Deliverable Register
A1: Deliverable ID | B1: Deliverable | C1: Package Path | D1: Format | E1: Accountable Owner | F1: Status | G1: Linked Tasks
A2: D-001 | B2: Project presentation (18 slides, editable) | C2: 1. Project Presentation/PowerPoint_Presentation.pptx | D2: PPTX | E2: Mohamed Mahmoud Abdel Bary | F2: Delivered (generated) | G2: T-042
A3: D-002 | B3: Project presentation (18 slides, PDF) | C3: 1. Project Presentation/PDF_Presentations.pdf | D3: PDF | E3: Mohamed Mahmoud Abdel Bary | F3: Delivered (generated) | G3: T-042
A4: D-003 | B4: Project name and scope | C4: 2. Project Preparations Documents/Project_Name_and_Scope.docx | D4: DOCX | E4: Mohamed Essam El-Din Youssef | F4: Delivered (generated) | G4: T-002, T-035
A5: D-004 | B5: Company profile (bilingual) | C5: 2. Project Preparations Documents/Company_Profile.docx | D5: DOCX | E5: Mohamed Essam El-Din Youssef | F5: Delivered (generated) | G5: T-002
A6: D-005 | B6: Project team, roles and task register | C6: 2. Project Preparations Documents/Project_Team_and_Roles.xlsx | D6: XLSX | E6: Mohamed Mahmoud Abdel Bary | F6: Delivered (generated) | G6: T-003
A7: D-006 | B7: Basic database configuration | C7: 2. Project Preparations Documents/Basic_Database_Configuration.docx | D7: DOCX | E7: Mohamed Mahmoud Abdel Bary | F7: Delivered (generated) | G7: T-033, T-004
A8: D-007 | B8: Business requirements document (BRD) | C8: 3. Project Documents/BRD_Business_Requirements.docx | D8: DOCX | E8: Mohamed Essam El-Din Youssef | F8: Delivered (generated) | G8: T-005 - T-008
A9: D-008 | B9: Requirements traceability matrix (RTM) | C9: 3. Project Documents/RTM_Traceability_Matrix.xlsx | D9: XLSX | E9: Mohamed Essam El-Din Youssef | F9: Delivered (generated) | G9: T-010, T-028
A10: D-009 | B10: Solution design document (SSD) | C10: 3. Project Documents/SSD_Solution_Design.docx | D10: DOCX | E10: Mohamed Mahmoud Abdel Bary | F10: Delivered (generated) | G10: T-011 - T-014
A11: D-010 | B11: Gap analysis and workflow documentation (GAWF) | C11: 3. Project Documents/GAWF_Gap_Analysis.docx | D11: DOCX | E11: Mohamed Mahmoud Abdel Bary | F11: Delivered (generated) | G11: T-009
A12: D-011 | B12: Technical proposal (TPD) | C12: 3. Project Documents/TPD_Technical_Proposal.docx | D12: DOCX | E12: Ahmed Mahmoud Mohamed | F12: Delivered (generated) | G12: T-015
... A24: D-023 | B24: User guide and training outline (SSD appendix, BDC section 10) | C24: 3. Project Documents/SSD_Solution_Design.docx | D24: DOCX (sections) | E24: Fathy Adel Fathy | F24: Delivered (generated) | G24: T-031, T-032

Sheet Milestones
A1: Milestone ID | B1: Milestone | C1: Target Date | D1: Owner | E1: Linked Tasks | F1: Status
A2: M-01 | B2: Project kick-off and charter approved | C2: 46296 | D2: Mohamed Mahmoud Abdel Bary | E2: T-001 | F2: Achieved
A3: M-02 | B3: Requirements baseline (BRD + RTM) | C3: 46303 | D3: Mohamed Essam El-Din Youssef | E3: T-007, T-010 | F3: Achieved
A4: M-03 | B4: Solution design and GAWF approved | C4: 46307 | D4: Mohamed Mahmoud Abdel Bary | E4: T-009, T-014 | F4: Achieved
A5: M-04 | B5: Master and transactional data prepared | C5: 46314 | D5: Ahmed Mahmoud Mohamed | E5: T-022 - T-027 | F5: Achieved
A6: M-05 | B6: UAT documented and reviewed (simulated) | C6: 46308 | D6: Fathy Adel Fathy | E6: T-029, T-030 | F6: Achieved
A7: M-06 | B7: Final review and package validated | C7: 46315 | D7: Mohamed Mahmoud Abdel Bary | E7: T-044, T-045 | F7: Achieved

Sheet Module Responsibility Matrix
A1: Odoo Area | B1: Responsible (does the work) | C1: Configuration | D1: File upload / data | E1: Journals | F1: Testing | G1: Documentation | H1: Reviewer
A2: General settings, apps, companies and branches | B2: Mohamed Mahmoud Abdel Bary | C2: Install apps, company, branches, languages | D2: Configure in Odoo; no data file | E2: Not applicable | F2: Settings review | G2: Basic_Database_Configuration §1-5 | H2: Mohamed Essam El-Din Youssef (review)
A3: Users, access rights and approvals | B3: Mohamed Mahmoud Abdel Bary | C3: Groups, record rules, approval thresholds | D3: Users created from placeholders | E3: Not applicable | F3: Access tests (SEC-001..005) | G3: UPD_Users_Privileges | H3: Omnia Haitham (review)
A4: Sales and CRM | B4: Mohamed Essam El-Din Youssef | C4: Pricelists, quotation templates, pipeline stages, sales teams | D4: Customers, pricelists, CRM sample (CSV 06, 16) | E4: Sales journal INV used with Accounting | F4: Sales and CRM test cases | G4: BRD 6.2-6.3, UDP 3 | H4: Mohamed Mahmoud Abdel Bary (review)
A5: Purchase and vendors | B5: Fathy Adel Fathy | C5: RFQ/PO flow, approvals, vendor pricelists, quality checks | D5: Vendors (CSV 07) | E5: Vendor bills BILL journal with Accounting | F5: Purchase and quality test cases | G5: BRD 6.4, UDP 4 and 6 | H5: Ahmed Mahmoud Mohamed (review)
A6: Inventory and warehouses | B6: Ahmed Mahmoud Mohamed | C6: Warehouses, locations, routes, lots/serials, expiry, FEFO, reordering | D6: Products, lots/serials, opening stock (CSV 02-05, 11-13) | E6: Stock Journal STJ, valuation accounts with Accounting | F6: Inventory test cases | G6: BRD 6.5, SSD 6, UDP 5 | H6: Fathy Adel Fathy (review)
A7: Accounting and journals | B7: Omnia Haitham | C7: Chart, taxes, payment terms, fiscal settings, analytic plan | D7: Chart, journals, mapping (CSV 08-10) | E7: All journals: INV, BILL, STJ, MISC, OPEN, banks, cash safes | F7: Accounting test cases and reconciliations | G7: BRD 6.6, SSD 9, UDP 7 | H7: Mohamed Mahmoud Abdel Bary (review)
A8: Data upload (CSV import) | B8: Ahmed Mahmoud Mohamed | C8: Import order and dependencies, error handling | D8: All CSV files (01-16) | E8: Opening entry reviewed by Omnia Haitham | F8: Counts, duplicates, keys | G8: Import_Package README | H8: Omnia Haitham (review)

Sheet Summary
A1: Project status summary (formulas)
A3: Owner | B3: Tasks | C3: Completed | D3: Avg Progress | E3: Earliest Start | F3: Latest End
A4: Mohamed Mahmoud Abdel Bary | B4: =COUNTIF('Task List'!$E$2:$E$46,A4) -> 13 | C4: =COUNTIFS('Task List'!$E$2:$E$46,A4,'Task List'!$K$2:$K$46,"Completed") -> 13 | D4: =AVERAGEIFS('Task List'!$L$2:$L$46,'Task List'!$E$2:$E$46,A4) -> 1 | E4: =_xlfn.MINIFS('Task List'!$F$2:$F$46,'Task List'!$E$2:$E$46,A4) -> 46296 | F4: =_xlfn.MAXIFS('Task List'!$G$2:$G$46,'Task List'!$E$2:$E$46,A4) -> 46315
A5: Mohamed Essam El-Din Youssef | B5: =COUNTIF('Task List'!$E$2:$E$46,A5) -> 12 | C5: =COUNTIFS('Task List'!$E$2:$E$46,A5,'Task List'!$K$2:$K$46,"Completed") -> 12 | D5: =AVERAGEIFS('Task List'!$L$2:$L$46,'Task List'!$E$2:$E$46,A5) -> 1 | E5: =_xlfn.MINIFS('Task List'!$F$2:$F$46,'Task List'!$E$2:$E$46,A5) -> 46296 | F5: =_xlfn.MAXIFS('Task List'!$G$2:$G$46,'Task List'!$E$2:$E$46,A5) -> 46313
A6: Ahmed Mahmoud Mohamed | B6: =COUNTIF('Task List'!$E$2:$E$46,A6) -> 10 | C6: =COUNTIFS('Task List'!$E$2:$E$46,A6,'Task List'!$K$2:$K$46,"Completed") -> 10 | D6: =AVERAGEIFS('Task List'!$L$2:$L$46,'Task List'!$E$2:$E$46,A6) -> 1 | E6: =_xlfn.MINIFS('Task List'!$F$2:$F$46,'Task List'!$E$2:$E$46,A6) -> 46303 | F6: =_xlfn.MAXIFS('Task List'!$G$2:$G$46,'Task List'!$E$2:$E$46,A6) -> 46315
A7: Fathy Adel Fathy | B7: =COUNTIF('Task List'!$E$2:$E$46,A7) -> 5 | C7: =COUNTIFS('Task List'!$E$2:$E$46,A7,'Task List'!$K$2:$K$46,"Completed") -> 5 | D7: =AVERAGEIFS('Task List'!$L$2:$L$46,'Task List'!$E$2:$E$46,A7) -> 1 | E7: =_xlfn.MINIFS('Task List'!$F$2:$F$46,'Task List'!$E$2:$E$46,A7) -> 46303 | F7: =_xlfn.MAXIFS('Task List'!$G$2:$G$46,'Task List'!$E$2:$E$46,A7) -> 46315
A8: Omnia Haitham | B8: =COUNTIF('Task List'!$E$2:$E$46,A8) -> 5 | C8: =COUNTIFS('Task List'!$E$2:$E$46,A8,'Task List'!$K$2:$K$46,"Completed") -> 5 | D8: =AVERAGEIFS('Task List'!$L$2:$L$46,'Task List'!$E$2:$E$46,A8) -> 1 | E8: =_xlfn.MINIFS('Task List'!$F$2:$F$46,'Task List'!$E$2:$E$46,A8) -> 46306 | F8: =_xlfn.MAXIFS('Task List'!$G$2:$G$46,'Task List'!$E$2:$E$46,A8) -> 46314
A9: All tasks | B9: =SUM(B4:B8) -> 45 | C9: =SUM(C4:C8) -> 45 | D9: =AVERAGE('Task List'!$L$2:$L$46) -> 1 | E9: =MIN(E4:E8) -> 46296 | F9: =MAX(F4:F8) -> 46315
A11: Tasks not at 100% | B11: =COUNTIF('Task List'!$L$2:$L$46,"<1") -> 0
A12: Tasks without owner | B12: =COUNTBLANK('Task List'!$E$2:$E$46) -> 0
A13: Overall completion | B13: =D9 -> 1
