Workbook

Sheet README
A1: RedLine Medical — Requirements Traceability Matrix
A3: Project | B3: RedLine Medical Supplies & Equipment Trading — Odoo ERP Graduation Project
A4: Version / date | B4: 1.0 — 2026-10-25
A5: Target Odoo version | B5: Odoo 19.0 (Enterprise edition assumed)
A6: Scope | B6: 75 requirements across Contacts, Sales, CRM, Purchase, Inventory, Accounting, Reporting, Security, Non-functional and Migration; every requirement links to at least one test case in UATD_User_Acceptance_Testing.xlsx.
A7: Validation status meaning | B7: 'Validated (simulated review)' = every linked test was reviewed against its documented scenario and the simulated data. 'Pending live Odoo verification' = at least one linked test depends on Enterprise/optional/custom features or needs real-server confirmation. Nothing has been executed on a live Odoo server.
A8: Flags | B8: 'Customization / verification needed' = Yes when the feature class is a proposed customization, Enterprise/optional app, or flagged for technical verification.
A9: Formulas | B9: Coverage columns and the Summary sheet use COUNTIF formulas.

Sheet RTM
A1: Requirement ID | B1: Requirement | C1: Business Requirement (description) | D1: Business Process | E1: Odoo Module | F1: Standard / Customization | G1: Customization or Verification Needed | H1: Responsible Stakeholder | I1: Test Case ID(s) | J1: Acceptance Criteria | K1: Validation Status | L1: Test Coverage | M1: # Test Cases
A2: CON-001 | B2: Customer master with classification | C2: Maintain customers (hospitals, clinics, labs, imaging centers, providers, retail) with bilingual names, address, contact role, payment terms, credit limit and tax-ID field. | D2: Master Data | E2: Contacts | F2: Standard (configuration) | G2: No | H2: Sales & Marketing Manager | I2: TC-001 | J2: A customer record can be created with Arabic and English name, classification tag, payment term and credit limit, and is selectable on a quotation. | K2: Validated (simulated review) | L2: =IF(I2="","NO TEST","Covered") -> Covered | M2: =LEN(I2)-LEN(SUBSTITUTE(I2,",",""))+1 -> 1
A3: CON-002 | B3: Vendor master with terms and bank | C3: Maintain vendors (manufacturers, distributors) with payment terms, paying bank, classification and a flag for verified authorization status. | D3: Master Data | E3: Contacts | F3: Standard (configuration) | G3: No | H3: Procurement Manager | I3: TC-002 | J3: A vendor record is created with payment term and bank; the vendor appears on RFQs and bills. | K3: Validated (simulated review) | L3: =IF(I3="","NO TEST","Covered") -> Covered | M3: =LEN(I3)-LEN(SUBSTITUTE(I3,",",""))+1 -> 1
A4: CON-003 | B4: Duplicate partner prevention | C4: Warn on duplicate partner name or tax ID at creation. | D4: Master Data | E4: Contacts | F4: Standard (configuration) | G4: Yes | H4: Finance & Accounting Manager | I4: TC-003 | J4: Creating a partner with an existing tax ID/name raises a warning or is blocked per setting. | K4: Pending live Odoo verification | L4: =IF(I4="","NO TEST","Covered") -> Covered | M4: =LEN(I4)-LEN(SUBSTITUTE(I4,",",""))+1 -> 1
A5: CON-004 | B5: Customer credit limit control | C5: Warn or block sales confirmation when open receivables plus the new order exceed the customer credit limit. | D5: Credit Management | E5: Contacts | F5: Customization (proposed) | G5: Yes | H5: Finance & Accounting Manager | I5: TC-004 | J5: Confirming an order that breaches the credit limit shows a warning; a hard block is available only if configured/customized. | K5: Pending live Odoo verification | L5: =IF(I5="","NO TEST","Covered") -> Covered | M5: =LEN(I5)-LEN(SUBSTITUTE(I5,",",""))+1 -> 1
A6: SAL-001 | B6: Quotation creation with pricelist | C6: Create quotations with customer pricelist/contract discount, bilingual product names and VAT 14%. | D6: Order-to-Cash | E6: Sales | F6: Standard | G6: No | H6: Sales & Marketing Manager | I6: TC-005 | J6: Quotation lines show contract-discounted ex-VAT prices and 14% VAT; PDF prints in Arabic and English. | K6: Validated (simulated review) | L6: =IF(I6="","NO TEST","Covered") -> Covered | M6: =LEN(I6)-LEN(SUBSTITUTE(I6,",",""))+1 -> 1
A7: SAL-002 | B7: Quotation approval above threshold | C7: Quotations above EGP 500,000 require approval by the Sales & Marketing Manager before confirmation. | D7: Order-to-Cash | E7: Sales | F7: Customization (proposed) | G7: Yes | H7: Sales & Marketing Manager | I7: TC-006 | J7: A quotation above the threshold cannot be confirmed until approved; approval is logged. | K7: Pending live Odoo verification | L7: =IF(I7="","NO TEST","Covered") -> Covered | M7: =LEN(I7)-LEN(SUBSTITUTE(I7,",",""))+1 -> 1
A8: SAL-003 | B8: Sales order confirmation creates delivery | C8: Confirming a sales order creates delivery orders from the correct home warehouse(s). | D8: Order-to-Cash | E8: Sales | F8: Standard | G8: No | H8: Warehouse & Logistics Manager | I8: TC-007 | J8: Confirmation creates one delivery per source warehouse with reserved lots/serials. | K8: Validated (simulated review) | L8: =IF(I8="","NO TEST","Covered") -> Covered | M8: =LEN(I8)-LEN(SUBSTITUTE(I8,",",""))+1 -> 1
A9: SAL-004 | B9: Partial delivery and backorder | C9: Allow partial deliveries with a backorder for remaining quantities and invoice on delivered quantity. | D9: Order-to-Cash | E9: Sales | F9: Standard | G9: No | H9: Warehouse & Logistics Manager | I9: TC-008 | J9: Validating a partial delivery creates a backorder; the invoice reflects delivered quantity only. | K9: Validated (simulated review) | L9: =IF(I9="","NO TEST","Covered") -> Covered | M9: =LEN(I9)-LEN(SUBSTITUTE(I9,",",""))+1 -> 1
A10: SAL-005 | B10: Branch assignment on sales documents | C10: Every sales order and invoice carries the responsible branch for reporting (analytic plan Branch). | D10: Branch Reporting | E10: Sales | F10: Standard (configuration) | G10: Yes | H10: General Manager | I10: TC-009 | J10: Sales analysis can be filtered by branch BR-NSC / BR-MAA / BR-MOH and totals agree with invoices. | K10: Pending live Odoo verification | L10: =IF(I10="","NO TEST","Covered") -> Covered | M10: =LEN(I10)-LEN(SUBSTITUTE(I10,",",""))+1 -> 1
A11: SAL-006 | B11: Contract discounts per customer | C11: Apply contract discount percentages (0–5%) per customer through pricelists. | D11: Pricing | E11: Sales | F11: Standard | G11: No | H11: Sales & Marketing Manager | I11: TC-010 | J11: Orders for a customer use that customer's discounted price automatically. | K11: Validated (simulated review) | L11: =IF(I11="","NO TEST","Covered") -> Covered | M11: =LEN(I11)-LEN(SUBSTITUTE(I11,",",""))+1 -> 1
A12: SAL-007 | B12: Warranty tracking for serial equipment | C12: Record warranty duration per product and calculate warranty end date per delivered serial number. | D12: Warranty | E12: Sales | F12: Customization (proposed) | G12: Yes | H12: Technical Service Manager | I12: TC-011 | J12: For a delivered serial number the warranty end date and status can be viewed and reported. | K12: Pending live Odoo verification | L12: =IF(I12="","NO TEST","Covered") -> Covered | M12: =LEN(I12)-LEN(SUBSTITUTE(I12,",",""))+1 -> 1
A13: SAL-008 | B13: Customer return (RMA) with credit note | C13: Receive returned goods into the quarantine warehouse and issue a credit note referencing the original invoice. | D13: Returns | E13: Sales | F13: Standard | G13: No | H13: Warehouse & Logistics Manager | I13: TC-012, TC-076 | J13: A return is received into QRT/Quarantine and a posted credit note reverses the revenue and VAT of the returned quantity. | K13: Validated (simulated review) | L13: =IF(I13="","NO TEST","Covered") -> Covered | M13: =LEN(I13)-LEN(SUBSTITUTE(I13,",",""))+1 -> 2
... A76: MIG-005 | B76: Historical transaction loading | C76: Load five months of history as completed documents or summarized entries. | D76: Data Migration | E76: Migration | F76: Customization (proposed) | G76: Yes | H76: Inventory & Data Upload | I76: TC-075 | J76: History is loaded or summarized per documented limitation; totals reconcile to the trial balance. | K76: Pending live Odoo verification | L76: =IF(I76="","NO TEST","Covered") -> Covered | M76: =LEN(I76)-LEN(SUBSTITUTE(I76,",",""))+1 -> 1

Sheet Summary
A1: Traceability summary (formulas)
A3: Total requirements | B3: =COUNTA(RTM!$A$2:$A$76) -> 75
A4: Requirements with a test case | B4: =COUNTIF(RTM!$L$2:$L$76,"Covered") -> 75
A5: Requirements without a test case | B5: =COUNTIF(RTM!$L$2:$L$76,"NO TEST") -> 0
A6: Validated (simulated review) | B6: =COUNTIF(RTM!$K$2:$K$76,"Validated (simulated review)") -> 48
A7: Pending live Odoo verification | B7: =COUNTIF(RTM!$K$2:$K$76,"Pending live Odoo verification") -> 27
A8: Flagged: customization / verification needed | B8: =COUNTIF(RTM!$G$2:$G$76,"Yes") -> 19
A9: Total test case links | B9: =SUM(RTM!$M$2:$M$76) -> 77
A12: By module
A13: Module | B13: Requirements | C13: Flagged | D13: Pending verification
A14: Contacts | B14: =COUNTIF(RTM!$E$2:$E$76,A14) -> 4 | C14: =COUNTIFS(RTM!$E$2:$E$76,A14,RTM!$G$2:$G$76,"Yes") -> 2 | D14: =COUNTIFS(RTM!$E$2:$E$76,A14,RTM!$K$2:$K$76,"Pending live Odoo verification") -> 2
A15: Sales | B15: =COUNTIF(RTM!$E$2:$E$76,A15) -> 9 | C15: =COUNTIFS(RTM!$E$2:$E$76,A15,RTM!$G$2:$G$76,"Yes") -> 3 | D15: =COUNTIFS(RTM!$E$2:$E$76,A15,RTM!$K$2:$K$76,"Pending live Odoo verification") -> 3
A16: CRM | B16: =COUNTIF(RTM!$E$2:$E$76,A16) -> 8 | C16: =COUNTIFS(RTM!$E$2:$E$76,A16,RTM!$G$2:$G$76,"Yes") -> 1 | D16: =COUNTIFS(RTM!$E$2:$E$76,A16,RTM!$K$2:$K$76,"Pending live Odoo verification") -> 1
A17: Purchase | B17: =COUNTIF(RTM!$E$2:$E$76,A17) -> 7 | C17: =COUNTIFS(RTM!$E$2:$E$76,A17,RTM!$G$2:$G$76,"Yes") -> 0 | D17: =COUNTIFS(RTM!$E$2:$E$76,A17,RTM!$K$2:$K$76,"Pending live Odoo verification") -> 0
A18: Inventory | B18: =COUNTIF(RTM!$E$2:$E$76,A18) -> 17 | C18: =COUNTIFS(RTM!$E$2:$E$76,A18,RTM!$G$2:$G$76,"Yes") -> 4 | D18: =COUNTIFS(RTM!$E$2:$E$76,A18,RTM!$K$2:$K$76,"Pending live Odoo verification") -> 4
A19: Accounting | B19: =COUNTIF(RTM!$E$2:$E$76,A19) -> 12 | C19: =COUNTIFS(RTM!$E$2:$E$76,A19,RTM!$G$2:$G$76,"Yes") -> 3 | D19: =COUNTIFS(RTM!$E$2:$E$76,A19,RTM!$K$2:$K$76,"Pending live Odoo verification") -> 5
A20: Reporting | B20: =COUNTIF(RTM!$E$2:$E$76,A20) -> 4 | C20: =COUNTIFS(RTM!$E$2:$E$76,A20,RTM!$G$2:$G$76,"Yes") -> 1 | D20: =COUNTIFS(RTM!$E$2:$E$76,A20,RTM!$K$2:$K$76,"Pending live Odoo verification") -> 1
A21: Security | B21: =COUNTIF(RTM!$E$2:$E$76,A21) -> 5 | C21: =COUNTIFS(RTM!$E$2:$E$76,A21,RTM!$G$2:$G$76,"Yes") -> 2 | D21: =COUNTIFS(RTM!$E$2:$E$76,A21,RTM!$K$2:$K$76,"Pending live Odoo verification") -> 5
A22: Non-functional | B22: =COUNTIF(RTM!$E$2:$E$76,A22) -> 4 | C22: =COUNTIFS(RTM!$E$2:$E$76,A22,RTM!$G$2:$G$76,"Yes") -> 1 | D22: =COUNTIFS(RTM!$E$2:$E$76,A22,RTM!$K$2:$K$76,"Pending live Odoo verification") -> 4
A23: Migration | B23: =COUNTIF(RTM!$E$2:$E$76,A23) -> 5 | C23: =COUNTIFS(RTM!$E$2:$E$76,A23,RTM!$G$2:$G$76,"Yes") -> 2 | D23: =COUNTIFS(RTM!$E$2:$E$76,A23,RTM!$K$2:$K$76,"Pending live Odoo verification") -> 2
A24: Total | B24: =SUM(B14:B23) -> 75 | C24: =SUM(C14:C23) -> 19 | D24: =SUM(D14:D23) -> 27
