Workbook

Sheet README
A1: RedLine Medical — Partners and Operations Cycles
A3: Company | B3: RedLine Medical Supplies & Equipment Trading
A4: Reporting period | B4: 1 May 2026 – 30 September 2026 (five completed months)
A5: Document date | B5: 2026-10-25
A6: Version | B6: 1.0 — graduation-project simulation
A7: Currency | B7: EGP. No foreign-currency transactions; imported items are priced in EGP on the vendor bill (assumption).
A8: Nature of data | B8: SIMULATED. All customers and vendors are fictional or clearly illustrative; none is a verified real customer, manufacturer or authorized distributor. Tax IDs are placeholders. Transactions were generated by a deterministic Python model; nothing was imported into a live Odoo server.
A9: VAT assumption | B9: 14% output/input VAT applied on all lines (assumed standard rate; applicability to specific medical items must be confirmed by a qualified Egyptian tax advisor).
A10: Payments | B10: Customer receipts and vendor payments are simulated through journals CIB1, NBE1 and branch cash safes; timing follows each partner's payment-behaviour profile.
A11: Cut-over | B11: Opening receivables/payables assumed nil at 1 May 2026 (simulated clean cut-over). Opening stock is carried in the Products workbook.
A12: Formulas | B12: Balances, status flags, monthly summaries and reconciliation checks are live Excel formulas. 'Ledger' values come from the simulated journal model as independent cross-checks.
A13: Sheets | B13: Customer Master · Vendor Master · Sales Orders · Sales Order Lines · CRM Pipeline · Customer Invoices and Payments · Purchase Orders · Purchase Order Lines · Vendor Bills and Payments · Delivery and Receipt Records · Customer and Supplier Returns · Monthly Business Summary · Transaction Reconciliation

Sheet Customer Master
A1: Customer ID | B1: Name (EN) | C1: الاسم (AR) | D1: Classification | E1: City | F1: Address (illustrative) | G1: Contact Role | H1: Payment Terms (days) | I1: Credit Limit (EGP) | J1: Tax ID (placeholder) | K1: Responsible Branch | L1: Contract Discount | M1: Peak Receivable Exposure (EGP, simulated) | N1: Balance 30-Sep-2026 (EGP) | O1: Credit Utilisation
A2: CUS-001 | B2: Al Salam Teaching Hospital | C2: مستشفى السلام التعليمي | D2: Hospital | E2: Cairo | F2: 12 Hospital Rd, Abbassia, Cairo | G2: Procurement Manager | H2: 30 | I2: 1000000 | J2: TAXID-PLACEHOLDER-001 | K2: BR-NSC | L2: 0.03 | M2: 497516.01 | N2: =SUMIFS('Customer Invoices and Payments'!$I$4:$I$85,'Customer Invoices and Payments'!$D$4:$D$85,A2)-SUMIFS('Customer and Supplier Returns'!$S$2:$S$12,'Customer and Supplier Returns'!$D$2:$D$12,A2,'Customer and Supplier Returns'!$B$2:$B$12,"Customer return")-SUMIFS('Customer Invoices and Payments'!$F$91:$F$152,'Customer Invoices and Payments'!$C$91:$C$152,A2) -> 124081.82 | O2: =IF(I2=0,"n/a (cash)",N2/I2) -> 0.12408182
A3: CUS-002 | B3: Nile Valley Medical Center | C3: مركز وادي النيل الطبي | D3: Hospital | E3: Giza | F3: 7 Nile Corniche St, Giza | G3: Biomedical Engineering Head | H3: 45 | I3: 2000000 | J3: TAXID-PLACEHOLDER-002 | K3: BR-MOH | L3: 0.03 | M3: 1318074.9 | N3: =SUMIFS('Customer Invoices and Payments'!$I$4:$I$85,'Customer Invoices and Payments'!$D$4:$D$85,A3)-SUMIFS('Customer and Supplier Returns'!$S$2:$S$12,'Customer and Supplier Returns'!$D$2:$D$12,A3,'Customer and Supplier Returns'!$B$2:$B$12,"Customer return")-SUMIFS('Customer Invoices and Payments'!$F$91:$F$152,'Customer Invoices and Payments'!$C$91:$C$152,A3) -> 394731.9 | O3: =IF(I3=0,"n/a (cash)",N3/I3) -> 0.19736595
A4: CUS-003 | B4: Delta Care Hospital | C4: مستشفى دلتا كير | D4: Hospital | E4: Mansoura | F4: 31 El Gomhoria St, Mansoura | G4: Purchasing Director | H4: 45 | I4: 1000000 | J4: TAXID-PLACEHOLDER-003 | K4: BR-MOH | L4: 0.02 | M4: 599612.41 | N4: =SUMIFS('Customer Invoices and Payments'!$I$4:$I$85,'Customer Invoices and Payments'!$D$4:$D$85,A4)-SUMIFS('Customer and Supplier Returns'!$S$2:$S$12,'Customer and Supplier Returns'!$D$2:$D$12,A4,'Customer and Supplier Returns'!$B$2:$B$12,"Customer return")-SUMIFS('Customer Invoices and Payments'!$F$91:$F$152,'Customer Invoices and Payments'!$C$91:$C$152,A4) -> 375535.61 | O4: =IF(I4=0,"n/a (cash)",N4/I4) -> 0.37553561
A5: CUS-004 | B5: Alexandria Coastal Hospital | C5: مستشفى الإسكندرية الساحلي | D5: Hospital | E5: Alexandria | F5: 90 Corniche Rd, Alexandria | G5: Supply Chain Manager | H5: 30 | I5: 1000000 | J5: TAXID-PLACEHOLDER-004 | K5: BR-MOH | L5: 0.03 | M5: 506351.35 | N5: =SUMIFS('Customer Invoices and Payments'!$I$4:$I$85,'Customer Invoices and Payments'!$D$4:$D$85,A5)-SUMIFS('Customer and Supplier Returns'!$S$2:$S$12,'Customer and Supplier Returns'!$D$2:$D$12,A5,'Customer and Supplier Returns'!$B$2:$B$12,"Customer return")-SUMIFS('Customer Invoices and Payments'!$F$91:$F$152,'Customer Invoices and Payments'!$C$91:$C$152,A5) -> 373141.15 | O5: =IF(I5=0,"n/a (cash)",N5/I5) -> 0.37314115
A6: CUS-005 | B6: Nasr City Family Clinics | C6: عيادات مدينة نصر العائلية | D6: Clinic | E6: Cairo | F6: 14 Abbas El Akkad St, Nasr City | G6: Clinic Administrator | H6: 15 | I6: 500000 | J6: TAXID-PLACEHOLDER-005 | K6: BR-NSC | L6: 0 | M6: 234498 | N6: =SUMIFS('Customer Invoices and Payments'!$I$4:$I$85,'Customer Invoices and Payments'!$D$4:$D$85,A6)-SUMIFS('Customer and Supplier Returns'!$S$2:$S$12,'Customer and Supplier Returns'!$D$2:$D$12,A6,'Customer and Supplier Returns'!$B$2:$B$12,"Customer return")-SUMIFS('Customer Invoices and Payments'!$F$91:$F$152,'Customer Invoices and Payments'!$C$91:$C$152,A6) -> 63966.54 | O6: =IF(I6=0,"n/a (cash)",N6/I6) -> 0.12793308
A7: CUS-006 | B7: Heliopolis Diagnostic Laboratories | C7: معامل مصر الجديدة التشخيصية | D7: Laboratory | E7: Cairo | F7: 5 Baghdad St, Heliopolis | G7: Lab Operations Manager | H7: 30 | I7: 500000 | J7: TAXID-PLACEHOLDER-006 | K7: BR-NSC | L7: 0.02 | M7: 219999.02 | N7: =SUMIFS('Customer Invoices and Payments'!$I$4:$I$85,'Customer Invoices and Payments'!$D$4:$D$85,A7)-SUMIFS('Customer and Supplier Returns'!$S$2:$S$12,'Customer and Supplier Returns'!$D$2:$D$12,A7,'Customer and Supplier Returns'!$B$2:$B$12,"Customer return")-SUMIFS('Customer Invoices and Payments'!$F$91:$F$152,'Customer Invoices and Payments'!$C$91:$C$152,A7) -> 0 | O7: =IF(I7=0,"n/a (cash)",N7/I7) -> 0
A8: CUS-007 | B8: Giza Advanced Imaging Center | C8: مركز الجيزة المتقدم للأشعة | D8: Imaging Center | E8: Giza | F8: 40 Mohy El Din Abou El Ezz St, Dokki | G8: Medical Director | H8: 60 | I8: 35000000 | J8: TAXID-PLACEHOLDER-007 | K8: BR-MOH | L8: 0 | M8: 26640332 | N8: =SUMIFS('Customer Invoices and Payments'!$I$4:$I$85,'Customer Invoices and Payments'!$D$4:$D$85,A8)-SUMIFS('Customer and Supplier Returns'!$S$2:$S$12,'Customer and Supplier Returns'!$D$2:$D$12,A8,'Customer and Supplier Returns'!$B$2:$B$12,"Customer return")-SUMIFS('Customer Invoices and Payments'!$F$91:$F$152,'Customer Invoices and Payments'!$C$91:$C$152,A8) -> 26640332 | O8: =IF(I8=0,"n/a (cash)",N8/I8) -> 0.76115233
A9: CUS-008 | B9: New Cairo Women's Health Clinic | C9: عيادة صحة المرأة بالقاهرة الجديدة | D9: Clinic | E9: New Cairo | F9: 8 South 90th St, New Cairo | G9: Clinic Manager | H9: 15 | I9: 500000 | J9: TAXID-PLACEHOLDER-008 | K9: BR-NSC | L9: 0 | M9: 244262.1 | N9: =SUMIFS('Customer Invoices and Payments'!$I$4:$I$85,'Customer Invoices and Payments'!$D$4:$D$85,A9)-SUMIFS('Customer and Supplier Returns'!$S$2:$S$12,'Customer and Supplier Returns'!$D$2:$D$12,A9,'Customer and Supplier Returns'!$B$2:$B$12,"Customer return")-SUMIFS('Customer Invoices and Payments'!$F$91:$F$152,'Customer Invoices and Payments'!$C$91:$C$152,A9) -> 71837.1 | O9: =IF(I9=0,"n/a (cash)",N9/I9) -> 0.1436742
A10: CUS-009 | B10: Upper Egypt Medical Complex | C10: مجمع صعيد مصر الطبي | D10: Hospital | E10: Assiut | F10: 3 University St, Assiut | G10: Procurement Officer | H10: 60 | I10: 1000000 | J10: TAXID-PLACEHOLDER-009 | K10: BR-NSC | L10: 0.05 | M10: 429209.15 | N10: =SUMIFS('Customer Invoices and Payments'!$I$4:$I$85,'Customer Invoices and Payments'!$D$4:$D$85,A10)-SUMIFS('Customer and Supplier Returns'!$S$2:$S$12,'Customer and Supplier Returns'!$D$2:$D$12,A10,'Customer and Supplier Returns'!$B$2:$B$12,"Customer return")-SUMIFS('Customer Invoices and Payments'!$F$91:$F$152,'Customer Invoices and Payments'!$C$91:$C$152,A10) -> 325880.12 | O10: =IF(I10=0,"n/a (cash)",N10/I10) -> 0.32588012
A11: CUS-010 | B11: Maadi Pediatric Hospital | C11: مستشفى المعادي للأطفال | D11: Hospital | E11: Cairo | F11: 21 Road 233, Degla, Maadi | G11: Head of Procurement | H11: 30 | I11: 500000 | J11: TAXID-PLACEHOLDER-010 | K11: BR-MAA | L11: 0.03 | M11: 353670.23 | N11: =SUMIFS('Customer Invoices and Payments'!$I$4:$I$85,'Customer Invoices and Payments'!$D$4:$D$85,A11)-SUMIFS('Customer and Supplier Returns'!$S$2:$S$12,'Customer and Supplier Returns'!$D$2:$D$12,A11,'Customer and Supplier Returns'!$B$2:$B$12,"Customer return")-SUMIFS('Customer Invoices and Payments'!$F$91:$F$152,'Customer Invoices and Payments'!$C$91:$C$152,A11) -> 114533.24 | O11: =IF(I11=0,"n/a (cash)",N11/I11) -> 0.22906648
A12: CUS-011 | B12: Red Sea Emergency Hospital | C12: مستشفى البحر الأحمر للطوارئ | D12: Hospital | E12: Hurghada | F12: 2 Sheraton Rd, Hurghada | G12: Hospital Administrator | H12: 45 | I12: 1500000 | J12: TAXID-PLACEHOLDER-011 | K12: BR-NSC | L12: 0.02 | M12: 887396.86 | N12: =SUMIFS('Customer Invoices and Payments'!$I$4:$I$85,'Customer Invoices and Payments'!$D$4:$D$85,A12)-SUMIFS('Customer and Supplier Returns'!$S$2:$S$12,'Customer and Supplier Returns'!$D$2:$D$12,A12,'Customer and Supplier Returns'!$B$2:$B$12,"Customer return")-SUMIFS('Customer Invoices and Payments'!$F$91:$F$152,'Customer Invoices and Payments'!$C$91:$C$152,A12) -> 786848.86 | O12: =IF(I12=0,"n/a (cash)",N12/I12) -> 0.52456591
A13: CUS-012 | B13: Zagazig Dialysis Center | C13: مركز الزقازيق لغسيل الكلى | D13: Healthcare Provider | E13: Zagazig | F13: 16 Saad Zaghloul St, Zagazig | G13: Center Manager | H13: 30 | I13: 500000 | J13: TAXID-PLACEHOLDER-012 | K13: BR-NSC | L13: 0 | M13: 379353.24 | N13: =SUMIFS('Customer Invoices and Payments'!$I$4:$I$85,'Customer Invoices and Payments'!$D$4:$D$85,A13)-SUMIFS('Customer and Supplier Returns'!$S$2:$S$12,'Customer and Supplier Returns'!$D$2:$D$12,A13,'Customer and Supplier Returns'!$B$2:$B$12,"Customer return")-SUMIFS('Customer Invoices and Payments'!$F$91:$F$152,'Customer Invoices and Payments'!$C$91:$C$152,A13) -> 261185.4 | O13: =IF(I13=0,"n/a (cash)",N13/I13) -> 0.5223708
A14: CUS-013 | B14: Walk-in Retail Customers (Maadi) | C14: عملاء التجزئة - المعادي | D14: Individual / Retail | E14: Cairo | F14: Maadi Branch retail counter | G14: Retail Counter Supervisor | H14: 0 | I14: 0 | J14: n/a (retail) | K14: BR-MAA | L14: 0 | M14: 7136.4 | N14: =SUMIFS('Customer Invoices and Payments'!$I$4:$I$85,'Customer Invoices and Payments'!$D$4:$D$85,A14)-SUMIFS('Customer and Supplier Returns'!$S$2:$S$12,'Customer and Supplier Returns'!$D$2:$D$12,A14,'Customer and Supplier Returns'!$B$2:$B$12,"Customer return")-SUMIFS('Customer Invoices and Payments'!$F$91:$F$152,'Customer Invoices and Payments'!$C$91:$C$152,A14) -> 0 | O14: =IF(I14=0,"n/a (cash)",N14/I14) -> n/a (cash)

Sheet Vendor Master
A1: Vendor ID | B1: Name (EN) | C1: الاسم (AR) | D1: Classification | E1: City / Country | F1: Address (illustrative) | G1: Contact Role | H1: Payment Terms (days) | I1: Tax ID (placeholder) | J1: Paying Bank | K1: Verified Authorized Distributor? | L1: Payable Balance 30-Sep-2026 (EGP)
A2: VEN-001 | B2: Helios Medical Systems GmbH | C2: هيليوس ميديكال سيستمز | D2: Manufacturer (illustrative) | E2: Hamburg, Germany | F2: Illustrative address, Hamburg | G2: Export Sales Manager | H2: 60 | I2: TAXID-PLACEHOLDER-001 | J2: CIB (simulated relationship) | K2: No - illustrative partner; authorization not verified | L2: =SUMIFS('Vendor Bills and Payments'!$K$4:$K$31,'Vendor Bills and Payments'!$D$4:$D$31,A2)-SUMIFS('Customer and Supplier Returns'!$S$2:$S$12,'Customer and Supplier Returns'!$D$2:$D$12,A2,'Customer and Supplier Returns'!$B$2:$B$12,"Supplier return")-SUMIFS('Vendor Bills and Payments'!$F$37:$F$54,'Vendor Bills and Payments'!$B$37:$B$54,A2) -> 2618580
A3: VEN-002 | B3: Orient Imaging Technologies Co. | C3: أورينت لتقنيات التصوير | D3: Manufacturer (illustrative) | E3: Shenzhen, China | F3: Illustrative address, Shenzhen | G3: Key Accounts Manager | H3: 60 | I3: TAXID-PLACEHOLDER-002 | J3: CIB (simulated relationship) | K3: No - illustrative partner; authorization not verified | L3: =SUMIFS('Vendor Bills and Payments'!$K$4:$K$31,'Vendor Bills and Payments'!$D$4:$D$31,A3)-SUMIFS('Customer and Supplier Returns'!$S$2:$S$12,'Customer and Supplier Returns'!$D$2:$D$12,A3,'Customer and Supplier Returns'!$B$2:$B$12,"Supplier return")-SUMIFS('Vendor Bills and Payments'!$F$37:$F$54,'Vendor Bills and Payments'!$B$37:$B$54,A3) -> 21090000
A4: VEN-003 | B4: MediPlast Industries Egypt | C4: ميدي بلاست الصناعية مصر | D4: Local Manufacturer (illustrative) | E4: 10th of Ramadan City, Egypt | F4: Industrial Zone B2, 10th of Ramadan City | G4: Sales Supervisor | H4: 30 | I4: TAXID-PLACEHOLDER-003 | J4: NBE (simulated relationship) | K4: No - illustrative partner; authorization not verified | L4: =SUMIFS('Vendor Bills and Payments'!$K$4:$K$31,'Vendor Bills and Payments'!$D$4:$D$31,A4)-SUMIFS('Customer and Supplier Returns'!$S$2:$S$12,'Customer and Supplier Returns'!$D$2:$D$12,A4,'Customer and Supplier Returns'!$B$2:$B$12,"Supplier return")-SUMIFS('Vendor Bills and Payments'!$F$37:$F$54,'Vendor Bills and Payments'!$B$37:$B$54,A4) -> 1466603.2
A5: VEN-004 | B5: Pharos Surgical Supplies | C5: فاروس للمستلزمات الجراحية | D5: Local Distributor (illustrative) | E5: Cairo, Egypt | F5: 9 Ramses St, Downtown Cairo | G5: Account Executive | H5: 30 | I5: TAXID-PLACEHOLDER-004 | J5: NBE (simulated relationship) | K5: No - illustrative partner; authorization not verified | L5: =SUMIFS('Vendor Bills and Payments'!$K$4:$K$31,'Vendor Bills and Payments'!$D$4:$D$31,A5)-SUMIFS('Customer and Supplier Returns'!$S$2:$S$12,'Customer and Supplier Returns'!$D$2:$D$12,A5,'Customer and Supplier Returns'!$B$2:$B$12,"Supplier return")-SUMIFS('Vendor Bills and Payments'!$F$37:$F$54,'Vendor Bills and Payments'!$B$37:$B$54,A5) -> 1744884
A6: VEN-005 | B6: Anatolia Biomed Distribution | C6: أناضول للتوزيع الطبي | D6: International Distributor (illustrative) | E6: Istanbul, Türkiye | F6: Illustrative address, Istanbul | G6: Regional Sales Manager | H6: 45 | I6: TAXID-PLACEHOLDER-005 | J6: CIB (simulated relationship) | K6: No - illustrative partner; authorization not verified | L6: =SUMIFS('Vendor Bills and Payments'!$K$4:$K$31,'Vendor Bills and Payments'!$D$4:$D$31,A6)-SUMIFS('Customer and Supplier Returns'!$S$2:$S$12,'Customer and Supplier Returns'!$D$2:$D$12,A6,'Customer and Supplier Returns'!$B$2:$B$12,"Supplier return")-SUMIFS('Vendor Bills and Payments'!$F$37:$F$54,'Vendor Bills and Payments'!$B$37:$B$54,A6) -> 764712
A7: VEN-006 | B7: CareTech Spare Parts Trading | C7: كير تك لتجارة قطع الغيار | D7: Local Distributor (illustrative) | E7: Cairo, Egypt | F7: 33 Shubra St, Cairo | G7: Parts Sales Coordinator | H7: 30 | I7: TAXID-PLACEHOLDER-006 | J7: NBE (simulated relationship) | K7: No - illustrative partner; authorization not verified | L7: =SUMIFS('Vendor Bills and Payments'!$K$4:$K$31,'Vendor Bills and Payments'!$D$4:$D$31,A7)-SUMIFS('Customer and Supplier Returns'!$S$2:$S$12,'Customer and Supplier Returns'!$D$2:$D$12,A7,'Customer and Supplier Returns'!$B$2:$B$12,"Supplier return")-SUMIFS('Vendor Bills and Payments'!$F$37:$F$54,'Vendor Bills and Payments'!$B$37:$B$54,A7) -> 300207.6

Sheet Sales Orders
A1: SO No | B1: Order Date | C1: Month | D1: Customer ID | E1: Customer | F1: Branch | G1: Payment Terms (days) | H1: Status (30-Sep-2026) | I1: Delivery Orders | J1: Customer Invoice
A2: SO/2026/0001 | B2: 46147 | C2: 2026-05 | D2: CUS-001 | E2: Al Salam Teaching Hospital | F2: BR-NSC | G2: 30 | H2: Fully Delivered | I2: CON/OUT/00001, EQP/OUT/00001 | J2: INV/2026/00001
A3: SO/2026/0002 | B3: 46147 | C3: 2026-05 | D3: CUS-003 | E3: Delta Care Hospital | F3: BR-MOH | G3: 45 | H3: Fully Delivered | I3: EQP/OUT/00002, SPR/OUT/00001 | J3: INV/2026/00002
A4: SO/2026/0003 | B4: 46152 | C4: 2026-05 | D4: CUS-005 | E4: Nasr City Family Clinics | F4: BR-NSC | G4: 15 | H4: Fully Delivered | I4: CON/OUT/00004, EQP/OUT/00003 | J4: INV/2026/00007
A5: SO/2026/0004 | B5: 46154 | C5: 2026-05 | D5: CUS-002 | E5: Nile Valley Medical Center | F5: BR-MOH | G5: 45 | H5: Fully Delivered | I5: CON/OUT/00002, SPR/OUT/00002 | J5: INV/2026/00005
A6: SO/2026/0005 | B6: 46154 | C6: 2026-05 | D6: CUS-013 | E6: Walk-in Retail Customers (Maadi) | F6: BR-MAA | G6: 0 | H6: Fully Delivered | I6: SPR/OUT/00003 | J6: INV/2026/00003
A7: SO/2026/0006 | B7: 46155 | C7: 2026-05 | D7: CUS-013 | E7: Walk-in Retail Customers (Maadi) | F7: BR-MAA | G7: 0 | H7: Fully Delivered | I7: CON/OUT/00003 | J7: INV/2026/00004
A8: SO/2026/0007 | B8: 46159 | C8: 2026-05 | D8: CUS-009 | E8: Upper Egypt Medical Complex | F8: BR-NSC | G8: 60 | H8: Fully Delivered | I8: CON/OUT/00006, EQP/OUT/00004, SPR/OUT/00005 | J8: INV/2026/00009
A9: SO/2026/0008 | B9: 46160 | C9: 2026-05 | D9: CUS-010 | E9: Maadi Pediatric Hospital | F9: BR-MAA | G9: 30 | H9: Fully Delivered | I9: CON/OUT/00005, SPR/OUT/00004 | J9: INV/2026/00006
A10: SO/2026/0009 | B10: 46163 | C10: 2026-05 | D10: CUS-013 | E10: Walk-in Retail Customers (Maadi) | F10: BR-MAA | G10: 0 | H10: Fully Delivered | I10: CON/OUT/00007 | J10: INV/2026/00008
A11: SO/2026/0010 | B11: 46163 | C11: 2026-05 | D11: CUS-013 | E11: Walk-in Retail Customers (Maadi) | F11: BR-MAA | G11: 0 | H11: Fully Delivered | I11: CON/OUT/00008 | J11: INV/2026/00010
A12: SO/2026/0011 | B12: 46166 | C12: 2026-05 | D12: CUS-006 | E12: Heliopolis Diagnostic Laboratories | F12: BR-NSC | G12: 30 | H12: Fully Delivered | I12: CON/OUT/00009 | J12: INV/2026/00012
A13: SO/2026/0012 | B13: 46166 | C13: 2026-05 | D13: CUS-012 | E13: Zagazig Dialysis Center | F13: BR-NSC | G13: 30 | H13: Fully Delivered | I13: CON/OUT/00010, EQP/OUT/00005, SPR/OUT/00006 | J13: INV/2026/00011
... A83: SO/2026/0082 | B83: 46289 | C83: 2026-09 | D83: CUS-013 | E83: Walk-in Retail Customers (Maadi) | F83: BR-MAA | G83: 0 | H83: Fully Delivered | I83: CON/OUT/00074, SPR/OUT/00023 | J83: INV/2026/00081
A84: SO/2026/0083 | B84: 46292 | C84: 2026-09 | D84: CUS-004 | E84: Alexandria Coastal Hospital | F84: BR-MOH | G84: 30 | H84: Confirmed - delivery scheduled after period end
A85: SO/2026/0084 | B85: 46293 | C85: 2026-09 | D85: CUS-006 | E85: Heliopolis Diagnostic Laboratories | F85: BR-NSC | G85: 30 | H85: Fully Delivered | I85: CON/OUT/00075 | J85: (invoice dated after period end)
A86: SO/2026/0085 | B86: 46294 | C86: 2026-09 | D86: CUS-007 | E86: Giza Advanced Imaging Center | F86: BR-MOH | G86: 60 | H86: Fully Delivered | I86: CON/OUT/00076, SPR/OUT/00025 | J86: INV/2026/00082
A87: SO/2026/0086 | B87: 46294 | C87: 2026-09 | D87: CUS-003 | E87: Delta Care Hospital | F87: BR-MOH | G87: 45 | H87: Confirmed - delivery scheduled after period end
A88: SO/2026/0087 | B88: 46294 | C88: 2026-09 | D88: CUS-013 | E88: Walk-in Retail Customers (Maadi) | F88: BR-MAA | G88: 0 | H88: Confirmed - delivery scheduled after period end

Sheet Sales Order Lines
A1: SO No | B1: Line | C1: Product Ref | D1: Product | E1: Ordered Qty | F1: Delivered Qty | G1: Invoiced Qty | H1: UoM | I1: Unit Price (EGP, ex-VAT) | J1: Backorder Qty | K1: Delivered Net (EGP) | L1: Ordered Net (EGP)
A2: SO/2026/0001 | B2: 1 | C2: EQ-SUR-001 | D2: Surgical Instrument Set (General Surgery, 120 pcs) | E2: 3 | F2: 3 | G2: 3 | H2: Set | I2: 35405 | J2: =E2-F2 -> 0 | K2: =F2*I2 -> 106215 | L2: =E2*I2 -> 106215
A3: SO/2026/0001 | B3: 2 | C3: CN-MSK-001 | D3: Surgical Face Mask 3-Ply (Box of 50) | E3: 494 | F3: 494 | G3: 494 | H3: Box | I3: 56.26 | J3: =E3-F3 -> 0 | K3: =F3*I3 -> 27792.44 | L3: =E3*I3 -> 27792.44
A4: SO/2026/0002 | B4: 1 | C4: EQ-INF-001 | D4: Infusion Pump (Volumetric) | E4: 2 | F4: 2 | G4: 2 | H4: Unit | I4: 23520 | J4: =E4-F4 -> 0 | K4: =F4*I4 -> 47040 | L4: =E4*I4 -> 47040
A5: SO/2026/0002 | B5: 2 | C5: SP-BAT-001 | D5: Patient Monitor Li-ion Battery Pack | E5: 3 | F5: 3 | G5: 3 | H5: Unit | I5: 4998 | J5: =E5-F5 -> 0 | K5: =F5*I5 -> 14994 | L5: =E5*I5 -> 14994
A6: SO/2026/0002 | B6: 3 | C6: EQ-MON-001 | D6: Patient Monitor (Multi-parameter, 12") | E6: 3 | F6: 3 | G6: 3 | H6: Unit | I6: 53410 | J6: =E6-F6 -> 0 | K6: =F6*I6 -> 160230 | L6: =E6*I6 -> 160230
A7: SO/2026/0003 | B7: 1 | C7: CN-SYR-001 | D7: Disposable Syringe 5 ml (Box of 100) | E7: 134 | F7: 134 | G7: 134 | H7: Box | I7: 195 | J7: =E7-F7 -> 0 | K7: =F7*I7 -> 26130 | L7: =E7*I7 -> 26130
A8: SO/2026/0003 | B8: 2 | C8: EQ-ECG-001 | D8: ECG Machine (12-Channel) | E8: 2 | F8: 2 | G8: 2 | H8: Unit | I8: 47500 | J8: =E8-F8 -> 0 | K8: =F8*I8 -> 95000 | L8: =E8*I8 -> 95000
A9: SO/2026/0004 | B9: 1 | C9: SP-GSK-001 | D9: Autoclave Door Gasket | E9: 1 | F9: 1 | G9: 1 | H9: Unit | I9: 4074 | J9: =E9-F9 -> 0 | K9: =F9*I9 -> 4074 | L9: =E9*I9 -> 4074
A10: SO/2026/0004 | B10: 2 | C10: CN-MSK-001 | D10: Surgical Face Mask 3-Ply (Box of 50) | E10: 240 | F10: 240 | G10: 240 | H10: Box | I10: 56.26 | J10: =E10-F10 -> 0 | K10: =F10*I10 -> 13502.4 | L10: =E10*I10 -> 13502.4
A11: SO/2026/0004 | B11: 3 | C11: CN-GLV-001 | D11: Nitrile Examination Gloves, Medium (Box of 100) | E11: 247 | F11: 247 | G11: 247 | H11: Box | I11: 223.1 | J11: =E11-F11 -> 0 | K11: =F11*I11 -> 55105.7 | L11: =E11*I11 -> 55105.7
A12: SO/2026/0005 | B12: 1 | C12: SP-SPO-001 | D12: SpO2 Sensor, Adult Reusable | E12: 2 | F12: 2 | G12: 2 | H12: Unit | I12: 1750 | J12: =E12-F12 -> 0 | K12: =F12*I12 -> 3500 | L12: =E12*I12 -> 3500
A13: SO/2026/0006 | B13: 1 | C13: CN-GLV-001 | D13: Nitrile Examination Gloves, Medium (Box of 100) | E13: 12 | F13: 12 | G13: 12 | H13: Box | I13: 230 | J13: =E13-F13 -> 0 | K13: =F13*I13 -> 2760 | L13: =E13*I13 -> 2760
... A207: SO/2026/0087 | B207: 2 | C207: CN-SYR-001 | D207: Disposable Syringe 5 ml (Box of 100) | E207: 11 | F207: 0 | G207: 0 | H207: Box | I207: 195 | J207: =E207-F207 -> 11 | K207: =F207*I207 -> 0 | L207: =E207*I207 -> 2145

Sheet CRM Pipeline
A1: CRM pipeline (simulated): leads and opportunities, 1 May - 30 Sep 2026
A2: Won opportunities link to the simulated sales orders; open opportunities have expected close dates after the period end. Retail counter sales (CUS-013) do not use the pipeline.
A3: Opportunity ID | B3: Opportunity | C3: Customer ID | D3: Customer | E3: Sales Team (branch) | F3: Salesperson | G3: Lead Source | H3: Stage | I3: Probability % | J3: Expected Revenue (EGP, ex-VAT) | K3: Weighted Revenue (EGP) | L3: Created | M3: Closed / Expected Close | N3: Lost Reason | O3: Linked SO | P3: Linked SO Ordered Net (EGP) | Q3: Variance to SO (EGP)
A4: OPP-0001 | B4: Al Salam Teaching Hospital - Surgical Instrument Set (General Surgery, 120 pcs) | C4: CUS-001 | D4: Al Salam Teaching Hospital | E4: Nasr City Sales Team | F4: sales.nsc (placeholder) | G4: Existing customer | H4: Won | I4: 100 | J4: 134007.44 | K4: =J4*I4/100 -> 134007.44 | L4: 46143 | M4: 46147 | O4: SO/2026/0001 | P4: =SUMIFS('Sales Order Lines'!$L$2:$L$207,'Sales Order Lines'!$A$2:$A$207,O4) -> 134007.44 | Q4: =IF(O4="",0,P4-J4) -> 0
A5: OPP-0002 | B5: Nile Valley Medical Center - Autoclave Door Gasket | C5: CUS-002 | D5: Nile Valley Medical Center | E5: Mohandeseen Sales Team | F5: sales.moh (placeholder) | G5: Hospital tender | H5: Won | I5: 100 | J5: 72682.1 | K5: =J5*I5/100 -> 72682.1 | L5: 46143 | M5: 46154 | O5: SO/2026/0004 | P5: =SUMIFS('Sales Order Lines'!$L$2:$L$207,'Sales Order Lines'!$A$2:$A$207,O5) -> 72682.1 | Q5: =IF(O5="",0,P5-J5) -> 0
A6: OPP-0003 | B6: Nile Valley Medical Center - Infusion Pump (Volumetric) | C6: CUS-002 | D6: Nile Valley Medical Center | E6: Mohandeseen Sales Team | F6: sales.moh (placeholder) | G6: Website inquiry | H6: Won | I6: 100 | J6: 113679.15 | K6: =J6*I6/100 -> 113679.15 | L6: 46143 | M6: 46180 | O6: SO/2026/0020 | P6: =SUMIFS('Sales Order Lines'!$L$2:$L$207,'Sales Order Lines'!$A$2:$A$207,O6) -> 113679.15 | Q6: =IF(O6="",0,P6-J6) -> 0
A7: OPP-0004 | B7: Delta Care Hospital - Infusion Pump (Volumetric) | C7: CUS-003 | D7: Delta Care Hospital | E7: Mohandeseen Sales Team | F7: sales.moh (placeholder) | G7: Hospital tender | H7: Won | I7: 100 | J7: 222264 | K7: =J7*I7/100 -> 222264 | L7: 46143 | M7: 46147 | O7: SO/2026/0002 | P7: =SUMIFS('Sales Order Lines'!$L$2:$L$207,'Sales Order Lines'!$A$2:$A$207,O7) -> 222264 | Q7: =IF(O7="",0,P7-J7) -> 0
A8: OPP-0005 | B8: Alexandria Coastal Hospital - Infusion Pump (Volumetric) | C8: CUS-004 | D8: Alexandria Coastal Hospital | E8: Mohandeseen Sales Team | F8: sales.moh (placeholder) | G8: Referral | H8: Won | I8: 100 | J8: 90803.64 | K8: =J8*I8/100 -> 90803.64 | L8: 46143 | M8: 46170 | O8: SO/2026/0016 | P8: =SUMIFS('Sales Order Lines'!$L$2:$L$207,'Sales Order Lines'!$A$2:$A$207,O8) -> 90803.64 | Q8: =IF(O8="",0,P8-J8) -> 0
A9: OPP-0006 | B9: Nasr City Family Clinics - Disposable Syringe 5 ml (Box of 100) | C9: CUS-005 | D9: Nasr City Family Clinics | E9: Nasr City Sales Team | F9: sales.nsc (placeholder) | G9: Hospital tender | H9: Won | I9: 100 | J9: 121130 | K9: =J9*I9/100 -> 121130 | L9: 46143 | M9: 46152 | O9: SO/2026/0003 | P9: =SUMIFS('Sales Order Lines'!$L$2:$L$207,'Sales Order Lines'!$A$2:$A$207,O9) -> 121130 | Q9: =IF(O9="",0,P9-J9) -> 0
A10: OPP-0007 | B10: Nasr City Family Clinics - Disposable Syringe 5 ml (Box of 100) | C10: CUS-005 | D10: Nasr City Family Clinics | E10: Nasr City Sales Team | F10: sales.nsc (placeholder) | G10: Referral | H10: Won | I10: 100 | J10: 48150 | K10: =J10*I10/100 -> 48150 | L10: 46143 | M10: 46196 | O10: SO/2026/0028 | P10: =SUMIFS('Sales Order Lines'!$L$2:$L$207,'Sales Order Lines'!$A$2:$A$207,O10) -> 48150 | Q10: =IF(O10="",0,P10-J10) -> 0
A11: OPP-0008 | B11: Heliopolis Diagnostic Laboratories - Nitrile Examination Gloves, Medium (Box of 100) | C11: CUS-006 | D11: Heliopolis Diagnostic Laboratories | E11: Nasr City Sales Team | F11: sales.nsc (placeholder) | G11: Referral | H11: Won | I11: 100 | J11: 85431.5 | K11: =J11*I11/100 -> 85431.5 | L11: 46143 | M11: 46166 | O11: SO/2026/0011 | P11: =SUMIFS('Sales Order Lines'!$L$2:$L$207,'Sales Order Lines'!$A$2:$A$207,O11) -> 85431.5 | Q11: =IF(O11="",0,P11-J11) -> 0
A12: OPP-0009 | B12: Upper Egypt Medical Complex - ECG Electrodes (Pack of 50) | C12: CUS-009 | D12: Upper Egypt Medical Complex | E12: Nasr City Sales Team | F12: sales.nsc (placeholder) | G12: Email inquiry | H12: Won | I12: 100 | J12: 90639.5 | K12: =J12*I12/100 -> 90639.5 | L12: 46143 | M12: 46159 | O12: SO/2026/0007 | P12: =SUMIFS('Sales Order Lines'!$L$2:$L$207,'Sales Order Lines'!$A$2:$A$207,O12) -> 90639.5 | Q12: =IF(O12="",0,P12-J12) -> 0
A13: OPP-0010 | B13: Maadi Pediatric Hospital - ECG Electrodes (Pack of 50) | C13: CUS-010 | D13: Maadi Pediatric Hospital | E13: Maadi Sales Team | F13: retail.maadi (placeholder) | G13: Referral | H13: Won | I13: 100 | J13: 69005.8 | K13: =J13*I13/100 -> 69005.8 | L13: 46143 | M13: 46160 | O13: SO/2026/0008 | P13: =SUMIFS('Sales Order Lines'!$L$2:$L$207,'Sales Order Lines'!$A$2:$A$207,O13) -> 69005.8 | Q13: =IF(O13="",0,P13-J13) -> 0
A14: OPP-0011 | B14: Maadi Pediatric Hospital - Patient Monitor (Multi-parameter, 12") | C14: CUS-010 | D14: Maadi Pediatric Hospital | E14: Maadi Sales Team | F14: retail.maadi (placeholder) | G14: Exhibition / conference | H14: Won | I14: 100 | J14: 103984 | K14: =J14*I14/100 -> 103984 | L14: 46143 | M14: 46181 | O14: SO/2026/0022 | P14: =SUMIFS('Sales Order Lines'!$L$2:$L$207,'Sales Order Lines'!$A$2:$A$207,O14) -> 103984 | Q14: =IF(O14="",0,P14-J14) -> 0
A15: OPP-0012 | B15: Red Sea Emergency Hospital - Nitrile Examination Gloves, Medium (Box of 100) | C15: CUS-011 | D15: Red Sea Emergency Hospital | E15: Nasr City Sales Team | F15: sales.nsc (placeholder) | G15: Email inquiry | H15: Won | I15: 100 | J15: 56448 | K15: =J15*I15/100 -> 56448 | L15: 46143 | M15: 46170 | O15: SO/2026/0015 | P15: =SUMIFS('Sales Order Lines'!$L$2:$L$207,'Sales Order Lines'!$A$2:$A$207,O15) -> 56448 | Q15: =IF(O15="",0,P15-J15) -> 0
... A18: OPP-0015 | B18: New Cairo Women's Health Clinic - Gauze Swabs & Dressings Pack | C18: CUS-008 | D18: New Cairo Women's Health Clinic | E18: Nasr City Sales Team | F18: sales.nsc (placeholder) | G18: Website inquiry | H18: Won | I18: 100 | J18: 87170 | K18: =J18*I18/100 -> 87170 | L18: 46148 | M18: 46169 | O18: SO/2026/0014 | P18: =SUMIFS('Sales Order Lines'!$L$2:$L$207,'Sales Order Lines'!$A$2:$A$207,O18) -> 87170 | Q18: =IF(O18="",0,P18-J18) -> 0
A19: OPP-0016 | B19: Upper Egypt Medical Complex - Patient Monitor Li-ion Battery Pack | C19: CUS-009 | D19: Upper Egypt Medical Complex | E19: Nasr City Sales Team | F19: sales.nsc (placeholder) | G19: Hospital tender | H19: Lost | I19: 0 | J19: 3768900 | K19: =J19*I19/100 -> 0 | L19: 46150 | M19: 46169 | N19: Competitor selected | P19: 0 | Q19: =IF(O19="",0,P19-J19) -> 0
A20: OPP-0017 | B20: Giza Advanced Imaging Center - ECG Electrodes (Pack of 50) | C20: CUS-007 | D20: Giza Advanced Imaging Center | E20: Mohandeseen Sales Team | F20: sales.moh (placeholder) | G20: Email inquiry | H20: Won | I20: 100 | J20: 33430 | K20: =J20*I20/100 -> 33430 | L20: 46153 | M20: 46168 | O20: SO/2026/0013 | P20: =SUMIFS('Sales Order Lines'!$L$2:$L$207,'Sales Order Lines'!$A$2:$A$207,O20) -> 33430 | Q20: =IF(O20="",0,P20-J20) -> 0
A21: OPP-0018 | B21: Zagazig Dialysis Center - Oxygen Concentrator (5 L/min) | C21: CUS-012 | D21: Zagazig Dialysis Center | E21: Nasr City Sales Team | F21: sales.nsc (placeholder) | G21: Exhibition / conference | H21: Lost | I21: 0 | J21: 38000 | K21: =J21*I21/100 -> 0 | L21: 46154 | M21: 46177 | N21: Delivery time too long | P21: 0 | Q21: =IF(O21="",0,P21-J21) -> 0
A22: OPP-0019 | B22: New Cairo Women's Health Clinic - ECG Machine (12-Channel) | C22: CUS-008 | D22: New Cairo Women's Health Clinic | E22: Nasr City Sales Team | F22: sales.nsc (placeholder) | G22: Exhibition / conference | H22: Lost | I22: 0 | J22: 95000 | K22: =J22*I22/100 -> 0 | L22: 46155 | M22: 46184 | N22: Price too high | P22: 0 | Q22: =IF(O22="",0,P22-J22) -> 0
A23: OPP-0020 | B23: Giza Advanced Imaging Center - Nitrile Examination Gloves, Medium (Box of 100) | C23: CUS-007 | D23: Giza Advanced Imaging Center | E23: Mohandeseen Sales Team | F23: sales.moh (placeholder) | G23: Existing customer | H23: Lost | I23: 0 | J23: 129720 | K23: =J23*I23/100 -> 0 | L23: 46158 | M23: 46192 | N23: Tender cancelled | P23: 0 | Q23: =IF(O23="",0,P23-J23) -> 0
A24: OPP-0021 | B24: Red Sea Emergency Hospital - Surgical Instrument Set (General Surgery, 120 pcs) | C24: CUS-011 | D24: Red Sea Emergency Hospital | E24: Nasr City Sales Team | F24: sales.nsc (placeholder) | G24: Website inquiry | H24: Won | I24: 100 | J24: 220500 | K24: =J24*I24/100 -> 220500 | L24: 46159 | M24: 46175 | O24: SO/2026/0017 | P24: =SUMIFS('Sales Order Lines'!$L$2:$L$207,'Sales Order Lines'!$A$2:$A$207,O24) -> 220500 | Q24: =IF(O24="",0,P24-J24) -> 0
A25: OPP-0022 | B25: Upper Egypt Medical Complex - Patient Monitor Li-ion Battery Pack | C25: CUS-009 | D25: Upper Egypt Medical Complex | E25: Nasr City Sales Team | F25: sales.nsc (placeholder) | G25: Existing customer | H25: Lost | I25: 0 | J25: 2381700 | K25: =J25*I25/100 -> 0 | L25: 46160 | M25: 46184 | N25: Competitor selected | P25: 0 | Q25: =IF(O25="",0,P25-J25) -> 0
A26: OPP-0023 | B26: New Cairo Women's Health Clinic - Disposable Syringe 5 ml (Box of 100) | C26: CUS-008 | D26: New Cairo Women's Health Clinic | E26: Nasr City Sales Team | F26: sales.nsc (placeholder) | G26: Hospital tender | H26: Won | I26: 100 | J26: 127095 | K26: =J26*I26/100 -> 127095 | L26: 46163 | M26: 46189 | O26: SO/2026/0025 | P26: =SUMIFS('Sales Order Lines'!$L$2:$L$207,'Sales Order Lines'!$A$2:$A$207,O26) -> 127095 | Q26: =IF(O26="",0,P26-J26) -> 0
A27: OPP-0024 | B27: Red Sea Emergency Hospital - Surgical Face Mask 3-Ply (Box of 50) | C27: CUS-011 | D27: Red Sea Emergency Hospital | E27: Nasr City Sales Team | F27: sales.nsc (placeholder) | G27: Email inquiry | H27: Won | I27: 100 | J27: 115565.52 | K27: =J27*I27/100 -> 115565.52 | L27: 46163 | M27: 46217 | O27: SO/2026/0042 | P27: =SUMIFS('Sales Order Lines'!$L$2:$L$207,'Sales Order Lines'!$A$2:$A$207,O27) -> 115565.52 | Q27: =IF(O27="",0,P27-J27) -> 0
A28: OPP-0025 | B28: Heliopolis Diagnostic Laboratories - Nitrile Examination Gloves, Medium (Box of 100) | C28: CUS-006 | D28: Heliopolis Diagnostic Laboratories | E28: Nasr City Sales Team | F28: sales.nsc (placeholder) | G28: Referral | H28: Won | I28: 100 | J28: 79002.7 | K28: =J28*I28/100 -> 79002.7 | L28: 46168 | M28: 46180 | O28: SO/2026/0019 | P28: =SUMIFS('Sales Order Lines'!$L$2:$L$207,'Sales Order Lines'!$A$2:$A$207,O28) -> 79002.7 | Q28: =IF(O28="",0,P28-J28) -> 0
A29: OPP-0026 | B29: Giza Advanced Imaging Center - Surgical Face Mask 3-Ply (Box of 50) | C29: CUS-007 | D29: Giza Advanced Imaging Center | E29: Mohandeseen Sales Team | F29: sales.moh (placeholder) | G29: Exhibition / conference | H29: Won | I29: 100 | J29: 36110 | K29: =J29*I29/100 -> 36110 | L29: 46168 | M29: 46201 | O29: SO/2026/0030 | P29: =SUMIFS('Sales Order Lines'!$L$2:$L$207,'Sales Order Lines'!$A$2:$A$207,O29) -> 36110 | Q29: =IF(O29="",0,P29-J29) -> 0
A30: OPP-0027 | B30: Upper Egypt Medical Complex - Disposable Syringe 5 ml (Box of 100) | C30: CUS-009 | D30: Upper Egypt Medical Complex | E30: Nasr City Sales Team | F30: sales.nsc (placeholder) | G30: Exhibition / conference | H30: Won | I30: 100 | J30: 72318.75 | K30: =J30*I30/100 -> 72318.75 | L30: 46168 | M30: 46205 | O30: SO/2026/0033 | P30: =SUMIFS('Sales Order Lines'!$L$2:$L$207,'Sales Order Lines'!$A$2:$A$207,O30) -> 72318.75 | Q30: =IF(O30="",0,P30-J30) -> 0
A31: OPP-0028 | B31: Alexandria Coastal Hospital - Gauze Swabs & Dressings Pack | C31: CUS-004 | D31: Alexandria Coastal Hospital | E31: Mohandeseen Sales Team | F31: sales.moh (placeholder) | G31: Exhibition / conference | H31: Won | I31: 100 | J31: 278778 | K31: =J31*I31/100 -> 278778 | L31: 46170 | M31: 46197 | O31: SO/2026/0029 | P31: =SUMIFS('Sales Order Lines'!$L$2:$L$207,'Sales Order Lines'!$A$2:$A$207,O31) -> 278778 | Q31: =IF(O31="",0,P31-J31) -> 0
A32: OPP-0029 | B32: Red Sea Emergency Hospital - SpO2 Sensor, Adult Reusable | C32: CUS-011 | D32: Red Sea Emergency Hospital | E32: Nasr City Sales Team | F32: sales.nsc (placeholder) | G32: Website inquiry | H32: Lost | I32: 0 | J32: 1037750 | K32: =J32*I32/100 -> 0 | L32: 46171 | M32: 46188 | N32: Competitor selected | P32: 0 | Q32: =IF(O32="",0,P32-J32) -> 0
A33: OPP-0030 | B33: Al Salam Teaching Hospital - ECG Machine (12-Channel) | C33: CUS-001 | D33: Al Salam Teaching Hospital | E33: Nasr City Sales Team | F33: sales.nsc (placeholder) | G33: Email inquiry | H33: Won | I33: 100 | J33: 54484.9 | K33: =J33*I33/100 -> 54484.9 | L33: 46174 | M33: 46201 | O33: SO/2026/0031 | P33: =SUMIFS('Sales Order Lines'!$L$2:$L$207,'Sales Order Lines'!$A$2:$A$207,O33) -> 54484.9 | Q33: =IF(O33="",0,P33-J33) -> 0
A34: OPP-0031 | B34: Giza Advanced Imaging Center - ECG Electrodes (Pack of 50) | C34: CUS-007 | D34: Giza Advanced Imaging Center | E34: Mohandeseen Sales Team | F34: sales.moh (placeholder) | G34: Hospital tender | H34: Won | I34: 100 | J34: 20060 | K34: =J34*I34/100 -> 20060 | L34: 46175 | M34: 46226 | O34: SO/2026/0047 | P34: =SUMIFS('Sales Order Lines'!$L$2:$L$207,'Sales Order Lines'!$A$2:$A$207,O34) -> 20060 | Q34: =IF(O34="",0,P34-J34) -> 0
A35: OPP-0032 | B35: Alexandria Coastal Hospital - Ultrasound System (Colour Doppler) | C35: CUS-004 | D35: Alexandria Coastal Hospital | E35: Mohandeseen Sales Team | F35: sales.moh (placeholder) | G35: Exhibition / conference | H35: Lost | I35: 0 | J35: 835000 | K35: =J35*I35/100 -> 0 | L35: 46178 | M35: 46205 | N35: Price too high | P35: 0 | Q35: =IF(O35="",0,P35-J35) -> 0
A36: OPP-0033 | B36: Upper Egypt Medical Complex - Oxygen Concentrator (5 L/min) | C36: CUS-009 | D36: Upper Egypt Medical Complex | E36: Nasr City Sales Team | F36: sales.nsc (placeholder) | G36: Hospital tender | H36: Won | I36: 100 | J36: 80104 | K36: =J36*I36/100 -> 80104 | L36: 46179 | M36: 46202 | O36: SO/2026/0032 | P36: =SUMIFS('Sales Order Lines'!$L$2:$L$207,'Sales Order Lines'!$A$2:$A$207,O36) -> 80104 | Q36: =IF(O36="",0,P36-J36) -> 0
A37: OPP-0034 | B37: Al Salam Teaching Hospital - Disposable Syringe 5 ml (Box of 100) | C37: CUS-001 | D37: Al Salam Teaching Hospital | E37: Nasr City Sales Team | F37: sales.nsc (placeholder) | G37: Referral | H37: Won | I37: 100 | J37: 80155.95 | K37: =J37*I37/100 -> 80155.95 | L37: 46180 | M37: 46223 | O37: SO/2026/0045 | P37: =SUMIFS('Sales Order Lines'!$L$2:$L$207,'Sales Order Lines'!$A$2:$A$207,O37) -> 80155.95 | Q37: =IF(O37="",0,P37-J37) -> 0
A38: OPP-0035 | B38: New Cairo Women's Health Clinic - Disposable Syringe 5 ml (Box of 100) | C38: CUS-008 | D38: New Cairo Women's Health Clinic | E38: Nasr City Sales Team | F38: sales.nsc (placeholder) | G38: Email inquiry | H38: Won | I38: 100 | J38: 72905 | K38: =J38*I38/100 -> 72905 | L38: 46180 | M38: 46215 | O38: SO/2026/0040 | P38: =SUMIFS('Sales Order Lines'!$L$2:$L$207,'Sales Order Lines'!$A$2:$A$207,O38) -> 72905 | Q38: =IF(O38="",0,P38-J38) -> 0
A39: OPP-0036 | B39: Delta Care Hospital - Oxygen Concentrator (5 L/min) | C39: CUS-003 | D39: Delta Care Hospital | E39: Mohandeseen Sales Team | F39: sales.moh (placeholder) | G39: Exhibition / conference | H39: Won | I39: 100 | J39: 114954 | K39: =J39*I39/100 -> 114954 | L39: 46182 | M39: 46189 | O39: SO/2026/0026 | P39: =SUMIFS('Sales Order Lines'!$L$2:$L$207,'Sales Order Lines'!$A$2:$A$207,O39) -> 114954 | Q39: =IF(O39="",0,P39-J39) -> 0
A40: OPP-0037 | B40: Nasr City Family Clinics - Infusion Pump (Volumetric) | C40: CUS-005 | D40: Nasr City Family Clinics | E40: Nasr City Sales Team | F40: sales.nsc (placeholder) | G40: Website inquiry | H40: Won | I40: 100 | J40: 159300 | K40: =J40*I40/100 -> 159300 | L40: 46185 | M40: 46211 | O40: SO/2026/0038 | P40: =SUMIFS('Sales Order Lines'!$L$2:$L$207,'Sales Order Lines'!$A$2:$A$207,O40) -> 159300 | Q40: =IF(O40="",0,P40-J40) -> 0
A41: OPP-0038 | B41: Giza Advanced Imaging Center - Hospital Bed (Electric, 3-Function) | C41: CUS-007 | D41: Giza Advanced Imaging Center | E41: Mohandeseen Sales Team | F41: sales.moh (placeholder) | G41: Existing customer | H41: Lost | I41: 0 | J41: 124500 | K41: =J41*I41/100 -> 0 | L41: 46185 | M41: 46201 | N41: Tender cancelled | P41: 0 | Q41: =IF(O41="",0,P41-J41) -> 0
A42: OPP-0039 | B42: Zagazig Dialysis Center - IV Infusion Set (Box of 25) | C42: CUS-012 | D42: Zagazig Dialysis Center | E42: Nasr City Sales Team | F42: sales.nsc (placeholder) | G42: Email inquiry | H42: Won | I42: 100 | J42: 176460 | K42: =J42*I42/100 -> 176460 | L42: 46187 | M42: 46208 | O42: SO/2026/0034 | P42: =SUMIFS('Sales Order Lines'!$L$2:$L$207,'Sales Order Lines'!$A$2:$A$207,O42) -> 176460 | Q42: =IF(O42="",0,P42-J42) -> 0
A43: OPP-0040 | B43: Heliopolis Diagnostic Laboratories - Medical Silicone Tubing 8 mm (Roll of 25 m) | C43: CUS-006 | D43: Heliopolis Diagnostic Laboratories | E43: Nasr City Sales Team | F43: sales.nsc (placeholder) | G43: Existing customer | H43: Won | I43: 100 | J43: 82109.3 | K43: =J43*I43/100 -> 82109.3 | L43: 46192 | M43: 46219 | O43: SO/2026/0044 | P43: =SUMIFS('Sales Order Lines'!$L$2:$L$207,'Sales Order Lines'!$A$2:$A$207,O43) -> 82109.3 | Q43: =IF(O43="",0,P43-J43) -> 0
A44: OPP-0041 | B44: Zagazig Dialysis Center - Infusion Pump (Volumetric) | C44: CUS-012 | D44: Zagazig Dialysis Center | E44: Nasr City Sales Team | F44: sales.nsc (placeholder) | G44: Email inquiry | H44: Won | I44: 100 | J44: 119090 | K44: =J44*I44/100 -> 119090 | L44: 46193 | M44: 46243 | O44: SO/2026/0055 | P44: =SUMIFS('Sales Order Lines'!$L$2:$L$207,'Sales Order Lines'!$A$2:$A$207,O44) -> 119090 | Q44: =IF(O44="",0,P44-J44) -> 0
A45: OPP-0042 | B45: Red Sea Emergency Hospital - SpO2 Sensor, Adult Reusable | C45: CUS-011 | D45: Red Sea Emergency Hospital | E45: Nasr City Sales Team | F45: sales.nsc (placeholder) | G45: Exhibition / conference | H45: Won | I45: 100 | J45: 347375.7 | K45: =J45*I45/100 -> 347375.7 | L45: 46195 | M45: 46247 | O45: SO/2026/0060 | P45: =SUMIFS('Sales Order Lines'!$L$2:$L$207,'Sales Order Lines'!$A$2:$A$207,O45) -> 347375.7 | Q45: =IF(O45="",0,P45-J45) -> 0
A46: OPP-0043 | B46: Al Salam Teaching Hospital - Defibrillator (Biphasic) | C46: CUS-001 | D46: Al Salam Teaching Hospital | E46: Nasr City Sales Team | F46: sales.nsc (placeholder) | G46: Website inquiry | H46: Won | I46: 100 | J46: 302601.2 | K46: =J46*I46/100 -> 302601.2 | L46: 46196 | M46: 46218 | O46: SO/2026/0043 | P46: =SUMIFS('Sales Order Lines'!$L$2:$L$207,'Sales Order Lines'!$A$2:$A$207,O46) -> 302601.2 | Q46: =IF(O46="",0,P46-J46) -> 0
A47: OPP-0044 | B47: Delta Care Hospital - ECG Machine (12-Channel) | C47: CUS-003 | D47: Delta Care Hospital | E47: Mohandeseen Sales Team | F47: sales.moh (placeholder) | G47: Existing customer | H47: Won | I47: 100 | J47: 81604.6 | K47: =J47*I47/100 -> 81604.6 | L47: 46197 | M47: 46208 | O47: SO/2026/0035 | P47: =SUMIFS('Sales Order Lines'!$L$2:$L$207,'Sales Order Lines'!$A$2:$A$207,O47) -> 81604.6 | Q47: =IF(O47="",0,P47-J47) -> 0
A48: OPP-0045 | B48: Nasr City Family Clinics - Nitrile Examination Gloves, Medium (Box of 100) | C48: CUS-005 | D48: Nasr City Family Clinics | E48: Nasr City Sales Team | F48: sales.nsc (placeholder) | G48: Website inquiry | H48: Won | I48: 100 | J48: 86600 | K48: =J48*I48/100 -> 86600 | L48: 46197 | M48: 46246 | O48: SO/2026/0059 | P48: =SUMIFS('Sales Order Lines'!$L$2:$L$207,'Sales Order Lines'!$A$2:$A$207,O48) -> 86600 | Q48: =IF(O48="",0,P48-J48) -> 0
A49: OPP-0046 | B49: Giza Advanced Imaging Center - MRI Machine 1.5T | C49: CUS-007 | D49: Giza Advanced Imaging Center | E49: Mohandeseen Sales Team | F49: sales.moh (placeholder) | G49: Exhibition / conference | H49: Won | I49: 100 | J49: 23125000 | K49: =J49*I49/100 -> 23125000 | L49: 46200 | M49: 46243 | O49: SO/2026/0056 | P49: =SUMIFS('Sales Order Lines'!$L$2:$L$207,'Sales Order Lines'!$A$2:$A$207,O49) -> 23125000 | Q49: =IF(O49="",0,P49-J49) -> 0
A50: OPP-0047 | B50: Delta Care Hospital - Hospital Bed (Electric, 3-Function) | C50: CUS-003 | D50: Delta Care Hospital | E50: Mohandeseen Sales Team | F50: sales.moh (placeholder) | G50: Existing customer | H50: Won | I50: 100 | J50: 329417.2 | K50: =J50*I50/100 -> 329417.2 | L50: 46202 | M50: 46239 | O50: SO/2026/0053 | P50: =SUMIFS('Sales Order Lines'!$L$2:$L$207,'Sales Order Lines'!$A$2:$A$207,O50) -> 329417.2 | Q50: =IF(O50="",0,P50-J50) -> 0
A51: OPP-0048 | B51: Nile Valley Medical Center - Nitrile Examination Gloves, Medium (Box of 100) | C51: CUS-002 | D51: Nile Valley Medical Center | E51: Mohandeseen Sales Team | F51: sales.moh (placeholder) | G51: Existing customer | H51: Won | I51: 100 | J51: 85282.4 | K51: =J51*I51/100 -> 85282.4 | L51: 46203 | M51: 46233 | O51: SO/2026/0051 | P51: =SUMIFS('Sales Order Lines'!$L$2:$L$207,'Sales Order Lines'!$A$2:$A$207,O51) -> 85282.4 | Q51: =IF(O51="",0,P51-J51) -> 0
A52: OPP-0049 | B52: Maadi Pediatric Hospital - Hospital Bed (Electric, 3-Function) | C52: CUS-010 | D52: Maadi Pediatric Hospital | E52: Maadi Sales Team | F52: retail.maadi (placeholder) | G52: Website inquiry | H52: Won | I52: 100 | J52: 226361.14 | K52: =J52*I52/100 -> 226361.14 | L52: 46204 | M52: 46231 | O52: SO/2026/0048 | P52: =SUMIFS('Sales Order Lines'!$L$2:$L$207,'Sales Order Lines'!$A$2:$A$207,O52) -> 226361.14 | Q52: =IF(O52="",0,P52-J52) -> 0
A53: OPP-0050 | B53: Zagazig Dialysis Center - Nitrile Examination Gloves, Medium (Box of 100) | C53: CUS-012 | D53: Zagazig Dialysis Center | E53: Nasr City Sales Team | F53: sales.nsc (placeholder) | G53: Hospital tender | H53: Lost | I53: 0 | J53: 42090 | K53: =J53*I53/100 -> 0 | L53: 46206 | M53: 46250 | N53: Tender cancelled | P53: 0 | Q53: =IF(O53="",0,P53-J53) -> 0
A54: OPP-0051 | B54: Red Sea Emergency Hospital - ECG Electrodes (Pack of 50) | C54: CUS-011 | D54: Red Sea Emergency Hospital | E54: Nasr City Sales Team | F54: sales.nsc (placeholder) | G54: Website inquiry | H54: Lost | I54: 0 | J54: 49640 | K54: =J54*I54/100 -> 0 | L54: 46207 | M54: 46250 | N54: Tender cancelled | P54: 0 | Q54: =IF(O54="",0,P54-J54) -> 0
A55: OPP-0052 | B55: Alexandria Coastal Hospital - Infusion Pump (Volumetric) | C55: CUS-004 | D55: Alexandria Coastal Hospital | E55: Mohandeseen Sales Team | F55: sales.moh (placeholder) | G55: Exhibition / conference | H55: Won | I55: 100 | J55: 327316.8 | K55: =J55*I55/100 -> 327316.8 | L55: 46209 | M55: 46260 | O55: SO/2026/0067 | P55: =SUMIFS('Sales Order Lines'!$L$2:$L$207,'Sales Order Lines'!$A$2:$A$207,O55) -> 327316.8 | Q55: =IF(O55="",0,P55-J55) -> 0
A56: OPP-0053 | B56: Alexandria Coastal Hospital - Infusion Pump (Volumetric) | C56: CUS-004 | D56: Alexandria Coastal Hospital | E56: Mohandeseen Sales Team | F56: sales.moh (placeholder) | G56: Referral | H56: Won | I56: 100 | J56: 165389.85 | K56: =J56*I56/100 -> 165389.85 | L56: 46210 | M56: 46216 | O56: SO/2026/0041 | P56: =SUMIFS('Sales Order Lines'!$L$2:$L$207,'Sales Order Lines'!$A$2:$A$207,O56) -> 165389.85 | Q56: =IF(O56="",0,P56-J56) -> 0
A57: OPP-0054 | B57: Maadi Pediatric Hospital - Nitrile Examination Gloves, Medium (Box of 100) | C57: CUS-010 | D57: Maadi Pediatric Hospital | E57: Maadi Sales Team | F57: retail.maadi (placeholder) | G57: Hospital tender | H57: Won | I57: 100 | J57: 83875.9 | K57: =J57*I57/100 -> 83875.9 | L57: 46214 | M57: 46253 | O57: SO/2026/0063 | P57: =SUMIFS('Sales Order Lines'!$L$2:$L$207,'Sales Order Lines'!$A$2:$A$207,O57) -> 83875.9 | Q57: =IF(O57="",0,P57-J57) -> 0
A58: OPP-0055 | B58: Upper Egypt Medical Complex - Gauze Swabs & Dressings Pack | C58: CUS-009 | D58: Upper Egypt Medical Complex | E58: Nasr City Sales Team | F58: sales.nsc (placeholder) | G58: Existing customer | H58: Lost | I58: 0 | J58: 104355 | K58: =J58*I58/100 -> 0 | L58: 46216 | M58: 46261 | N58: Tender cancelled | P58: 0 | Q58: =IF(O58="",0,P58-J58) -> 0
A59: OPP-0056 | B59: Upper Egypt Medical Complex - Defibrillator Pads, Adult (Pair) | C59: CUS-009 | D59: Upper Egypt Medical Complex | E59: Nasr City Sales Team | F59: sales.nsc (placeholder) | G59: Exhibition / conference | H59: Won | I59: 100 | J59: 134045 | K59: =J59*I59/100 -> 134045 | L59: 46221 | M59: 46251 | O59: SO/2026/0061 | P59: =SUMIFS('Sales Order Lines'!$L$2:$L$207,'Sales Order Lines'!$A$2:$A$207,O59) -> 134045 | Q59: =IF(O59="",0,P59-J59) -> 0
A60: OPP-0057 | B60: Giza Advanced Imaging Center - Nitrile Examination Gloves, Medium (Box of 100) | C60: CUS-007 | D60: Giza Advanced Imaging Center | E60: Mohandeseen Sales Team | F60: sales.moh (placeholder) | G60: Email inquiry | H60: Won | I60: 100 | J60: 100026 | K60: =J60*I60/100 -> 100026 | L60: 46222 | M60: 46265 | O60: SO/2026/0069 | P60: =SUMIFS('Sales Order Lines'!$L$2:$L$207,'Sales Order Lines'!$A$2:$A$207,O60) -> 100026 | Q60: =IF(O60="",0,P60-J60) -> 0
A61: OPP-0058 | B61: Heliopolis Diagnostic Laboratories - Nitrile Examination Gloves, Medium (Box of 100) | C61: CUS-006 | D61: Heliopolis Diagnostic Laboratories | E61: Nasr City Sales Team | F61: sales.nsc (placeholder) | G61: Exhibition / conference | H61: Won | I61: 100 | J61: 111901.3 | K61: =J61*I61/100 -> 111901.3 | L61: 46225 | M61: 46240 | O61: SO/2026/0054 | P61: =SUMIFS('Sales Order Lines'!$L$2:$L$207,'Sales Order Lines'!$A$2:$A$207,O61) -> 111901.3 | Q61: =IF(O61="",0,P61-J61) -> 0
A62: OPP-0059 | B62: New Cairo Women's Health Clinic - Infusion Pump (Volumetric) | C62: CUS-008 | D62: New Cairo Women's Health Clinic | E62: Nasr City Sales Team | F62: sales.nsc (placeholder) | G62: Existing customer | H62: Won | I62: 100 | J62: 136910 | K62: =J62*I62/100 -> 136910 | L62: 46228 | M62: 46258 | O62: SO/2026/0066 | P62: =SUMIFS('Sales Order Lines'!$L$2:$L$207,'Sales Order Lines'!$A$2:$A$207,O62) -> 136910 | Q62: =IF(O62="",0,P62-J62) -> 0
A63: OPP-0060 | B63: New Cairo Women's Health Clinic - Disposable Syringe 5 ml (Box of 100) | C63: CUS-008 | D63: New Cairo Women's Health Clinic | E63: Nasr City Sales Team | F63: sales.nsc (placeholder) | G63: Hospital tender | H63: Won | I63: 100 | J63: 121155 | K63: =J63*I63/100 -> 121155 | L63: 46229 | M63: 46279 | O63: SO/2026/0076 | P63: =SUMIFS('Sales Order Lines'!$L$2:$L$207,'Sales Order Lines'!$A$2:$A$207,O63) -> 121155 | Q63: =IF(O63="",0,P63-J63) -> 0
A64: OPP-0061 | B64: Nasr City Family Clinics - ECG Electrodes (Pack of 50) | C64: CUS-005 | D64: Nasr City Family Clinics | E64: Nasr City Sales Team | F64: sales.nsc (placeholder) | G64: Existing customer | H64: Lost | I64: 0 | J64: 66640 | K64: =J64*I64/100 -> 0 | L64: 46231 | M64: 46270 | N64: Price too high | P64: 0 | Q64: =IF(O64="",0,P64-J64) -> 0
A65: OPP-0062 | B65: New Cairo Women's Health Clinic - Defibrillator Pads, Adult (Pair) | C65: CUS-008 | D65: New Cairo Women's Health Clinic | E65: Nasr City Sales Team | F65: sales.nsc (placeholder) | G65: Existing customer | H65: New | I65: 10 | J65: 547600 | K65: =J65*I65/100 -> 54760 | L65: 46234 | M65: 46312 | P65: 0 | Q65: =IF(O65="",0,P65-J65) -> 0
A66: OPP-0063 | B66: Maadi Pediatric Hospital - Disposable Syringe 5 ml (Box of 100) | C66: CUS-010 | D66: Maadi Pediatric Hospital | E66: Maadi Sales Team | F66: retail.maadi (placeholder) | G66: Referral | H66: Won | I66: 100 | J66: 183320.3 | K66: =J66*I66/100 -> 183320.3 | L66: 46234 | M66: 46279 | O66: SO/2026/0077 | P66: =SUMIFS('Sales Order Lines'!$L$2:$L$207,'Sales Order Lines'!$A$2:$A$207,O66) -> 183320.3 | Q66: =IF(O66="",0,P66-J66) -> 0
A67: OPP-0064 | B67: Al Salam Teaching Hospital - Defibrillator (Biphasic) | C67: CUS-001 | D67: Al Salam Teaching Hospital | E67: Nasr City Sales Team | F67: sales.nsc (placeholder) | G67: Exhibition / conference | H67: Won | I67: 100 | J67: 153745 | K67: =J67*I67/100 -> 153745 | L67: 46235 | M67: 46254 | O67: SO/2026/0065 | P67: =SUMIFS('Sales Order Lines'!$L$2:$L$207,'Sales Order Lines'!$A$2:$A$207,O67) -> 153745 | Q67: =IF(O67="",0,P67-J67) -> 0
A68: OPP-0065 | B68: Nile Valley Medical Center - MRI Machine 1.5T | C68: CUS-002 | D68: Nile Valley Medical Center | E68: Mohandeseen Sales Team | F68: sales.moh (placeholder) | G68: Hospital tender | H68: Negotiation | I68: 75 | J68: 23125000 | K68: =J68*I68/100 -> 17343750 | L68: 46236 | M68: 46305 | P68: 0 | Q68: =IF(O68="",0,P68-J68) -> 0
A69: OPP-0066 | B69: Al Salam Teaching Hospital - Oxygen Concentrator (5 L/min) | C69: CUS-001 | D69: Al Salam Teaching Hospital | E69: Nasr City Sales Team | F69: sales.nsc (placeholder) | G69: Website inquiry | H69: Won | I69: 100 | J69: 108843.7 | K69: =J69*I69/100 -> 108843.7 | L69: 46237 | M69: 46274 | O69: SO/2026/0073 | P69: =SUMIFS('Sales Order Lines'!$L$2:$L$207,'Sales Order Lines'!$A$2:$A$207,O69) -> 108843.7 | Q69: =IF(O69="",0,P69-J69) -> 0
A70: OPP-0067 | B70: Heliopolis Diagnostic Laboratories - Patient Monitor (Multi-parameter, 12") | C70: CUS-006 | D70: Heliopolis Diagnostic Laboratories | E70: Nasr City Sales Team | F70: sales.nsc (placeholder) | G70: Existing customer | H70: Lost | I70: 0 | J70: 163500 | K70: =J70*I70/100 -> 0 | L70: 46238 | M70: 46271 | N70: Price too high | P70: 0 | Q70: =IF(O70="",0,P70-J70) -> 0
A71: OPP-0068 | B71: Nile Valley Medical Center - Patient Monitor (Multi-parameter, 12") | C71: CUS-002 | D71: Nile Valley Medical Center | E71: Mohandeseen Sales Team | F71: sales.moh (placeholder) | G71: Referral | H71: Won | I71: 100 | J71: 163687.5 | K71: =J71*I71/100 -> 163687.5 | L71: 46240 | M71: 46272 | O71: SO/2026/0070 | P71: =SUMIFS('Sales Order Lines'!$L$2:$L$207,'Sales Order Lines'!$A$2:$A$207,O71) -> 163687.5 | Q71: =IF(O71="",0,P71-J71) -> 0
A72: OPP-0069 | B72: Maadi Pediatric Hospital - Disposable Syringe 5 ml (Box of 100) | C72: CUS-010 | D72: Maadi Pediatric Hospital | E72: Maadi Sales Team | F72: retail.maadi (placeholder) | G72: Exhibition / conference | H72: Lost | I72: 0 | J72: 97500 | K72: =J72*I72/100 -> 0 | L72: 46243 | M72: 46274 | N72: Budget not approved | P72: 0 | Q72: =IF(O72="",0,P72-J72) -> 0
A73: OPP-0070 | B73: Giza Advanced Imaging Center - Nitrile Examination Gloves, Medium (Box of 100) | C73: CUS-007 | D73: Giza Advanced Imaging Center | E73: Mohandeseen Sales Team | F73: sales.moh (placeholder) | G73: Hospital tender | H73: Won | I73: 100 | J73: 123626 | K73: =J73*I73/100 -> 123626 | L73: 46244 | M73: 46294 | O73: SO/2026/0085 | P73: =SUMIFS('Sales Order Lines'!$L$2:$L$207,'Sales Order Lines'!$A$2:$A$207,O73) -> 123626 | Q73: =IF(O73="",0,P73-J73) -> 0
A74: OPP-0071 | B74: Delta Care Hospital - Hospital Bed (Electric, 3-Function) | C74: CUS-003 | D74: Delta Care Hospital | E74: Mohandeseen Sales Team | F74: sales.moh (placeholder) | G74: Email inquiry | H74: New | I74: 10 | J74: 83000 | K74: =J74*I74/100 -> 8300 | L74: 46245 | M74: 46332 | P74: 0 | Q74: =IF(O74="",0,P74-J74) -> 0
A75: OPP-0072 | B75: Red Sea Emergency Hospital - Patient Monitor (Multi-parameter, 12") | C75: CUS-011 | D75: Red Sea Emergency Hospital | E75: Nasr City Sales Team | F75: sales.nsc (placeholder) | G75: Referral | H75: Won | I75: 100 | J75: 204697.5 | K75: =J75*I75/100 -> 204697.5 | L75: 46245 | M75: 46280 | O75: SO/2026/0078 | P75: =SUMIFS('Sales Order Lines'!$L$2:$L$207,'Sales Order Lines'!$A$2:$A$207,O75) -> 204697.5 | Q75: =IF(O75="",0,P75-J75) -> 0
A76: OPP-0073 | B76: Upper Egypt Medical Complex - ECG Machine (12-Channel) | C76: CUS-009 | D76: Upper Egypt Medical Complex | E76: Nasr City Sales Team | F76: sales.nsc (placeholder) | G76: Website inquiry | H76: Won | I76: 100 | J76: 94240 | K76: =J76*I76/100 -> 94240 | L76: 46246 | M76: 46288 | O76: SO/2026/0081 | P76: =SUMIFS('Sales Order Lines'!$L$2:$L$207,'Sales Order Lines'!$A$2:$A$207,O76) -> 94240 | Q76: =IF(O76="",0,P76-J76) -> 0
A77: OPP-0074 | B77: Zagazig Dialysis Center - Medical Silicone Tubing 8 mm (Roll of 25 m) | C77: CUS-012 | D77: Zagazig Dialysis Center | E77: Nasr City Sales Team | F77: sales.nsc (placeholder) | G77: Exhibition / conference | H77: Won | I77: 100 | J77: 110020 | K77: =J77*I77/100 -> 110020 | L77: 46248 | M77: 46286 | O77: SO/2026/0079 | P77: =SUMIFS('Sales Order Lines'!$L$2:$L$207,'Sales Order Lines'!$A$2:$A$207,O77) -> 110020 | Q77: =IF(O77="",0,P77-J77) -> 0
A78: OPP-0075 | B78: Nile Valley Medical Center - Disposable Syringe 5 ml (Box of 100) | C78: CUS-002 | D78: Nile Valley Medical Center | E78: Mohandeseen Sales Team | F78: sales.moh (placeholder) | G78: Hospital tender | H78: Won | I78: 100 | J78: 907236.15 | K78: =J78*I78/100 -> 907236.15 | L78: 46249 | M78: 46260 | O78: SO/2026/0068 | P78: =SUMIFS('Sales Order Lines'!$L$2:$L$207,'Sales Order Lines'!$A$2:$A$207,O78) -> 907236.15 | Q78: =IF(O78="",0,P78-J78) -> 0
A79: OPP-0076 | B79: Delta Care Hospital - Hospital Bed (Electric, 3-Function) | C79: CUS-003 | D79: Delta Care Hospital | E79: Mohandeseen Sales Team | F79: sales.moh (placeholder) | G79: Hospital tender | H79: Won | I79: 100 | J79: 170637.6 | K79: =J79*I79/100 -> 170637.6 | L79: 46254 | M79: 46294 | O79: SO/2026/0086 | P79: =SUMIFS('Sales Order Lines'!$L$2:$L$207,'Sales Order Lines'!$A$2:$A$207,O79) -> 170637.6 | Q79: =IF(O79="",0,P79-J79) -> 0
A80: OPP-0077 | B80: Alexandria Coastal Hospital - IV Infusion Set (Box of 25) | C80: CUS-004 | D80: Alexandria Coastal Hospital | E80: Mohandeseen Sales Team | F80: sales.moh (placeholder) | G80: Hospital tender | H80: Quotation Sent | I80: 50 | J80: 197780 | K80: =J80*I80/100 -> 98890 | L80: 46259 | M80: 46318 | P80: 0 | Q80: =IF(O80="",0,P80-J80) -> 0
A81: OPP-0078 | B81: Heliopolis Diagnostic Laboratories - Disposable Syringe 5 ml (Box of 100) | C81: CUS-006 | D81: Heliopolis Diagnostic Laboratories | E81: Nasr City Sales Team | F81: sales.nsc (placeholder) | G81: Referral | H81: Won | I81: 100 | J81: 130085.2 | K81: =J81*I81/100 -> 130085.2 | L81: 46261 | M81: 46293 | O81: SO/2026/0084 | P81: =SUMIFS('Sales Order Lines'!$L$2:$L$207,'Sales Order Lines'!$A$2:$A$207,O81) -> 130085.2 | Q81: =IF(O81="",0,P81-J81) -> 0
A82: OPP-0079 | B82: Nasr City Family Clinics - Autoclave Door Gasket | C82: CUS-005 | D82: Nasr City Family Clinics | E82: Nasr City Sales Team | F82: sales.nsc (placeholder) | G82: Exhibition / conference | H82: Qualified | I82: 25 | J82: 2318400 | K82: =J82*I82/100 -> 579600 | L82: 46263 | M82: 46325 | P82: 0 | Q82: =IF(O82="",0,P82-J82) -> 0
A83: OPP-0080 | B83: New Cairo Women's Health Clinic - Autoclave Door Gasket | C83: CUS-008 | D83: New Cairo Women's Health Clinic | E83: Nasr City Sales Team | F83: sales.nsc (placeholder) | G83: Website inquiry | H83: Quotation Sent | I83: 50 | J83: 2763600 | K83: =J83*I83/100 -> 1381800 | L83: 46265 | M83: 46329 | P83: 0 | Q83: =IF(O83="",0,P83-J83) -> 0
A84: OPP-0081 | B84: Heliopolis Diagnostic Laboratories - IV Cannula 20G (Box of 50) | C84: CUS-006 | D84: Heliopolis Diagnostic Laboratories | E84: Nasr City Sales Team | F84: sales.nsc (placeholder) | G84: Hospital tender | H84: Qualified | I84: 25 | J84: 263250 | K84: =J84*I84/100 -> 65812.5 | L84: 46270 | M84: 46323 | P84: 0 | Q84: =IF(O84="",0,P84-J84) -> 0
A85: OPP-0082 | B85: Nasr City Family Clinics - Gauze Swabs & Dressings Pack | C85: CUS-005 | D85: Nasr City Family Clinics | E85: Nasr City Sales Team | F85: sales.nsc (placeholder) | G85: Email inquiry | H85: Won | I85: 100 | J85: 56111 | K85: =J85*I85/100 -> 56111 | L85: 46272 | M85: 46287 | O85: SO/2026/0080 | P85: =SUMIFS('Sales Order Lines'!$L$2:$L$207,'Sales Order Lines'!$A$2:$A$207,O85) -> 56111 | Q85: =IF(O85="",0,P85-J85) -> 0
A86: OPP-0083 | B86: Al Salam Teaching Hospital - IV Cannula 20G (Box of 50) | C86: CUS-001 | D86: Al Salam Teaching Hospital | E86: Nasr City Sales Team | F86: sales.nsc (placeholder) | G86: Website inquiry | H86: Qualified | I86: 25 | J86: 331200 | K86: =J86*I86/100 -> 82800 | L86: 46275 | M86: 46355 | P86: 0 | Q86: =IF(O86="",0,P86-J86) -> 0
A87: OPP-0084 | B87: Alexandria Coastal Hospital - Hospital Bed (Electric, 3-Function) | C87: CUS-004 | D87: Alexandria Coastal Hospital | E87: Mohandeseen Sales Team | F87: sales.moh (placeholder) | G87: Existing customer | H87: Won | I87: 100 | J87: 187307 | K87: =J87*I87/100 -> 187307 | L87: 46275 | M87: 46292 | O87: SO/2026/0083 | P87: =SUMIFS('Sales Order Lines'!$L$2:$L$207,'Sales Order Lines'!$A$2:$A$207,O87) -> 187307 | Q87: =IF(O87="",0,P87-J87) -> 0
A88: OPP-0085 | B88: Nasr City Family Clinics - Defibrillator Pads, Adult (Pair) | C88: CUS-005 | D88: Nasr City Family Clinics | E88: Nasr City Sales Team | F88: sales.nsc (placeholder) | G88: Existing customer | H88: Qualified | I88: 25 | J88: 1158100 | K88: =J88*I88/100 -> 289525 | L88: 46278 | M88: 46339 | P88: 0 | Q88: =IF(O88="",0,P88-J88) -> 0
A89: OPP-0086 | B89: Maadi Pediatric Hospital - Ultrasound System (Colour Doppler) | C89: CUS-010 | D89: Maadi Pediatric Hospital | E89: Maadi Sales Team | F89: retail.maadi (placeholder) | G89: Exhibition / conference | H89: Negotiation | I89: 75 | J89: 1670000 | K89: =J89*I89/100 -> 1252500 | L89: 46284 | M89: 46351 | P89: 0 | Q89: =IF(O89="",0,P89-J89) -> 0
A91: Stage | B91: Probability % | C91: Opportunities | D91: Expected Revenue (EGP) | E91: Weighted Revenue (EGP)
A92: New | B92: 10 | C92: =COUNTIF('CRM Pipeline'!$H$4:$H$89,A92) -> 2 | D92: =SUMIFS('CRM Pipeline'!$J$4:$J$89,'CRM Pipeline'!$H$4:$H$89,A92) -> 630600 | E92: =SUMIFS('CRM Pipeline'!$K$4:$K$89,'CRM Pipeline'!$H$4:$H$89,A92) -> 63060
A93: Qualified | B93: 25 | C93: =COUNTIF('CRM Pipeline'!$H$4:$H$89,A93) -> 4 | D93: =SUMIFS('CRM Pipeline'!$J$4:$J$89,'CRM Pipeline'!$H$4:$H$89,A93) -> 4070950 | E93: =SUMIFS('CRM Pipeline'!$K$4:$K$89,'CRM Pipeline'!$H$4:$H$89,A93) -> 1017737.5
A94: Quotation Sent | B94: 50 | C94: =COUNTIF('CRM Pipeline'!$H$4:$H$89,A94) -> 2 | D94: =SUMIFS('CRM Pipeline'!$J$4:$J$89,'CRM Pipeline'!$H$4:$H$89,A94) -> 2961380 | E94: =SUMIFS('CRM Pipeline'!$K$4:$K$89,'CRM Pipeline'!$H$4:$H$89,A94) -> 1480690
A95: Negotiation | B95: 75 | C95: =COUNTIF('CRM Pipeline'!$H$4:$H$89,A95) -> 2 | D95: =SUMIFS('CRM Pipeline'!$J$4:$J$89,'CRM Pipeline'!$H$4:$H$89,A95) -> 24795000 | E95: =SUMIFS('CRM Pipeline'!$K$4:$K$89,'CRM Pipeline'!$H$4:$H$89,A95) -> 18596250
A96: Won | B96: 100 | C96: =COUNTIF('CRM Pipeline'!$H$4:$H$89,A96) -> 62 | D96: =SUMIFS('CRM Pipeline'!$J$4:$J$89,'CRM Pipeline'!$H$4:$H$89,A96) -> 31732543 | E96: =SUMIFS('CRM Pipeline'!$K$4:$K$89,'CRM Pipeline'!$H$4:$H$89,A96) -> 31732543
A97: Lost | B97: 0 | C97: =COUNTIF('CRM Pipeline'!$H$4:$H$89,A97) -> 14 | D97: =SUMIFS('CRM Pipeline'!$J$4:$J$89,'CRM Pipeline'!$H$4:$H$89,A97) -> 8934295 | E97: =SUMIFS('CRM Pipeline'!$K$4:$K$89,'CRM Pipeline'!$H$4:$H$89,A97) -> 0
A98: Total | C98: =SUM(C92:C97) -> 86 | D98: =SUM(D92:D97) -> 73124768 | E98: =SUM(E92:E97) -> 52890281

Sheet Customer Invoices and Payments
A1: A. Customer invoices (journal INV)
A2: Payments applied come from table B below; credit notes from the 'Customer and Supplier Returns' sheet.
A3: Invoice No | B3: Invoice Date | C3: Month | D3: Customer ID | E3: Customer | F3: Sales Order | G3: Net (EGP) | H3: VAT (EGP) | I3: Total (EGP) | J3: Due Date | K3: Credit Notes (EGP) | L3: Payments Applied (EGP) | M3: Balance 30-Sep-2026 (EGP) | N3: Payment Status | O3: Days Overdue
A4: INV/2026/00001 | B4: 46154 | C4: 2026-05 | D4: CUS-001 | E4: Al Salam Teaching Hospital | F4: SO/2026/0001 | G4: 134007.44 | H4: 18761.04 | I4: =G4+H4 -> 152768.48 | J4: 46184 | K4: =SUMIFS('Customer and Supplier Returns'!$S$2:$S$12,'Customer and Supplier Returns'!$G$2:$G$12,A4,'Customer and Supplier Returns'!$B$2:$B$12,"Customer return") -> 0 | L4: =SUMIFS('Customer Invoices and Payments'!$F$91:$F$152,'Customer Invoices and Payments'!$D$91:$D$152,A4) -> 152768.48 | M4: =I4-K4-L4 -> 0 | N4: =IF(ROUND(M4,2)=0,"Paid",IF(L4>0,IF(J4<DATE(2026,9,30),"Partial - overdue","Partially paid"),IF(J4<DATE(2026,9,30),"Overdue","Open"))) -> Paid | O4: =IF(ROUND(M4,2)>0,MAX(0,DATE(2026,9,30)-J4),0) -> 0
A5: INV/2026/00002 | B5: 46155 | C5: 2026-05 | D5: CUS-003 | E5: Delta Care Hospital | F5: SO/2026/0002 | G5: 222264 | H5: 31116.96 | I5: =G5+H5 -> 253380.96 | J5: 46200 | K5: =SUMIFS('Customer and Supplier Returns'!$S$2:$S$12,'Customer and Supplier Returns'!$G$2:$G$12,A5,'Customer and Supplier Returns'!$B$2:$B$12,"Customer return") -> 0 | L5: =SUMIFS('Customer Invoices and Payments'!$F$91:$F$152,'Customer Invoices and Payments'!$D$91:$D$152,A5) -> 253380.96 | M5: =I5-K5-L5 -> 0 | N5: =IF(ROUND(M5,2)=0,"Paid",IF(L5>0,IF(J5<DATE(2026,9,30),"Partial - overdue","Partially paid"),IF(J5<DATE(2026,9,30),"Overdue","Open"))) -> Paid | O5: =IF(ROUND(M5,2)>0,MAX(0,DATE(2026,9,30)-J5),0) -> 0
A6: INV/2026/00003 | B6: 46156 | C6: 2026-05 | D6: CUS-013 | E6: Walk-in Retail Customers (Maadi) | F6: SO/2026/0005 | G6: 3500 | H6: 490 | I6: =G6+H6 -> 3990 | J6: 46156 | K6: =SUMIFS('Customer and Supplier Returns'!$S$2:$S$12,'Customer and Supplier Returns'!$G$2:$G$12,A6,'Customer and Supplier Returns'!$B$2:$B$12,"Customer return") -> 0 | L6: =SUMIFS('Customer Invoices and Payments'!$F$91:$F$152,'Customer Invoices and Payments'!$D$91:$D$152,A6) -> 3990 | M6: =I6-K6-L6 -> 0 | N6: =IF(ROUND(M6,2)=0,"Paid",IF(L6>0,IF(J6<DATE(2026,9,30),"Partial - overdue","Partially paid"),IF(J6<DATE(2026,9,30),"Overdue","Open"))) -> Paid | O6: =IF(ROUND(M6,2)>0,MAX(0,DATE(2026,9,30)-J6),0) -> 0
A7: INV/2026/00004 | B7: 46156 | C7: 2026-05 | D7: CUS-013 | E7: Walk-in Retail Customers (Maadi) | F7: SO/2026/0006 | G7: 2760 | H7: 386.4 | I7: =G7+H7 -> 3146.4 | J7: 46156 | K7: =SUMIFS('Customer and Supplier Returns'!$S$2:$S$12,'Customer and Supplier Returns'!$G$2:$G$12,A7,'Customer and Supplier Returns'!$B$2:$B$12,"Customer return") -> 0 | L7: =SUMIFS('Customer Invoices and Payments'!$F$91:$F$152,'Customer Invoices and Payments'!$D$91:$D$152,A7) -> 3146.4 | M7: =I7-K7-L7 -> 0 | N7: =IF(ROUND(M7,2)=0,"Paid",IF(L7>0,IF(J7<DATE(2026,9,30),"Partial - overdue","Partially paid"),IF(J7<DATE(2026,9,30),"Overdue","Open"))) -> Paid | O7: =IF(ROUND(M7,2)>0,MAX(0,DATE(2026,9,30)-J7),0) -> 0
A8: INV/2026/00005 | B8: 46159 | C8: 2026-05 | D8: CUS-002 | E8: Nile Valley Medical Center | F8: SO/2026/0004 | G8: 72682.1 | H8: 10175.49 | I8: =G8+H8 -> 82857.59 | J8: 46204 | K8: =SUMIFS('Customer and Supplier Returns'!$S$2:$S$12,'Customer and Supplier Returns'!$G$2:$G$12,A8,'Customer and Supplier Returns'!$B$2:$B$12,"Customer return") -> 0 | L8: =SUMIFS('Customer Invoices and Payments'!$F$91:$F$152,'Customer Invoices and Payments'!$D$91:$D$152,A8) -> 82857.59 | M8: =I8-K8-L8 -> 0 | N8: =IF(ROUND(M8,2)=0,"Paid",IF(L8>0,IF(J8<DATE(2026,9,30),"Partial - overdue","Partially paid"),IF(J8<DATE(2026,9,30),"Overdue","Open"))) -> Paid | O8: =IF(ROUND(M8,2)>0,MAX(0,DATE(2026,9,30)-J8),0) -> 0
A9: INV/2026/00006 | B9: 46161 | C9: 2026-05 | D9: CUS-010 | E9: Maadi Pediatric Hospital | F9: SO/2026/0008 | G9: 69005.8 | H9: 9660.81 | I9: =G9+H9 -> 78666.61 | J9: 46191 | K9: =SUMIFS('Customer and Supplier Returns'!$S$2:$S$12,'Customer and Supplier Returns'!$G$2:$G$12,A9,'Customer and Supplier Returns'!$B$2:$B$12,"Customer return") -> 0 | L9: =SUMIFS('Customer Invoices and Payments'!$F$91:$F$152,'Customer Invoices and Payments'!$D$91:$D$152,A9) -> 78666.61 | M9: =I9-K9-L9 -> 0 | N9: =IF(ROUND(M9,2)=0,"Paid",IF(L9>0,IF(J9<DATE(2026,9,30),"Partial - overdue","Partially paid"),IF(J9<DATE(2026,9,30),"Overdue","Open"))) -> Paid | O9: =IF(ROUND(M9,2)>0,MAX(0,DATE(2026,9,30)-J9),0) -> 0
A10: INV/2026/00007 | B10: 46162 | C10: 2026-05 | D10: CUS-005 | E10: Nasr City Family Clinics | F10: SO/2026/0003 | G10: 121130 | H10: 16958.2 | I10: =G10+H10 -> 138088.2 | J10: 46177 | K10: =SUMIFS('Customer and Supplier Returns'!$S$2:$S$12,'Customer and Supplier Returns'!$G$2:$G$12,A10,'Customer and Supplier Returns'!$B$2:$B$12,"Customer return") -> 2889.9 | L10: =SUMIFS('Customer Invoices and Payments'!$F$91:$F$152,'Customer Invoices and Payments'!$D$91:$D$152,A10) -> 135198.3 | M10: =I10-K10-L10 -> 0 | N10: =IF(ROUND(M10,2)=0,"Paid",IF(L10>0,IF(J10<DATE(2026,9,30),"Partial - overdue","Partially paid"),IF(J10<DATE(2026,9,30),"Overdue","Open"))) -> Paid | O10: =IF(ROUND(M10,2)>0,MAX(0,DATE(2026,9,30)-J10),0) -> 0
A11: INV/2026/00008 | B11: 46166 | C11: 2026-05 | D11: CUS-013 | E11: Walk-in Retail Customers (Maadi) | F11: SO/2026/0009 | G11: 3065 | H11: 429.1 | I11: =G11+H11 -> 3494.1 | J11: 46166 | K11: =SUMIFS('Customer and Supplier Returns'!$S$2:$S$12,'Customer and Supplier Returns'!$G$2:$G$12,A11,'Customer and Supplier Returns'!$B$2:$B$12,"Customer return") -> 0 | L11: =SUMIFS('Customer Invoices and Payments'!$F$91:$F$152,'Customer Invoices and Payments'!$D$91:$D$152,A11) -> 3494.1 | M11: =I11-K11-L11 -> 0 | N11: =IF(ROUND(M11,2)=0,"Paid",IF(L11>0,IF(J11<DATE(2026,9,30),"Partial - overdue","Partially paid"),IF(J11<DATE(2026,9,30),"Overdue","Open"))) -> Paid | O11: =IF(ROUND(M11,2)>0,MAX(0,DATE(2026,9,30)-J11),0) -> 0
A12: INV/2026/00009 | B12: 46167 | C12: 2026-05 | D12: CUS-009 | E12: Upper Egypt Medical Complex | F12: SO/2026/0007 | G12: 90639.5 | H12: 12689.53 | I12: =G12+H12 -> 103329.03 | J12: 46227 | K12: =SUMIFS('Customer and Supplier Returns'!$S$2:$S$12,'Customer and Supplier Returns'!$G$2:$G$12,A12,'Customer and Supplier Returns'!$B$2:$B$12,"Customer return") -> 0 | L12: =SUMIFS('Customer Invoices and Payments'!$F$91:$F$152,'Customer Invoices and Payments'!$D$91:$D$152,A12) -> 103329.03 | M12: =I12-K12-L12 -> 0 | N12: =IF(ROUND(M12,2)=0,"Paid",IF(L12>0,IF(J12<DATE(2026,9,30),"Partial - overdue","Partially paid"),IF(J12<DATE(2026,9,30),"Overdue","Open"))) -> Paid | O12: =IF(ROUND(M12,2)>0,MAX(0,DATE(2026,9,30)-J12),0) -> 0
A13: INV/2026/00010 | B13: 46168 | C13: 2026-05 | D13: CUS-013 | E13: Walk-in Retail Customers (Maadi) | F13: SO/2026/0010 | G13: 920 | H13: 128.8 | I13: =G13+H13 -> 1048.8 | J13: 46168 | K13: =SUMIFS('Customer and Supplier Returns'!$S$2:$S$12,'Customer and Supplier Returns'!$G$2:$G$12,A13,'Customer and Supplier Returns'!$B$2:$B$12,"Customer return") -> 0 | L13: =SUMIFS('Customer Invoices and Payments'!$F$91:$F$152,'Customer Invoices and Payments'!$D$91:$D$152,A13) -> 1048.8 | M13: =I13-K13-L13 -> 0 | N13: =IF(ROUND(M13,2)=0,"Paid",IF(L13>0,IF(J13<DATE(2026,9,30),"Partial - overdue","Partially paid"),IF(J13<DATE(2026,9,30),"Overdue","Open"))) -> Paid | O13: =IF(ROUND(M13,2)>0,MAX(0,DATE(2026,9,30)-J13),0) -> 0
A14: INV/2026/00011 | B14: 46169 | C14: 2026-05 | D14: CUS-012 | E14: Zagazig Dialysis Center | F14: SO/2026/0012 | G14: 129306 | H14: 18102.84 | I14: =G14+H14 -> 147408.84 | J14: 46199 | K14: =SUMIFS('Customer and Supplier Returns'!$S$2:$S$12,'Customer and Supplier Returns'!$G$2:$G$12,A14,'Customer and Supplier Returns'!$B$2:$B$12,"Customer return") -> 0 | L14: =SUMIFS('Customer Invoices and Payments'!$F$91:$F$152,'Customer Invoices and Payments'!$D$91:$D$152,A14) -> 147408.84 | M14: =I14-K14-L14 -> 0 | N14: =IF(ROUND(M14,2)=0,"Paid",IF(L14>0,IF(J14<DATE(2026,9,30),"Partial - overdue","Partially paid"),IF(J14<DATE(2026,9,30),"Overdue","Open"))) -> Paid | O14: =IF(ROUND(M14,2)>0,MAX(0,DATE(2026,9,30)-J14),0) -> 0
A15: INV/2026/00012 | B15: 46173 | C15: 2026-05 | D15: CUS-006 | E15: Heliopolis Diagnostic Laboratories | F15: SO/2026/0011 | G15: 85431.5 | H15: 11960.41 | I15: =G15+H15 -> 97391.91 | J15: 46203 | K15: =SUMIFS('Customer and Supplier Returns'!$S$2:$S$12,'Customer and Supplier Returns'!$G$2:$G$12,A15,'Customer and Supplier Returns'!$B$2:$B$12,"Customer return") -> 0 | L15: =SUMIFS('Customer Invoices and Payments'!$F$91:$F$152,'Customer Invoices and Payments'!$D$91:$D$152,A15) -> 97391.91 | M15: =I15-K15-L15 -> 0 | N15: =IF(ROUND(M15,2)=0,"Paid",IF(L15>0,IF(J15<DATE(2026,9,30),"Partial - overdue","Partially paid"),IF(J15<DATE(2026,9,30),"Overdue","Open"))) -> Paid | O15: =IF(ROUND(M15,2)>0,MAX(0,DATE(2026,9,30)-J15),0) -> 0
... A85: INV/2026/00082 | B85: 46295 | C85: 2026-09 | D85: CUS-007 | E85: Giza Advanced Imaging Center | F85: SO/2026/0085 | G85: 123626 | H85: 17307.64 | I85: =G85+H85 -> 140933.64 | J85: 46355 | K85: =SUMIFS('Customer and Supplier Returns'!$S$2:$S$12,'Customer and Supplier Returns'!$G$2:$G$12,A85,'Customer and Supplier Returns'!$B$2:$B$12,"Customer return") -> 0 | L85: =SUMIFS('Customer Invoices and Payments'!$F$91:$F$152,'Customer Invoices and Payments'!$D$91:$D$152,A85) -> 0 | M85: =I85-K85-L85 -> 140933.64 | N85: =IF(ROUND(M85,2)=0,"Paid",IF(L85>0,IF(J85<DATE(2026,9,30),"Partial - overdue","Partially paid"),IF(J85<DATE(2026,9,30),"Overdue","Open"))) -> Open | O85: =IF(ROUND(M85,2)>0,MAX(0,DATE(2026,9,30)-J85),0) -> 0
F86: Totals | G86: =SUM(G4:G85) -> 31077428 | H86: =SUM(H4:H85) -> 4350839.9 | I86: =SUM(I4:I85) -> 35428268 | K86: =SUM(K4:K85) -> 962383.1 | L86: =SUM(L4:L85) -> 4933811.3 | M86: =SUM(M4:M85) -> 29532073
A88: B. Customer receipts (journals CIB1 / NBE1 / CSH1-3)
A89: One row per receipt; partial payments appear as separate rows.
A90: Payment No | B90: Payment Date | C90: Customer ID (placeholder) | D90: Applied to Invoice | E90: Customer | F90: Amount (EGP) | G90: Method | H90: Journal | I90: Month
A91: CSH2/IN/2026/0001 | B91: 46156 | C91: CUS-013 | D91: INV/2026/00003 | E91: Walk-in Retail Customers (Maadi) | F91: 3990 | G91: Cash | H91: CSH2 | I91: 2026-05
A92: CSH2/IN/2026/0002 | B92: 46156 | C92: CUS-013 | D92: INV/2026/00004 | E92: Walk-in Retail Customers (Maadi) | F92: 3146.4 | G92: Cash | H92: CSH2 | I92: 2026-05
A93: CSH2/IN/2026/0003 | B93: 46166 | C93: CUS-013 | D93: INV/2026/00008 | E93: Walk-in Retail Customers (Maadi) | F93: 3494.1 | G93: Cash | H93: CSH2 | I93: 2026-05
A94: CSH2/IN/2026/0004 | B94: 46168 | C94: CUS-013 | D94: INV/2026/00010 | E94: Walk-in Retail Customers (Maadi) | F94: 1048.8 | G94: Cash | H94: CSH2 | I94: 2026-05
A95: CSH2/IN/2026/0005 | B95: 46181 | C95: CUS-013 | D95: INV/2026/00017 | E95: Walk-in Retail Customers (Maadi) | F95: 3895.38 | G95: Cash | H95: CSH2 | I95: 2026-06
A96: NBE1/IN/2026/0001 | B96: 46183 | C96: CUS-001 | D96: INV/2026/00001 | E96: Al Salam Teaching Hospital | F96: 152768.48 | G96: Cheque | H96: NBE1 | I96: 2026-06
A97: CSH2/IN/2026/0006 | B97: 46183 | C97: CUS-013 | D97: INV/2026/00020 | E97: Walk-in Retail Customers (Maadi) | F97: 2958.3 | G97: Cash | H97: CSH2 | I97: 2026-06
A98: CSH2/IN/2026/0007 | B98: 46183 | C98: CUS-013 | D98: INV/2026/00021 | E98: Walk-in Retail Customers (Maadi) | F98: 1835.4 | G98: Cash | H98: CSH2 | I98: 2026-06
A99: NBE1/IN/2026/0002 | B99: 46194 | C99: CUS-005 | D99: INV/2026/00007 | E99: Nasr City Family Clinics | F99: 135198.3 | G99: Cheque | H99: NBE1 | I99: 2026-06
A100: NBE1/IN/2026/0003 | B100: 46194 | C100: CUS-008 | D100: INV/2026/00014 | E100: New Cairo Women's Health Clinic | F100: 99373.8 | G100: Cheque | H100: NBE1 | I100: 2026-06
A101: CIB1/IN/2026/0001 | B101: 46194 | C101: CUS-010 | D101: INV/2026/00006 | E101: Maadi Pediatric Hospital | F101: 78666.61 | G101: Bank transfer | H101: CIB1 | I101: 2026-06
A102: CSH2/IN/2026/0008 | B102: 46196 | C102: CUS-013 | D102: INV/2026/00027 | E102: Walk-in Retail Customers (Maadi) | F102: 2884.2 | G102: Cash | H102: CSH2 | I102: 2026-06
... A152: NBE1/IN/2026/0024 | B152: 46294 | C152: CUS-011 | D152: INV/2026/00018 | E152: Red Sea Emergency Hospital | F152: 100548 | G152: Bank transfer | H152: NBE1 | I152: 2026-09
E153: Total receipts | F153: =SUM(F91:F152) -> 4933811.3

Sheet Purchase Orders
A1: PO No | B1: Order Date | C1: Month | D1: Vendor ID | E1: Vendor | F1: Receiving Warehouse | G1: Expected Date | H1: Status (30-Sep-2026) | I1: Receipts | J1: Vendor Bills | K1: Origin
A2: PO/2026/0001 | B2: 46159 | C2: 2026-05 | D2: VEN-001 | E2: Helios Medical Systems GmbH | F2: EQP | G2: 46181 | H2: Fully Received | I2: EQP/IN/00001 | J2: BILL/2026/00002 | K2: Reordering rule (replenishment)
A3: PO/2026/0002 | B3: 46166 | C3: 2026-05 | D3: VEN-001 | E3: Helios Medical Systems GmbH | F3: EQP | G3: 46188 | H3: Fully Received | I3: EQP/IN/00002 | J3: BILL/2026/00004 | K3: Reordering rule (replenishment)
A4: PO/2026/0003 | B4: 46173 | C4: 2026-05 | D4: VEN-001 | E4: Helios Medical Systems GmbH | F4: EQP | G4: 46191 | H4: Fully Received | I4: EQP/IN/00003 | J4: BILL/2026/00006 | K4: Reordering rule (replenishment)
A5: PO/2026/0004 | B5: 46173 | C5: 2026-05 | D5: VEN-003 | E5: MediPlast Industries Egypt | F5: CON | G5: 46180 | H5: Fully Received | I5: CON/IN/00001 | J5: BILL/2026/00001 | K5: Reordering rule (replenishment)
A6: PO/2026/0005 | B6: 46173 | C6: 2026-05 | D6: VEN-004 | E6: Pharos Surgical Supplies | F6: CON | G6: 46182 | H6: Fully Received | I6: CON/IN/00002 | J6: BILL/2026/00003 | K6: Reordering rule (replenishment)
A7: PO/2026/0006 | B7: 46180 | C7: 2026-06 | D7: VEN-003 | E7: MediPlast Industries Egypt | F7: CON | G7: 46189 | H7: Fully Received | I7: CON/IN/00003 | J7: BILL/2026/00005 | K7: Reordering rule (replenishment)
A8: PO/2026/0007 | B8: 46181 | C8: 2026-06 | D8: VEN-002 | E8: Orient Imaging Technologies Co. | F8: EQP | G8: 46204 | H8: Fully Received | I8: EQP/IN/00005 | J8: BILL/2026/00009 | K8: Manual (made-to-order capital item)
A9: PO/2026/0008 | B9: 46187 | C9: 2026-06 | D9: VEN-004 | E9: Pharos Surgical Supplies | F9: EQP | G9: 46202 | H9: Fully Received | I9: EQP/IN/00004 | J9: BILL/2026/00008 | K9: Reordering rule (replenishment)
A10: PO/2026/0009 | B10: 46187 | C10: 2026-06 | D10: VEN-004 | E10: Pharos Surgical Supplies | F10: CON | G10: 46197 | H10: Fully Received | I10: CON/IN/00004 | J10: BILL/2026/00007 | K10: Reordering rule (replenishment)
A11: PO/2026/0010 | B11: 46201 | C11: 2026-06 | D11: VEN-005 | E11: Anatolia Biomed Distribution | F11: EQP | G11: 46219 | H11: Fully Received | I11: EQP/IN/00006, EQP/IN/00007 | J11: BILL/2026/00011, BILL/2026/00013 | K11: Reordering rule (replenishment)
A12: PO/2026/0011 | B12: 46201 | C12: 2026-06 | D12: VEN-003 | E12: MediPlast Industries Egypt | F12: CON | G12: 46208 | H12: Fully Received | I12: CON/IN/00005 | J12: BILL/2026/00010 | K12: Reordering rule (replenishment)
A13: PO/2026/0012 | B13: 46208 | C13: 2026-07 | D13: VEN-001 | E13: Helios Medical Systems GmbH | F13: EQP | G13: 46230 | H13: Fully Received | I13: EQP/IN/00008 | J13: BILL/2026/00014 | K13: Reordering rule (replenishment)
... A26: PO/2026/0025 | B26: 46271 | C26: 2026-09 | D26: VEN-004 | E26: Pharos Surgical Supplies | F26: CON | G26: 46280 | H26: Fully Received | I26: CON/IN/00011 | J26: BILL/2026/00027 | K26: Reordering rule (replenishment)
A27: PO/2026/0026 | B27: 46292 | C27: 2026-09 | D27: VEN-001 | E27: Helios Medical Systems GmbH | F27: EQP | G27: 46313 | H27: To Receive | J27: (none in period) | K27: Reordering rule (replenishment)
A28: PO/2026/0027 | B28: 46292 | C28: 2026-09 | D28: VEN-003 | E28: MediPlast Industries Egypt | F28: CON | G28: 46300 | H28: To Receive | J28: (none in period) | K28: Reordering rule (replenishment)

Sheet Purchase Order Lines
A1: PO No | B1: Line | C1: Product Ref | D1: Product | E1: Ordered Qty | F1: Received Qty | G1: UoM | H1: Unit Cost (EGP, ex-VAT) | I1: Open Qty | J1: Received Value (EGP) | K1: Ordered Value (EGP)
A2: PO/2026/0001 | B2: 1 | C2: EQ-MON-001 | D2: Patient Monitor (Multi-parameter, 12") | E2: 9 | F2: 9 | G2: Unit | H2: 42000 | I2: =E2-F2 -> 0 | J2: =F2*H2 -> 378000 | K2: =E2*H2 -> 378000
A3: PO/2026/0002 | B3: 1 | C3: EQ-ECG-001 | D3: ECG Machine (12-Channel) | E3: 7 | F3: 7 | G3: Unit | H3: 36000 | I3: =E3-F3 -> 0 | J3: =F3*H3 -> 252000 | K3: =E3*H3 -> 252000
A4: PO/2026/0003 | B4: 1 | C4: EQ-INF-001 | D4: Infusion Pump (Volumetric) | E4: 18 | F4: 18 | G4: Unit | H4: 18500 | I4: =E4-F4 -> 0 | J4: =F4*H4 -> 333000 | K4: =E4*H4 -> 333000
A5: PO/2026/0004 | B5: 1 | C5: CN-MSK-001 | D5: Surgical Face Mask 3-Ply (Box of 50) | E5: 2706 | F5: 2706 | G5: Box | H5: 38 | I5: =E5-F5 -> 0 | J5: =F5*H5 -> 102828 | K5: =E5*H5 -> 102828
A6: PO/2026/0005 | B6: 1 | C6: CN-ECE-001 | D6: ECG Electrodes (Pack of 50) | E6: 427 | F6: 427 | G6: Pack | H6: 120 | I6: =E6-F6 -> 0 | J6: =F6*H6 -> 51240 | K6: =E6*H6 -> 51240
A7: PO/2026/0006 | B7: 1 | C7: CN-GAU-001 | D7: Gauze Swabs & Dressings Pack | E7: 939 | F7: 939 | G7: Pack | H7: 95 | I7: =E7-F7 -> 0 | J7: =F7*H7 -> 89205 | K7: =E7*H7 -> 89205
A8: PO/2026/0007 | B8: 1 | C8: EQ-MRI-001 | D8: MRI Machine 1.5T | E8: 1 | F8: 1 | G8: Unit | H8: 18500000 | I8: =E8-F8 -> 0 | J8: =F8*H8 -> 18500000 | K8: =E8*H8 -> 18500000
A9: PO/2026/0008 | B9: 1 | C9: EQ-SUR-001 | D9: Surgical Instrument Set (General Surgery, 120 pcs) | E9: 9 | F9: 9 | G9: Set | H9: 27500 | I9: =E9-F9 -> 0 | J9: =F9*H9 -> 247500 | K9: =E9*H9 -> 247500
A10: PO/2026/0009 | B10: 1 | C10: CN-GLV-001 | D10: Nitrile Examination Gloves, Medium (Box of 100) | E10: 1836 | F10: 1836 | G10: Box | H10: 165 | I10: =E10-F10 -> 0 | J10: =F10*H10 -> 302940 | K10: =E10*H10 -> 302940
A11: PO/2026/0010 | B11: 1 | C11: EQ-OXY-001 | D11: Oxygen Concentrator (5 L/min) | E11: 14 | F11: 14 | G11: Unit | H11: 14200 | I11: =E11-F11 -> 0 | J11: =F11*H11 -> 198800 | K11: =E11*H11 -> 198800
A12: PO/2026/0011 | B12: 1 | C12: CN-SYR-001 | D12: Disposable Syringe 5 ml (Box of 100) | E12: 1307 | F12: 1307 | G12: Box | H12: 145 | I12: =E12-F12 -> 0 | J12: =F12*H12 -> 189515 | K12: =E12*H12 -> 189515
A13: PO/2026/0012 | B13: 1 | C13: EQ-DEF-001 | D13: Defibrillator (Biphasic) | E13: 5 | F13: 5 | G13: Unit | H13: 98000 | I13: =E13-F13 -> 0 | J13: =F13*H13 -> 490000 | K13: =E13*H13 -> 490000
... A31: PO/2026/0027 | B31: 1 | C31: CN-SYR-001 | D31: Disposable Syringe 5 ml (Box of 100) | E31: 1406 | F31: 0 | G31: Box | H31: 145 | I31: =E31-F31 -> 1406 | J31: =F31*H31 -> 0 | K31: =E31*H31 -> 203870

Sheet Vendor Bills and Payments
A1: A. Vendor bills (journal BILL)
A2: Matched to receipts (three-way match: PO - receipt - bill).
A3: Bill No | B3: Bill Date | C3: Month | D3: Vendor ID | E3: Vendor | F3: Purchase Order | G3: Receipt | H3: Vendor Reference | I3: Net (EGP) | J3: VAT (EGP) | K3: Total (EGP) | L3: Due Date | M3: Debit Notes (EGP) | N3: Payments Applied (EGP) | O3: Balance 30-Sep-2026 (EGP) | P3: Payment Status
A4: BILL/2026/00001 | B4: 46181 | C4: 2026-06 | D4: VEN-003 | E4: MediPlast Industries Egypt | F4: PO/2026/0004 | G4: CON/IN/00001 | H4: VINV-003-7554 | I4: 102828 | J4: 14395.92 | K4: =I4+J4 -> 117223.92 | L4: 46211 | M4: =SUMIFS('Customer and Supplier Returns'!$S$2:$S$12,'Customer and Supplier Returns'!$G$2:$G$12,A4,'Customer and Supplier Returns'!$B$2:$B$12,"Supplier return") -> 0 | N4: =SUMIFS('Vendor Bills and Payments'!$F$37:$F$54,'Vendor Bills and Payments'!$D$37:$D$54,A4) -> 117223.92 | O4: =K4-M4-N4 -> 0 | P4: =IF(ROUND(O4,2)=0,"Paid",IF(L4<DATE(2026,9,30),"Overdue","Open")) -> Paid
A5: BILL/2026/00002 | B5: 46182 | C5: 2026-06 | D5: VEN-001 | E5: Helios Medical Systems GmbH | F5: PO/2026/0001 | G5: EQP/IN/00001 | H5: VINV-001-9782 | I5: 378000 | J5: 52920 | K5: =I5+J5 -> 430920 | L5: 46242 | M5: =SUMIFS('Customer and Supplier Returns'!$S$2:$S$12,'Customer and Supplier Returns'!$G$2:$G$12,A5,'Customer and Supplier Returns'!$B$2:$B$12,"Supplier return") -> 0 | N5: =SUMIFS('Vendor Bills and Payments'!$F$37:$F$54,'Vendor Bills and Payments'!$D$37:$D$54,A5) -> 430920 | O5: =K5-M5-N5 -> 0 | P5: =IF(ROUND(O5,2)=0,"Paid",IF(L5<DATE(2026,9,30),"Overdue","Open")) -> Paid
A6: BILL/2026/00003 | B6: 46184 | C6: 2026-06 | D6: VEN-004 | E6: Pharos Surgical Supplies | F6: PO/2026/0005 | G6: CON/IN/00002 | H6: VINV-004-2553 | I6: 51240 | J6: 7173.6 | K6: =I6+J6 -> 58413.6 | L6: 46214 | M6: =SUMIFS('Customer and Supplier Returns'!$S$2:$S$12,'Customer and Supplier Returns'!$G$2:$G$12,A6,'Customer and Supplier Returns'!$B$2:$B$12,"Supplier return") -> 0 | N6: =SUMIFS('Vendor Bills and Payments'!$F$37:$F$54,'Vendor Bills and Payments'!$D$37:$D$54,A6) -> 58413.6 | O6: =K6-M6-N6 -> 0 | P6: =IF(ROUND(O6,2)=0,"Paid",IF(L6<DATE(2026,9,30),"Overdue","Open")) -> Paid
A7: BILL/2026/00004 | B7: 46189 | C7: 2026-06 | D7: VEN-001 | E7: Helios Medical Systems GmbH | F7: PO/2026/0002 | G7: EQP/IN/00002 | H7: VINV-001-2807 | I7: 252000 | J7: 35280 | K7: =I7+J7 -> 287280 | L7: 46249 | M7: =SUMIFS('Customer and Supplier Returns'!$S$2:$S$12,'Customer and Supplier Returns'!$G$2:$G$12,A7,'Customer and Supplier Returns'!$B$2:$B$12,"Supplier return") -> 0 | N7: =SUMIFS('Vendor Bills and Payments'!$F$37:$F$54,'Vendor Bills and Payments'!$D$37:$D$54,A7) -> 287280 | O7: =K7-M7-N7 -> 0 | P7: =IF(ROUND(O7,2)=0,"Paid",IF(L7<DATE(2026,9,30),"Overdue","Open")) -> Paid
A8: BILL/2026/00005 | B8: 46192 | C8: 2026-06 | D8: VEN-003 | E8: MediPlast Industries Egypt | F8: PO/2026/0006 | G8: CON/IN/00003 | H8: VINV-003-5243 | I8: 89205 | J8: 12488.7 | K8: =I8+J8 -> 101693.7 | L8: 46222 | M8: =SUMIFS('Customer and Supplier Returns'!$S$2:$S$12,'Customer and Supplier Returns'!$G$2:$G$12,A8,'Customer and Supplier Returns'!$B$2:$B$12,"Supplier return") -> 0 | N8: =SUMIFS('Vendor Bills and Payments'!$F$37:$F$54,'Vendor Bills and Payments'!$D$37:$D$54,A8) -> 101693.7 | O8: =K8-M8-N8 -> 0 | P8: =IF(ROUND(O8,2)=0,"Paid",IF(L8<DATE(2026,9,30),"Overdue","Open")) -> Paid
A9: BILL/2026/00006 | B9: 46193 | C9: 2026-06 | D9: VEN-001 | E9: Helios Medical Systems GmbH | F9: PO/2026/0003 | G9: EQP/IN/00003 | H9: VINV-001-5828 | I9: 333000 | J9: 46620 | K9: =I9+J9 -> 379620 | L9: 46253 | M9: =SUMIFS('Customer and Supplier Returns'!$S$2:$S$12,'Customer and Supplier Returns'!$G$2:$G$12,A9,'Customer and Supplier Returns'!$B$2:$B$12,"Supplier return") -> 0 | N9: =SUMIFS('Vendor Bills and Payments'!$F$37:$F$54,'Vendor Bills and Payments'!$D$37:$D$54,A9) -> 379620 | O9: =K9-M9-N9 -> 0 | P9: =IF(ROUND(O9,2)=0,"Paid",IF(L9<DATE(2026,9,30),"Overdue","Open")) -> Paid
A10: BILL/2026/00007 | B10: 46197 | C10: 2026-06 | D10: VEN-004 | E10: Pharos Surgical Supplies | F10: PO/2026/0009 | G10: CON/IN/00004 | H10: VINV-004-4822 | I10: 302940 | J10: 42411.6 | K10: =I10+J10 -> 345351.6 | L10: 46227 | M10: =SUMIFS('Customer and Supplier Returns'!$S$2:$S$12,'Customer and Supplier Returns'!$G$2:$G$12,A10,'Customer and Supplier Returns'!$B$2:$B$12,"Supplier return") -> 0 | N10: =SUMIFS('Vendor Bills and Payments'!$F$37:$F$54,'Vendor Bills and Payments'!$D$37:$D$54,A10) -> 345351.6 | O10: =K10-M10-N10 -> 0 | P10: =IF(ROUND(O10,2)=0,"Paid",IF(L10<DATE(2026,9,30),"Overdue","Open")) -> Paid
A11: BILL/2026/00008 | B11: 46202 | C11: 2026-06 | D11: VEN-004 | E11: Pharos Surgical Supplies | F11: PO/2026/0008 | G11: EQP/IN/00004 | H11: VINV-004-6829 | I11: 247500 | J11: 34650 | K11: =I11+J11 -> 282150 | L11: 46232 | M11: =SUMIFS('Customer and Supplier Returns'!$S$2:$S$12,'Customer and Supplier Returns'!$G$2:$G$12,A11,'Customer and Supplier Returns'!$B$2:$B$12,"Supplier return") -> 31350 | N11: =SUMIFS('Vendor Bills and Payments'!$F$37:$F$54,'Vendor Bills and Payments'!$D$37:$D$54,A11) -> 250800 | O11: =K11-M11-N11 -> 0 | P11: =IF(ROUND(O11,2)=0,"Paid",IF(L11<DATE(2026,9,30),"Overdue","Open")) -> Paid
A12: BILL/2026/00009 | B12: 46207 | C12: 2026-07 | D12: VEN-002 | E12: Orient Imaging Technologies Co. | F12: PO/2026/0007 | G12: EQP/IN/00005 | H12: VINV-002-9430 | I12: 18500000 | J12: 2590000 | K12: =I12+J12 -> 21090000 | L12: 46267 | M12: =SUMIFS('Customer and Supplier Returns'!$S$2:$S$12,'Customer and Supplier Returns'!$G$2:$G$12,A12,'Customer and Supplier Returns'!$B$2:$B$12,"Supplier return") -> 0 | N12: =SUMIFS('Vendor Bills and Payments'!$F$37:$F$54,'Vendor Bills and Payments'!$D$37:$D$54,A12) -> 21090000 | O12: =K12-M12-N12 -> 0 | P12: =IF(ROUND(O12,2)=0,"Paid",IF(L12<DATE(2026,9,30),"Overdue","Open")) -> Paid
A13: BILL/2026/00010 | B13: 46208 | C13: 2026-07 | D13: VEN-003 | E13: MediPlast Industries Egypt | F13: PO/2026/0011 | G13: CON/IN/00005 | H13: VINV-003-7359 | I13: 189515 | J13: 26532.1 | K13: =I13+J13 -> 216047.1 | L13: 46238 | M13: =SUMIFS('Customer and Supplier Returns'!$S$2:$S$12,'Customer and Supplier Returns'!$G$2:$G$12,A13,'Customer and Supplier Returns'!$B$2:$B$12,"Supplier return") -> 0 | N13: =SUMIFS('Vendor Bills and Payments'!$F$37:$F$54,'Vendor Bills and Payments'!$D$37:$D$54,A13) -> 216047.1 | O13: =K13-M13-N13 -> 0 | P13: =IF(ROUND(O13,2)=0,"Paid",IF(L13<DATE(2026,9,30),"Overdue","Open")) -> Paid
A14: BILL/2026/00011 | B14: 46219 | C14: 2026-07 | D14: VEN-005 | E14: Anatolia Biomed Distribution | F14: PO/2026/0010 | G14: EQP/IN/00006 | H14: VINV-005-8435 | I14: 113600 | J14: 15904 | K14: =I14+J14 -> 129504 | L14: 46264 | M14: =SUMIFS('Customer and Supplier Returns'!$S$2:$S$12,'Customer and Supplier Returns'!$G$2:$G$12,A14,'Customer and Supplier Returns'!$B$2:$B$12,"Supplier return") -> 0 | N14: =SUMIFS('Vendor Bills and Payments'!$F$37:$F$54,'Vendor Bills and Payments'!$D$37:$D$54,A14) -> 129504 | O14: =K14-M14-N14 -> 0 | P14: =IF(ROUND(O14,2)=0,"Paid",IF(L14<DATE(2026,9,30),"Overdue","Open")) -> Paid
A15: BILL/2026/00012 | B15: 46225 | C15: 2026-07 | D15: VEN-004 | E15: Pharos Surgical Supplies | F15: PO/2026/0013 | G15: CON/IN/00006 | H15: VINV-004-8431 | I15: 212520 | J15: 29752.8 | K15: =I15+J15 -> 242272.8 | L15: 46255 | M15: =SUMIFS('Customer and Supplier Returns'!$S$2:$S$12,'Customer and Supplier Returns'!$G$2:$G$12,A15,'Customer and Supplier Returns'!$B$2:$B$12,"Supplier return") -> 0 | N15: =SUMIFS('Vendor Bills and Payments'!$F$37:$F$54,'Vendor Bills and Payments'!$D$37:$D$54,A15) -> 242272.8 | O15: =K15-M15-N15 -> 0 | P15: =IF(ROUND(O15,2)=0,"Paid",IF(L15<DATE(2026,9,30),"Overdue","Open")) -> Paid
... A31: BILL/2026/00028 | B31: 46295 | C31: 2026-09 | D31: VEN-005 | E31: Anatolia Biomed Distribution | F31: PO/2026/0023 | G31: EQP/IN/00013 | H31: VINV-005-5682 | I31: 472000 | J31: 66080 | K31: =I31+J31 -> 538080 | L31: 46340 | M31: =SUMIFS('Customer and Supplier Returns'!$S$2:$S$12,'Customer and Supplier Returns'!$G$2:$G$12,A31,'Customer and Supplier Returns'!$B$2:$B$12,"Supplier return") -> 0 | N31: =SUMIFS('Vendor Bills and Payments'!$F$37:$F$54,'Vendor Bills and Payments'!$D$37:$D$54,A31) -> 0 | O31: =K31-M31-N31 -> 538080 | P31: =IF(ROUND(O31,2)=0,"Paid",IF(L31<DATE(2026,9,30),"Overdue","Open")) -> Open
H32: Totals | I32: =SUM(I4:I31) -> 24579359 | J32: =SUM(J4:J31) -> 3441110.3 | K32: =SUM(K4:K31) -> 28020469 | M32: =SUM(M4:M31) -> 35482.5 | N32: =SUM(N4:N31) -> 25322248 | O32: =SUM(O4:O31) -> 2662739
A34: B. Vendor payments (journals CIB1 / NBE1)
A35: Payments are net of any debit notes on the bill.
A36: Payment No | B36: Payment Date | C36: Vendor ID | D36: Applied to Bill | E36: Vendor | F36: Amount (EGP) | G36: Method | H36: Journal | I36: Month
A37: NBE1/OUT/2026/0001 | B37: 46205 | C37: VEN-003 | D37: BILL/2026/00001 | E37: MediPlast Industries Egypt | F37: 117223.92 | G37: Bank transfer | H37: NBE1 | I37: 2026-07
A38: NBE1/OUT/2026/0002 | B38: 46209 | C38: VEN-004 | D38: BILL/2026/00003 | E38: Pharos Surgical Supplies | F38: 58413.6 | G38: Bank transfer | H38: NBE1 | I38: 2026-07
A39: NBE1/OUT/2026/0003 | B39: 46215 | C39: VEN-003 | D39: BILL/2026/00005 | E39: MediPlast Industries Egypt | F39: 101693.7 | G39: Bank transfer | H39: NBE1 | I39: 2026-07
A40: NBE1/OUT/2026/0004 | B40: 46223 | C40: VEN-004 | D40: BILL/2026/00007 | E40: Pharos Surgical Supplies | F40: 345351.6 | G40: Bank transfer | H40: NBE1 | I40: 2026-07
A41: NBE1/OUT/2026/0005 | B41: 46236 | C41: VEN-004 | D41: BILL/2026/00008 | E41: Pharos Surgical Supplies | F41: 250800 | G41: Bank transfer | H41: NBE1 | I41: 2026-08
A42: CIB1/OUT/2026/0001 | B42: 46237 | C42: VEN-001 | D42: BILL/2026/00002 | E42: Helios Medical Systems GmbH | F42: 430920 | G42: Bank transfer | H42: CIB1 | I42: 2026-08
A43: NBE1/OUT/2026/0006 | B43: 46237 | C43: VEN-003 | D43: BILL/2026/00010 | E43: MediPlast Industries Egypt | F43: 216047.1 | G43: Bank transfer | H43: NBE1 | I43: 2026-08
A44: CIB1/OUT/2026/0002 | B44: 46244 | C44: VEN-001 | D44: BILL/2026/00004 | E44: Helios Medical Systems GmbH | F44: 287280 | G44: Bank transfer | H44: CIB1 | I44: 2026-08
A45: CIB1/OUT/2026/0003 | B45: 46246 | C45: VEN-001 | D45: BILL/2026/00006 | E45: Helios Medical Systems GmbH | F45: 379620 | G45: Bank transfer | H45: CIB1 | I45: 2026-08
A46: NBE1/OUT/2026/0007 | B46: 46257 | C46: VEN-004 | D46: BILL/2026/00012 | E46: Pharos Surgical Supplies | F46: 242272.8 | G46: Bank transfer | H46: NBE1 | I46: 2026-08
A47: NBE1/OUT/2026/0008 | B47: 46264 | C47: VEN-003 | D47: BILL/2026/00016 | E47: MediPlast Industries Egypt | F47: 291349.8 | G47: Bank transfer | H47: NBE1 | I47: 2026-08
A48: CIB1/OUT/2026/0004 | B48: 46266 | C48: VEN-005 | D48: BILL/2026/00011 | E48: Anatolia Biomed Distribution | F48: 129504 | G48: Bank transfer | H48: CIB1 | I48: 2026-09
... A54: CIB1/OUT/2026/0007 | B54: 46292 | C54: VEN-001 | D54: BILL/2026/00014 | E54: Helios Medical Systems GmbH | F54: 558600 | G54: Bank transfer | H54: CIB1 | I54: 2026-09
E55: Total payments | F55: =SUM(F37:F54) -> 25322248

Sheet Delivery and Receipt Records
A1: Document No | B1: Type | C1: Date | D1: Warehouse | E1: Order Ref | F1: Partner ID | G1: Product Ref | H1: Product | I1: Qty | J1: UoM | K1: Lots / Serials | L1: Invoice / Bill
A2: CON/OUT/00001 | B2: Delivery | C2: 46154 | D2: CON | E2: SO/2026/0001 | F2: CUS-001 | G2: CN-MSK-001 | H2: Surgical Face Mask 3-Ply (Box of 50) | I2: 494 | J2: Box | K2: LOT-MSK-2602A1 x494 | L2: INV/2026/00001
A3: CON/OUT/00002 | B3: Delivery | C3: 46155 | D3: CON | E3: SO/2026/0004 | F3: CUS-002 | G3: CN-MSK-001 | H3: Surgical Face Mask 3-Ply (Box of 50) | I3: 240 | J3: Box | K3: LOT-MSK-2602A1 x240 | L3: INV/2026/00005
A4: CON/OUT/00002 | B4: Delivery | C4: 46155 | D4: CON | E4: SO/2026/0004 | F4: CUS-002 | G4: CN-GLV-001 | H4: Nitrile Examination Gloves, Medium (Box of 100) | I4: 247 | J4: Box | K4: LOT-GLV-2603A1 x247 | L4: INV/2026/00005
A5: CON/OUT/00003 | B5: Delivery | C5: 46156 | D5: CON | E5: SO/2026/0006 | F5: CUS-013 | G5: CN-GLV-001 | H5: Nitrile Examination Gloves, Medium (Box of 100) | I5: 12 | J5: Box | K5: LOT-GLV-2603A1 x12 | L5: INV/2026/00004
A6: CON/OUT/00004 | B6: Delivery | C6: 46159 | D6: CON | E6: SO/2026/0003 | F6: CUS-005 | G6: CN-SYR-001 | H6: Disposable Syringe 5 ml (Box of 100) | I6: 134 | J6: Box | K6: LOT-SYR-2603A1 x134 | L6: INV/2026/00007
A7: CON/OUT/00005 | B7: Delivery | C7: 46161 | D7: CON | E7: SO/2026/0008 | F7: CUS-010 | G7: CN-ECE-001 | H7: ECG Electrodes (Pack of 50) | I7: 62 | J7: Pack | K7: LOT-ECE-2603A1 x62 | L7: INV/2026/00006
A8: CON/OUT/00005 | B8: Delivery | C8: 46161 | D8: CON | E8: SO/2026/0008 | F8: CUS-010 | G8: CN-IVS-001 | H8: IV Infusion Set (Box of 25) | I8: 180 | J8: Box | K8: LOT-IVS-2512A1 x180 | L8: INV/2026/00006
A9: CON/OUT/00006 | B9: Delivery | C9: 46166 | D9: CON | E9: SO/2026/0007 | F9: CUS-009 | G9: CN-ECE-001 | H9: ECG Electrodes (Pack of 50) | I9: 98 | J9: Pack | K9: LOT-ECE-2603A1 x98 | L9: INV/2026/00009
A10: CON/OUT/00006 | B10: Delivery | C10: 46166 | D10: CON | E10: SO/2026/0007 | F10: CUS-009 | G10: CN-PAD-001 | H10: Defibrillator Pads, Adult (Pair) | I10: 10 | J10: Pair | K10: LOT-PAD-2602A1 x10 | L10: INV/2026/00009
A11: CON/OUT/00007 | B11: Delivery | C11: 46166 | D11: CON | E11: SO/2026/0009 | F11: CUS-013 | G11: CN-GLV-001 | H11: Nitrile Examination Gloves, Medium (Box of 100) | I11: 4 | J11: Box | K11: LOT-GLV-2603A1 x4 | L11: INV/2026/00008
A12: CON/OUT/00007 | B12: Delivery | C12: 46166 | D12: CON | E12: SO/2026/0009 | F12: CUS-013 | G12: CN-SYR-001 | H12: Disposable Syringe 5 ml (Box of 100) | I12: 11 | J12: Box | K12: LOT-SYR-2603A1 x11 | L12: INV/2026/00008
A13: CON/OUT/00008 | B13: Delivery | C13: 46168 | D13: CON | E13: SO/2026/0010 | F13: CUS-013 | G13: CN-GLV-001 | H13: Nitrile Examination Gloves, Medium (Box of 100) | I13: 4 | J13: Box | K13: LOT-GLV-2603A1 x4 | L13: INV/2026/00010
... A231: SPR/IN/00004 | B231: Receipt | C231: 46280 | D231: SPR | E231: PO/2026/0022 | F231: VEN-006 | G231: SP-FIL-001 | H231: Replacement HEPA Air Filter (Box of 5) | I231: 58 | J231: Box | K231: LOT-FIL-2609D4 x58 | L231: BILL/2026/00026

Sheet Customer and Supplier Returns
A1: Return No | B1: Return Type | C1: Date | D1: Partner ID | E1: Partner | F1: Order Ref | G1: Invoice / Bill Ref | H1: Product Ref | I1: Product | J1: Lot / Serial | K1: Qty | L1: Reason | M1: Via Warehouse | N1: Outcome | O1: Credit / Debit Note | P1: Note Date | Q1: Note Net (EGP) | R1: Note VAT (EGP) | S1: Note Total (EGP)
A2: QRT/RET/0001 | B2: Customer return | C2: 46189 | D2: CUS-005 | E2: Nasr City Family Clinics | F2: SO/2026/0003 | G2: INV/2026/00007 | H2: CN-SYR-001 | I2: Disposable Syringe 5 ml (Box of 100) | J2: LOT-SYR-2603A1 | K2: 13 | L2: Damaged in transit | M2: QRT | N2: Scrapped | O2: RINV/2026/00001 | P2: 46191 | Q2: 2535 | R2: 354.9 | S2: =Q2+R2 -> 2889.9
A3: QRT/RET/0002 | B3: Customer return | C3: 46191 | D3: CUS-002 | E3: Nile Valley Medical Center | F3: SO/2026/0020 | G3: INV/2026/00022 | H3: EQ-INF-001 | I3: Infusion Pump (Volumetric) | J3: SN-INF-2603-0002 | K3: 1 | L3: Dead on arrival (DOA) | M3: QRT | N3: Scrapped | O3: RINV/2026/00002 | P3: 46193 | Q3: 23280 | R3: 3259.2 | S3: =Q3+R3 -> 26539.2
A4: QRT/RET/0003 | B4: Customer return | C4: 46209 | D4: CUS-005 | E4: Nasr City Family Clinics | F4: SO/2026/0028 | G4: INV/2026/00028 | H4: SP-SPO-001 | I4: SpO2 Sensor, Adult Reusable | J4: NOLOT-SP-SPO-001 | K4: 1 | L4: Damaged in transit | M4: QRT | N4: Scrapped | O4: RINV/2026/00003 | P4: 46210 | Q4: 1750 | R4: 245 | S4: =Q4+R4 -> 1995
A5: QRT/RET/0004 | B5: Customer return | C5: 46216 | D5: CUS-001 | E5: Al Salam Teaching Hospital | F5: SO/2026/0031 | G5: INV/2026/00030 | H5: CN-ECE-001 | I5: ECG Electrodes (Pack of 50) | J5: LOT-ECE-2606C3 | K5: 5 | L5: Dead on arrival (DOA) | M5: QRT | N5: Scrapped | O5: RINV/2026/00004 | P5: 46218 | Q5: 824.5 | R5: 115.43 | S5: =Q5+R5 -> 939.93
A6: QRT/RET/0005 | B6: Customer return | C6: 46218 | D6: CUS-009 | E6: Upper Egypt Medical Complex | F6: SO/2026/0032 | G6: INV/2026/00032 | H6: SP-FIL-001 | I6: Replacement HEPA Air Filter (Box of 5) | J6: LOT-FIL-2601B2 | K6: 1 | L6: Packaging breach | M6: QRT | N6: Scrapped | O6: RINV/2026/00005 | P6: 46220 | Q6: 608 | R6: 85.12 | S6: =Q6+R6 -> 693.12
A7: QRT/RET/0006 | B7: Customer return | C7: 46222 | D7: CUS-012 | E7: Zagazig Dialysis Center | F7: SO/2026/0034 | G7: INV/2026/00034 | H7: CN-IVS-001 | I7: IV Infusion Set (Box of 25) | J7: LOT-IVS-2512A1 | K7: 10 | L7: Damaged in transit | M7: QRT | N7: Scrapped | O7: RINV/2026/00006 | P7: 46224 | Q7: 2900 | R7: 406 | S7: =Q7+R7 -> 3306
A8: QRT/RET/0007 | B8: Customer return | C8: 46236 | D8: CUS-006 | E8: Heliopolis Diagnostic Laboratories | F8: SO/2026/0044 | G8: INV/2026/00042 | H8: CN-TUB-001 | I8: Medical Silicone Tubing 8 mm (Roll of 25 m) | J8: LOT-TUB-2512A1 | K8: 1 | L8: Excess quantity / order change | M8: QRT | N8: Restocked | O8: RINV/2026/00007 | P8: 46238 | Q8: 1029 | R8: 144.06 | S8: =Q8+R8 -> 1173.06
A9: QRT/RET/0008 | B9: Customer return | C9: 46236 | D9: CUS-001 | E9: Al Salam Teaching Hospital | F9: SO/2026/0043 | G9: INV/2026/00041 | H9: CN-ECE-001 | I9: ECG Electrodes (Pack of 50) | J9: LOT-ECE-2606C3 | K9: 8 | L9: Wrong item delivered | M9: QRT | N9: Restocked | O9: RINV/2026/00008 | P9: 46238 | Q9: 1319.2 | R9: 184.69 | S9: =Q9+R9 -> 1503.89
A10: QRT/RET/0009 | B10: Customer return | C10: 46288 | D10: CUS-002 | E10: Nile Valley Medical Center | F10: SO/2026/0068 | G10: INV/2026/00069 | H10: EQ-USG-001 | I10: Ultrasound System (Colour Doppler) | J10: SN-USG-2603-0003 | K10: 1 | L10: Excess quantity / order change | M10: QRT | N10: Restocked | O10: RINV/2026/00009 | P10: 46288 | Q10: 809950 | R10: 113393 | S10: =Q10+R10 -> 923343
A11: QRT/SRET/0001 | B11: Supplier return | C11: 46208 | D11: VEN-004 | E11: Pharos Surgical Supplies | F11: PO/2026/0008 | G11: BILL/2026/00008 | H11: EQ-SUR-001 | I11: Surgical Instrument Set (General Surgery, 120 pcs) | J11: SN-SUR-2606-0017 | K11: 1 | L11: Failed incoming inspection (QC) | M11: QRT | N11: Returned to vendor | O11: RBILL/2026/00001 | P11: 46210 | Q11: 27500 | R11: 3850 | S11: =Q11+R11 -> 31350
A12: QRT/SRET/0002 | B12: Supplier return | C12: 46247 | D12: VEN-003 | E12: MediPlast Industries Egypt | F12: PO/2026/0016 | G12: BILL/2026/00018 | H12: CN-SYR-001 | I12: Disposable Syringe 5 ml (Box of 100) | J12: LOT-SYR-2608E5 | K12: 25 | L12: Failed incoming inspection (QC) | M12: QRT | N12: Returned to vendor | O12: RBILL/2026/00002 | P12: 46249 | Q12: 3625 | R12: 507.5 | S12: =Q12+R12 -> 4132.5

Sheet Monthly Business Summary
A1: Month Key | B1: Month | C1: Sales Net (EGP) | D1: Output VAT (EGP) | E1: Credit Notes Net (EGP) | F1: Net Sales (EGP) | G1: COGS (EGP, ledger) | H1: Gross Profit (EGP) | I1: Gross Margin % | J1: Purchases Net (EGP) | K1: Input VAT (EGP) | L1: Customer Receipts (EGP) | M1: Vendor Payments (EGP) | N1: Receivables at Month-end (EGP) | O1: Payables at Month-end (EGP) | P1: Inventory Value at Month-end (EGP, ledger) | Q1: Sales Orders Created | R1: Purchase Orders Created
A2: 2026-05 | B2: May 2026 | C2: =SUMIFS('Customer Invoices and Payments'!$G$4:$G$85,'Customer Invoices and Payments'!$C$4:$C$85,A2) -> 968141.34 | D2: =SUMIFS('Customer Invoices and Payments'!$H$4:$H$85,'Customer Invoices and Payments'!$C$4:$C$85,A2) -> 135539.78 | E2: =SUMIFS('Customer and Supplier Returns'!$Q$2:$Q$12,'Customer and Supplier Returns'!$B$2:$B$12,"Customer return",'Customer and Supplier Returns'!$P$2:$P$12,">="&DATE(2026,5,1),'Customer and Supplier Returns'!$P$2:$P$12,"<="&DATE(2026,5,31)) -> 0 | F2: =C2-E2 -> 968141.34 | G2: 728418 | H2: =F2-G2 -> 239723.34 | I2: =IF(F2=0,0,H2/F2) -> 0.24761192 | J2: =SUMIFS('Vendor Bills and Payments'!$I$4:$I$31,'Vendor Bills and Payments'!$C$4:$C$31,A2) -> 0 | K2: =SUMIFS('Vendor Bills and Payments'!$J$4:$J$31,'Vendor Bills and Payments'!$C$4:$C$31,A2) -> 0 | L2: =SUMIFS('Customer Invoices and Payments'!$F$91:$F$152,'Customer Invoices and Payments'!$B$91:$B$152,">="&DATE(2026,5,1),'Customer Invoices and Payments'!$B$91:$B$152,"<="&DATE(2026,5,31)) -> 11679.3 | M2: =SUMIFS('Vendor Bills and Payments'!$F$37:$F$54,'Vendor Bills and Payments'!$B$37:$B$54,">="&DATE(2026,5,1),'Vendor Bills and Payments'!$B$37:$B$54,"<="&DATE(2026,5,31)) -> 0 | N2: =SUMIFS('Customer Invoices and Payments'!$I$4:$I$85,'Customer Invoices and Payments'!$B$4:$B$85,"<="&DATE(2026,5,31))-SUMIFS('Customer and Supplier Returns'!$S$2:$S$12,'Customer and Supplier Returns'!$B$2:$B$12,"Customer return",'Customer and Supplier Returns'!$P$2:$P$12,"<="&DATE(2026,5,31))-SUMIFS('Customer Invoices and Payments'!$F$91:$F$152,'Customer Invoices and Payments'!$B$91:$B$152,"<="&DATE(2026,5,31)) -> 1092001.8 | O2: =SUMIFS('Vendor Bills and Payments'!$K$4:$K$31,'Vendor Bills and Payments'!$B$4:$B$31,"<="&DATE(2026,5,31))-SUMIFS('Customer and Supplier Returns'!$S$2:$S$12,'Customer and Supplier Returns'!$B$2:$B$12,"Supplier return",'Customer and Supplier Returns'!$P$2:$P$12,"<="&DATE(2026,5,31))-SUMIFS('Vendor Bills and Payments'!$F$37:$F$54,'Vendor Bills and Payments'!$B$37:$B$54,"<="&DATE(2026,5,31)) -> 0 | P2: 23441782 | Q2: 16 | R2: 5
A3: 2026-06 | B3: Jun 2026 | C3: =SUMIFS('Customer Invoices and Payments'!$G$4:$G$85,'Customer Invoices and Payments'!$C$4:$C$85,A3) -> 1115048.5 | D3: =SUMIFS('Customer Invoices and Payments'!$H$4:$H$85,'Customer Invoices and Payments'!$C$4:$C$85,A3) -> 156106.79 | E3: =SUMIFS('Customer and Supplier Returns'!$Q$2:$Q$12,'Customer and Supplier Returns'!$B$2:$B$12,"Customer return",'Customer and Supplier Returns'!$P$2:$P$12,">="&DATE(2026,6,1),'Customer and Supplier Returns'!$P$2:$P$12,"<="&DATE(2026,6,30)) -> 25815 | F3: =C3-E3 -> 1089233.5 | G3: 818769 | H3: =F3-G3 -> 270464.49 | I3: =IF(F3=0,0,H3/F3) -> 0.24830717 | J3: =SUMIFS('Vendor Bills and Payments'!$I$4:$I$31,'Vendor Bills and Payments'!$C$4:$C$31,A3) -> 1756713 | K3: =SUMIFS('Vendor Bills and Payments'!$J$4:$J$31,'Vendor Bills and Payments'!$C$4:$C$31,A3) -> 245939.82 | L3: =SUMIFS('Customer Invoices and Payments'!$F$91:$F$152,'Customer Invoices and Payments'!$B$91:$B$152,">="&DATE(2026,6,1),'Customer Invoices and Payments'!$B$91:$B$152,"<="&DATE(2026,6,30)) -> 477580.47 | M3: =SUMIFS('Vendor Bills and Payments'!$F$37:$F$54,'Vendor Bills and Payments'!$B$37:$B$54,">="&DATE(2026,6,1),'Vendor Bills and Payments'!$B$37:$B$54,"<="&DATE(2026,6,30)) -> 0 | N3: =SUMIFS('Customer Invoices and Payments'!$I$4:$I$85,'Customer Invoices and Payments'!$B$4:$B$85,"<="&DATE(2026,6,30))-SUMIFS('Customer and Supplier Returns'!$S$2:$S$12,'Customer and Supplier Returns'!$B$2:$B$12,"Customer return",'Customer and Supplier Returns'!$P$2:$P$12,"<="&DATE(2026,6,30))-SUMIFS('Customer Invoices and Payments'!$F$91:$F$152,'Customer Invoices and Payments'!$B$91:$B$152,"<="&DATE(2026,6,30)) -> 1856147.5 | O3: =SUMIFS('Vendor Bills and Payments'!$K$4:$K$31,'Vendor Bills and Payments'!$B$4:$B$31,"<="&DATE(2026,6,30))-SUMIFS('Customer and Supplier Returns'!$S$2:$S$12,'Customer and Supplier Returns'!$B$2:$B$12,"Supplier return",'Customer and Supplier Returns'!$P$2:$P$12,"<="&DATE(2026,6,30))-SUMIFS('Vendor Bills and Payments'!$F$37:$F$54,'Vendor Bills and Payments'!$B$37:$B$54,"<="&DATE(2026,6,30)) -> 2002652.8 | P3: 24315081 | Q3: 16 | R3: 6
A4: 2026-07 | B4: Jul 2026 | C4: =SUMIFS('Customer Invoices and Payments'!$G$4:$G$85,'Customer Invoices and Payments'!$C$4:$C$85,A4) -> 1755623.1 | D4: =SUMIFS('Customer Invoices and Payments'!$H$4:$H$85,'Customer Invoices and Payments'!$C$4:$C$85,A4) -> 245787.23 | E4: =SUMIFS('Customer and Supplier Returns'!$Q$2:$Q$12,'Customer and Supplier Returns'!$B$2:$B$12,"Customer return",'Customer and Supplier Returns'!$P$2:$P$12,">="&DATE(2026,7,1),'Customer and Supplier Returns'!$P$2:$P$12,"<="&DATE(2026,7,31)) -> 6082.5 | F4: =C4-E4 -> 1749540.6 | G4: 1344255 | H4: =F4-G4 -> 405285.57 | I4: =IF(F4=0,0,H4/F4) -> 0.23165257 | J4: =SUMIFS('Vendor Bills and Payments'!$I$4:$I$31,'Vendor Bills and Payments'!$C$4:$C$31,A4) -> 19590835 | K4: =SUMIFS('Vendor Bills and Payments'!$J$4:$J$31,'Vendor Bills and Payments'!$C$4:$C$31,A4) -> 2742716.9 | L4: =SUMIFS('Customer Invoices and Payments'!$F$91:$F$152,'Customer Invoices and Payments'!$B$91:$B$152,">="&DATE(2026,7,1),'Customer Invoices and Payments'!$B$91:$B$152,"<="&DATE(2026,7,31)) -> 1023803 | M4: =SUMIFS('Vendor Bills and Payments'!$F$37:$F$54,'Vendor Bills and Payments'!$B$37:$B$54,">="&DATE(2026,7,1),'Vendor Bills and Payments'!$B$37:$B$54,"<="&DATE(2026,7,31)) -> 622682.82 | N4: =SUMIFS('Customer Invoices and Payments'!$I$4:$I$85,'Customer Invoices and Payments'!$B$4:$B$85,"<="&DATE(2026,7,31))-SUMIFS('Customer and Supplier Returns'!$S$2:$S$12,'Customer and Supplier Returns'!$B$2:$B$12,"Customer return",'Customer and Supplier Returns'!$P$2:$P$12,"<="&DATE(2026,7,31))-SUMIFS('Customer Invoices and Payments'!$F$91:$F$152,'Customer Invoices and Payments'!$B$91:$B$152,"<="&DATE(2026,7,31)) -> 2826820.7 | O4: =SUMIFS('Vendor Bills and Payments'!$K$4:$K$31,'Vendor Bills and Payments'!$B$4:$B$31,"<="&DATE(2026,7,31))-SUMIFS('Customer and Supplier Returns'!$S$2:$S$12,'Customer and Supplier Returns'!$B$2:$B$12,"Supplier return",'Customer and Supplier Returns'!$P$2:$P$12,"<="&DATE(2026,7,31))-SUMIFS('Vendor Bills and Payments'!$F$37:$F$54,'Vendor Bills and Payments'!$B$37:$B$54,"<="&DATE(2026,7,31)) -> 23682172 | P4: 42626831 | Q4: 19 | R4: 5
A5: 2026-08 | B5: Aug 2026 | C5: =SUMIFS('Customer Invoices and Payments'!$G$4:$G$85,'Customer Invoices and Payments'!$C$4:$C$85,A5) -> 24961163 | D5: =SUMIFS('Customer Invoices and Payments'!$H$4:$H$85,'Customer Invoices and Payments'!$C$4:$C$85,A5) -> 3494562.8 | E5: =SUMIFS('Customer and Supplier Returns'!$Q$2:$Q$12,'Customer and Supplier Returns'!$B$2:$B$12,"Customer return",'Customer and Supplier Returns'!$P$2:$P$12,">="&DATE(2026,8,1),'Customer and Supplier Returns'!$P$2:$P$12,"<="&DATE(2026,8,31)) -> 2348.2 | F5: =C5-E5 -> 24958814 | G5: 19901701 | H5: =F5-G5 -> 5057113.4 | I5: =IF(F5=0,0,H5/F5) -> 0.20261834 | J5: =SUMIFS('Vendor Bills and Payments'!$I$4:$I$31,'Vendor Bills and Payments'!$C$4:$C$31,A5) -> 1173575 | K5: =SUMIFS('Vendor Bills and Payments'!$J$4:$J$31,'Vendor Bills and Payments'!$C$4:$C$31,A5) -> 164300.5 | L5: =SUMIFS('Customer Invoices and Payments'!$F$91:$F$152,'Customer Invoices and Payments'!$B$91:$B$152,">="&DATE(2026,8,1),'Customer Invoices and Payments'!$B$91:$B$152,"<="&DATE(2026,8,31)) -> 1858830.3 | M5: =SUMIFS('Vendor Bills and Payments'!$F$37:$F$54,'Vendor Bills and Payments'!$B$37:$B$54,">="&DATE(2026,8,1),'Vendor Bills and Payments'!$B$37:$B$54,"<="&DATE(2026,8,31)) -> 2098289.7 | N5: =SUMIFS('Customer Invoices and Payments'!$I$4:$I$85,'Customer Invoices and Payments'!$B$4:$B$85,"<="&DATE(2026,8,31))-SUMIFS('Customer and Supplier Returns'!$S$2:$S$12,'Customer and Supplier Returns'!$B$2:$B$12,"Customer return",'Customer and Supplier Returns'!$P$2:$P$12,"<="&DATE(2026,8,31))-SUMIFS('Customer Invoices and Payments'!$F$91:$F$152,'Customer Invoices and Payments'!$B$91:$B$152,"<="&DATE(2026,8,31)) -> 29421039 | O5: =SUMIFS('Vendor Bills and Payments'!$K$4:$K$31,'Vendor Bills and Payments'!$B$4:$B$31,"<="&DATE(2026,8,31))-SUMIFS('Customer and Supplier Returns'!$S$2:$S$12,'Customer and Supplier Returns'!$B$2:$B$12,"Supplier return",'Customer and Supplier Returns'!$P$2:$P$12,"<="&DATE(2026,8,31))-SUMIFS('Vendor Bills and Payments'!$F$37:$F$54,'Vendor Bills and Payments'!$B$37:$B$54,"<="&DATE(2026,8,31)) -> 22917625 | P5: 23506735 | Q5: 18 | R5: 6
A6: 2026-09 | B6: Sep 2026 | C6: =SUMIFS('Customer Invoices and Payments'!$G$4:$G$85,'Customer Invoices and Payments'!$C$4:$C$85,A6) -> 2277452.4 | D6: =SUMIFS('Customer Invoices and Payments'!$H$4:$H$85,'Customer Invoices and Payments'!$C$4:$C$85,A6) -> 318843.34 | E6: =SUMIFS('Customer and Supplier Returns'!$Q$2:$Q$12,'Customer and Supplier Returns'!$B$2:$B$12,"Customer return",'Customer and Supplier Returns'!$P$2:$P$12,">="&DATE(2026,9,1),'Customer and Supplier Returns'!$P$2:$P$12,"<="&DATE(2026,9,30)) -> 809950 | F6: =C6-E6 -> 1467502.4 | G6: 1109823 | H6: =F6-G6 -> 357679.4 | I6: =IF(F6=0,0,H6/F6) -> 0.24373343 | J6: =SUMIFS('Vendor Bills and Payments'!$I$4:$I$31,'Vendor Bills and Payments'!$C$4:$C$31,A6) -> 2058236 | K6: =SUMIFS('Vendor Bills and Payments'!$J$4:$J$31,'Vendor Bills and Payments'!$C$4:$C$31,A6) -> 288153.04 | L6: =SUMIFS('Customer Invoices and Payments'!$F$91:$F$152,'Customer Invoices and Payments'!$B$91:$B$152,">="&DATE(2026,9,1),'Customer Invoices and Payments'!$B$91:$B$152,"<="&DATE(2026,9,30)) -> 1561918.2 | M6: =SUMIFS('Vendor Bills and Payments'!$F$37:$F$54,'Vendor Bills and Payments'!$B$37:$B$54,">="&DATE(2026,9,1),'Vendor Bills and Payments'!$B$37:$B$54,"<="&DATE(2026,9,30)) -> 22601275 | N6: =SUMIFS('Customer Invoices and Payments'!$I$4:$I$85,'Customer Invoices and Payments'!$B$4:$B$85,"<="&DATE(2026,9,30))-SUMIFS('Customer and Supplier Returns'!$S$2:$S$12,'Customer and Supplier Returns'!$B$2:$B$12,"Customer return",'Customer and Supplier Returns'!$P$2:$P$12,"<="&DATE(2026,9,30))-SUMIFS('Customer Invoices and Payments'!$F$91:$F$152,'Customer Invoices and Payments'!$B$91:$B$152,"<="&DATE(2026,9,30)) -> 29532073 | O6: =SUMIFS('Vendor Bills and Payments'!$K$4:$K$31,'Vendor Bills and Payments'!$B$4:$B$31,"<="&DATE(2026,9,30))-SUMIFS('Customer and Supplier Returns'!$S$2:$S$12,'Customer and Supplier Returns'!$B$2:$B$12,"Supplier return",'Customer and Supplier Returns'!$P$2:$P$12,"<="&DATE(2026,9,30))-SUMIFS('Vendor Bills and Payments'!$F$37:$F$54,'Vendor Bills and Payments'!$B$37:$B$54,"<="&DATE(2026,9,30)) -> 2662739 | P6: 24536323 | Q6: 18 | R6: 5
B7: Five-month total | C7: =SUM(C2:C6) -> 31077428 | D7: =SUM(D2:D6) -> 4350839.9 | E7: =SUM(E2:E6) -> 844195.7 | F7: =SUM(F2:F6) -> 30233232 | G7: =SUM(G2:G6) -> 23902966 | H7: =SUM(H2:H6) -> 6330266.2 | I7: =IF(F7=0,0,H7/F7) -> 0.20938106 | J7: =SUM(J2:J6) -> 24579359 | K7: =SUM(K2:K6) -> 3441110.3 | L7: =SUM(L2:L6) -> 4933811.3 | M7: =SUM(M2:M6) -> 25322248
B9: Notes
B10: COGS and inventory value come from the simulated stock-valuation ledger (FIFO = constant vendor cost). Gross profit is stated before inventory write-offs (scrap, expiry, count adjustments), which are shown separately in the Transaction Reconciliation sheet.
B11: Receivables/payables at month-end are computed by formula from invoices, credit/debit notes and payments dated on or before month-end.

Sheet Transaction Reconciliation
A1: Structural and arithmetic reconciliation of the simulated records
A2: Structural/mathematical validation only; it is not a functional test on a live Odoo server.
A3: Check ID | B3: Control | C3: Value A | D3: Value B (independent) | E3: Difference | F3: Result | G3: Unit | H3: Comment
A4: C01 | B4: Delivered qty on sales-order lines = qty on delivery records | C4: =SUM('Sales Order Lines'!$F$2:$F$207) -> 17011 | D4: =SUMIFS('Delivery and Receipt Records'!$I$2:$I$231,'Delivery and Receipt Records'!$B$2:$B$231,"Delivery") -> 17011 | E4: =ROUND(C4-D4,2) -> 0 | F4: =IF(E4=0,"PASS","CHECK") -> PASS | G4: Quantities | H4: Order-to-delivery
A5: C02 | B5: Invoiced qty <= delivered qty (difference = delivered, invoice dated after period end) | C5: =SUM('Sales Order Lines'!$G$2:$G$207) -> 16333 | D5: =SUM('Sales Order Lines'!$F$2:$F$207) -> 17011 | E5: =ROUND(C5-D5,2) -> -678 | F5: =IF(E5=0,"PASS","EXPLAINED - see note") -> EXPLAINED - see note | G5: Quantities | H5: Delivery-to-invoice; a non-zero difference is documented below and is expected only for late-September deliveries
A6: C03 | B6: Received qty on PO lines = qty on receipt records | C6: =SUM('Purchase Order Lines'!$F$2:$F$31) -> 16087 | D6: =SUMIFS('Delivery and Receipt Records'!$I$2:$I$231,'Delivery and Receipt Records'!$B$2:$B$231,"Receipt") -> 16087 | E6: =ROUND(C6-D6,2) -> 0 | F6: =IF(E6=0,"PASS","CHECK") -> PASS | G6: Quantities | H6: PO-to-receipt
A7: C04 | B7: Invoice totals = Net + VAT (sum of table A) | C7: =SUM('Customer Invoices and Payments'!$I$4:$I$85) -> 35428268 | D7: =SUM('Customer Invoices and Payments'!$G$4:$G$85)+SUM('Customer Invoices and Payments'!$H$4:$H$85) -> 35428268 | E7: =ROUND(C7-D7,2) -> 0 | F7: =IF(E7=0,"PASS","CHECK") -> PASS | G7: EGP | H7: Arithmetic
A8: C05 | B8: Invoiced net = sum of invoiced qty × unit price on SO lines | C8: =SUM('Customer Invoices and Payments'!$G$4:$G$85) -> 31077428 | D8: =SUMPRODUCT('Sales Order Lines'!$G$2:$G$207,'Sales Order Lines'!$I$2:$I$207) -> 31077428 | E8: =ROUND(C8-D8,2) -> 0 | F8: =IF(E8=0,"PASS","CHECK") -> PASS | G8: EGP | H8: Invoice-to-order pricing
A9: C06 | B9: Invoices − credit notes − receipts = customer balances (sum of invoice balances) | C9: =SUM('Customer Invoices and Payments'!$I$4:$I$85)-SUMIFS('Customer and Supplier Returns'!$S$2:$S$12,'Customer and Supplier Returns'!$B$2:$B$12,"Customer return")-SUM('Customer Invoices and Payments'!$F$91:$F$152) -> 29532073 | D9: =SUM('Customer Invoices and Payments'!$M$4:$M$85) -> 29532073 | E9: =ROUND(C9-D9,2) -> 0 | F9: =IF(E9=0,"PASS","CHECK") -> PASS | G9: EGP | H9: Receivable roll-forward
A10: C07 | B10: Receivables per sub-ledger = receivable control account 120100 (ledger) | C10: =SUM('Customer Invoices and Payments'!$M$4:$M$85) -> 29532073 | D10: 29532073 | E10: =ROUND(C10-D10,2) -> 0 | F10: =IF(E10=0,"PASS","CHECK") -> PASS | G10: EGP | H10: Sub-ledger to GL
A11: C08 | B11: Vendor bills − debit notes − payments = payable balances | C11: =SUM('Vendor Bills and Payments'!$K$4:$K$31)-SUMIFS('Customer and Supplier Returns'!$S$2:$S$12,'Customer and Supplier Returns'!$B$2:$B$12,"Supplier return")-SUM('Vendor Bills and Payments'!$F$37:$F$54) -> 2662739 | D11: =SUM('Vendor Bills and Payments'!$O$4:$O$31) -> 2662739 | E11: =ROUND(C11-D11,2) -> 0 | F11: =IF(E11=0,"PASS","CHECK") -> PASS | G11: EGP | H11: Payable roll-forward
A12: C09 | B12: Payables per sub-ledger = payable control account 210100 (ledger, credit shown positive) | C12: =SUM('Vendor Bills and Payments'!$O$4:$O$31) -> 2662739 | D12: 2662739 | E12: =ROUND(C12-D12,2) -> 0 | F12: =IF(E12=0,"PASS","CHECK") -> PASS | G12: EGP | H12: Sub-ledger to GL
A13: C10 | B13: Output VAT on invoices − credit notes = VAT output account 220100 (credit shown positive) | C13: =SUM('Customer Invoices and Payments'!$H$4:$H$85)-SUMIFS('Customer and Supplier Returns'!$R$2:$R$12,'Customer and Supplier Returns'!$B$2:$B$12,"Customer return") -> 4232652.5 | D13: 4232652.5 | E13: =ROUND(C13-D13,2) -> 0 | F13: =IF(E13=0,"PASS","CHECK") -> PASS | G13: EGP | H13: Tax
A14: C11 | B14: Input VAT on bills − debit notes = VAT input account 140300 | C14: =SUM('Vendor Bills and Payments'!$J$4:$J$31)-SUMIFS('Customer and Supplier Returns'!$R$2:$R$12,'Customer and Supplier Returns'!$B$2:$B$12,"Supplier return") -> 3436752.8 | D14: 3436752.8 | E14: =ROUND(C14-D14,2) -> 0 | F14: =IF(E14=0,"PASS","CHECK") -> PASS | G14: EGP | H14: Tax
A15: C12 | B15: Credit limits: customers whose peak exposure exceeded their limit (count) | C15: =SUMPRODUCT(('Customer Master'!$M$2:$M$14>'Customer Master'!$I$2:$I$14)*('Customer Master'!$I$2:$I$14>0)) -> 0 | D15: 0 | E15: =ROUND(C15-D15,2) -> 0 | F15: =IF(E15=0,"PASS","CHECK") -> PASS | G15: Count | H15: Credit-limited customers only (cash retail excluded); limits set at 130% of simulated peak exposure, rounded up
A16: C13 | B16: Won CRM opportunities = non-retail sales orders (count) | C16: =COUNTIF('CRM Pipeline'!$H$4:$H$89,"Won") -> 62 | D16: =COUNTIF('Sales Orders'!$D$2:$D$88,"<>CUS-013") -> 62 | E16: =ROUND(C16-D16,2) -> 0 | F16: =IF(E16=0,"PASS","CHECK") -> PASS | G16: Count | H16: CRM-to-sales link; retail counter sales do not use the pipeline
A17: C14 | B17: Linked sales orders of won opportunities exist in Sales Orders (count) | C17: =SUMPRODUCT(COUNTIF('Sales Orders'!$A$2:$A$88,'CRM Pipeline'!$O$4:$O$89)) -> 62 | D17: =COUNTIF('CRM Pipeline'!$H$4:$H$89,"Won") -> 62 | E17: =ROUND(C17-D17,2) -> 0 | F17: =IF(E17=0,"PASS","CHECK") -> PASS | G17: Count | H17: Referential integrity
A20: Documents dated after the period end (not posted in the five-month records)
A21: Item | B21: Reference | C21: Document Date | D21: Amount incl. VAT (EGP) | E21: Treatment
A22: Customer invoice (delivered 2026-09-30) | B22: SO/2026/0081 | C22: 46296 | D22: 107433.6 | E22: Delivered within the period; invoice dated after period end - recorded as delivered-not-invoiced
A23: Customer invoice (delivered 2026-09-29) | B23: SO/2026/0084 | C23: 46299 | D23: 148297.13 | E23: Delivered within the period; invoice dated after period end - recorded as delivered-not-invoiced
A27: Ledger cross-checks (static values from the simulated journal model)
A28: Ledger measure | B28: Amount (EGP)
A29: Net sales (410100+410200+410300+420100) | B29: 30233232
A30: COGS (510100+510200+510300) | B30: 23902966
A31: Inventory shrinkage and count adjustments (540100) | B31: 6405
A32: Expired inventory loss (540200) | B32: 46000
A33: Damaged goods loss (540300) | B33: 55795
A34: Inventory at 30-Sep-2026 (130100+130200+130300) | B34: 24536323
A35: Goods received not invoiced (210500, credit shown positive) | B35: 0
A36: Stock interim delivered (130600) | B36: 170945
